{
  "law_id": "uqn_17073",
  "law_name": "نظام الأجهزة والمستلزمات الطبية",
  "title": "نظام الأجهزة والمستلزمات الطبية",
  "jurisdiction_ar": "السعودية",
  "doc_type": "official_text",
  "category": "regulation",
  "primary_source_id": "uqn",
  "status": "ساري",
  "issue_date_hijri": "1442/07/16",
  "issue_date_gregorian": "28/02/2021",
  "publish_date_hijri": "1442/07/16",
  "publish_date_gregorian": "28/02/2021",
  "issuing_authority": "لوائح وأنظمة",
  "links": [
    {
      "source_id": "uqn",
      "url": "https://www.uqn.gov.sa/details?p=17073",
      "label_ar": "جريدة أم القرى الرسمية"
    }
  ],
  "total_articles": 46,
  "articles": [
    {
      "number": 1,
      "number_text": "المادة الأولى",
      "text": "المادة الأولى: \nيقصد بالكلمات والعبارات الآتية –أينما وردت في هذا النظام– المعاني المبينة أمام كل منها، ما لم يقتض السياق غير ذلك:\nالنظام:\nنظام الأجهزة والمستلزمات الطبية.\nالهيئة:\nالهيئة العامة للغذاء والدواء.\nالمجلس:\nمجلس إدارة الهيئة.\nالرئيس:\nالرئيس التنفيذي للهيئة.\nاللائحة:\nاللائحة التنفيذية للنظام.\nالجهاز الطبي:\nكل آلة أو أداة أو جهاز تطبيق أو جهاز زراعة أو كواشف مخبرية أو مواد معايرة مخبرية أو برامج أو مواد تشغيل للأجهزة الطبية، أو أي أداة شبيهة أو ذات علاقة صنعت لوحدها أو مع أجهزة أخرى؛ تستخدم في تشخيص الأمراض أو الإصابات أو الوقاية منها أو مراقبتها أو التحكم فيها أو علاجها أو تخفيفها أو تسكينها أو التعويض عن الإصابات، وتستخدم كذلك في الفحص أو الإحلال أو التعديل أو الدعم التشريحي أو التأثير على وظائف أعضاء الجسم، ودعم أو تمكين الحياة (الوظائف الحيوية للإنسان) من الاستمرار، وتنظيم الحمل أو المساعدة عليه، وتعقيم الأجهزة والمستلزمات الطبية، وإعطاء المعلومات –لغرض طبي أو تشخيصي– المستخلصة من الفحوصات المخبرية للعينات المأخوذة من جسم الإنسان، وكذلك التي لا يمكن أن تحقق الغرض الذي صنعت من أجله في جسم الإنسان أو عليه بوساطة العقار الدوائي أو العامل المناعي أو التحولات الأيضية، وإنما تساعد في تحقيق مفاعيلها فقط.\nالمستلزم الطبي:\nالمواد والمنتجات الطبية، المستخدمة في التشخيص أو العلاج، أو الاستعاضة، أو التقويم، أو حالات الإعاقة، أو غيرها من الاستخدامات الطبية للإنسان بما في ذلك الغازات الطبية.\nملحقات الجهاز والمستلزم الطبي:\nأي مادة أو منتج يُصنع خاصاً باستخدامه مع جهاز أو مستلزم طبي لتمكينه من تحقيق الغرض الذي صنع من أجله.\nالجهاز والمستلزم الطبي المبتكر:\nجهاز أو مستلزم طبي ذو فكرة مبتكرة في التقنية أو الاستخدام أو الأداء ولم يسبق طرحها في الأسواق داخلياً أو خارجياً.\nالأجهزة والمستلزمات الطبية المجمعة:\nكل ما يجمع في طقم واحد لتحقيق متطلبات المستخدم، وقد تحتوي على أجهزة أو مستلزمات ليست طبية.\nالجهاز والمستلزم الطبي ذو الاستخدام مرة واحدة:\nكل ما يصنع لغرض الاستخدام خلال الإجراء الطبي الواحد على مريض مرة واحدة ثم يُتخلص منه.\nالمواد الطبية المشعة:\nمادة تنطلق منها إشعاعات مؤينة، سواءً منفردة بنفسها أو ضمن أجهزة أو مستلزمات طبية أخرى، تستخدم للتشخيص والعلاج.\nالأجهزة والمستلزمات الطبية المغشوشة:\nهي التي يتعمد تغيير هويتها أو مصدرها بقصد الخداع، ويعد الجهاز والمستلزم الطبي مغشوشاً إذا تغير محتواه بما يؤثر سلباً في مأمونيته وسلامته، أو كان معبأ في عبوات مزيفة.\nإعادة المعالجة:\nإجراءات تنفذ على الجهاز والمستلزم الطبي المستخدم سابقاً؛ لإعادة استخدامه بطريقة آمنة، ومن ذلك: التنظيف، والتطهير، والتعقيم، واختبار واستعادة الوظائف الفنية والسلامة المتعلقة به.\nالمستخدم:\nمن يستخدم الجهاز والمستلزم الطبي سواء كان متخصصاً أو عادياً أو مريضاً.\nالمنشأة:\nكيان نظامي يزاول نشاطاً يتعلق بالأجهزة والمستلزمات الطبية.\nالمصنع:\nأي منشأة وطنية أو أجنبية يكون من أغراضها تصميم الأجهزة أو المستلزمات الطبية أو تصنيعها لطرحها للاستخدام باسمها، سواء كانت داخل المملكة أو خارجها. ويشمل التصنيع: تجديدها، وتجميعها، وتعبئتها، وتغليفها، ووضع المعلومات التعريفية عليها.\nمقدم الرعاية الصحية:\nأي منشأة حكومية أو أهلية تقدم خدمات الرعاية الصحية.\nالممثل المعتمد:\nشخص ذو صفة اعتبارية مقره في المملكة مفوض كتابياً من مصنع مقيم في الخارج لتمثيله داخل المملكة، فيما يتصل بتطبيق أحكام النظام واللائحة.\nتداول الأجهزة والمستلزمات الطبية:\nتوفيرها مجاناً أو بمقابل سواء كان للتوزيع أو للاستخدام.\nالترخيص:\nوثيقة تصدرها الهيئة لمزاولة أي من الأنشطة الخاضعة للنظام.\nالسجل الوطني:\nالسجل الوطني للمنشآت والأجهزة والمستلزمات الطبية المنشأ في الهيئة.\nالتسجيل:\nإجراء تقيد بناءً عليه الأجهزة والمستلزمات الطبية والمنشآت، التي تزاول أي من الأنشطة الخاضعة للنظام، في السجل الوطني.\nالإذن بالتسويق:\nوثيقة تصدرها الهيئة لأي جهاز أو مستلزم طبي تسمح بتداوله في الأسواق.\nشهادة حرية البيع:\nوثيقة تصدرها الهيئة للمصنع تفيد بأن المصنع مسجل في المملكة وأن الأجهزة والمستلزمات الطبية المراد تصديرها حاصلة على الإذن بالتسويق.\nالتحقق من الدراسات السريرية:\nبحث تطبيقي يستخدم فيه جهاز أو مستلزم طبي على إنسان أو أكثر؛ لتقويم مأمونيته وكفايته عند استخدامه.\nنظام التصنيف:\nهو نظام تعتمده الهيئة يعمل على تقويم درجة الخطورة المتعلقة بالجهاز أو المستلزم الطبي، وتقويم مأمونيته.\nنظام إدارة الجودة:\nنظام تعتمده الهيئة للتحقق من جودة وفاعلية ومأمونية الجهاز أو المستلزم الطبي وفقاً للنسخة الحديثة من المواصفة الفنية (الآيزو 13485) أو ما يماثلها، وذلك وفقاً لما تبينه اللائحة.\nتوكيد الجودة:\nمجموعة من الاختبارات والقياسات والمعايرة الفنية تعتمدها الهيئة، للتأكد من مأمونية أجهزة الأشعة الطبية وسلامتها ودقة الصور وجودتها، بما يضمن فاعلية التشخيص والعلاج وكفايتهما.\nاللوائح الفنية:\nوثائق إلزامية تصدرها الهيئة خاصة بالأجهزة والمستلزمات الطبية تحدد مبادئ السلامة والأداء والتصنيع والتعليمات المنظمة لذلك، بما في ذلك: المصطلحات، والرموز، والتعبئة، ومتطلبات المعلومات التعريفية.\nالمواصفات القياسية:\nوثائق غير إلزامية تقرها الهيئة، تتضمن قواعد أو مبادئ توجيهية أو خصائص الأجهزة والمستلزمات الطبية أو عمليات وأساليب الإنتاج المرتبطة بها، بما فيها: المصطلحات، والرموز، والتعبئة، ومتطلبات المعلومات التعريفية.\nالمعلومات التعريفية:\nأي بيان أو معلومة مرسومة أو مصورة مكتوبة أو مطبوعة على الجهاز والمستلزم الطبي، وتشمل المعلومات الخاصة بالتعريف به، والوصف الفني له، وكيفية استخدامه، وطرق تخزينه ونقله.\nالمواصفات الفنية والإكلينيكية:\nمجموعة معايير تحدد جودة وفاعلية ومأمونية استخدام المادة المشعة في التطبيقات الطبية.\nإنذار السلامة:\nإشعار يصدره المركز يوضح الخطر المرتبط بالجهاز أو المستلزم الطبي والإجراءات التصحيحية المطلوب القيام بها؛ تلافياً للخطر المرتبط به.\nالإجراء التصحيحي لإنذار السلامة:\nإجراء يتخذه المصنع للحد من الأخطار التي تؤثر في مأمونية الجهاز أو المستلزم الطبي أو التقليل منها.\nحوادث الأجهزة والمستلزمات الطبية: أي قصور أو تغير في خصائص أو أداء الجهاز أو المستلزم الطبي مما قد يسبب أو يسهم بصورة مباشرة أو غير مباشرة في وفاة أو إصابة خطيرة للمستخدم.\nالمركز:\nالمركز الوطني لبلاغات الأجهزة والمستلزمات الطبية.",
      "original_text": "المادة الأولى: \nيقصد بالكلمات والعبارات الآتية –أينما وردت في هذا النظام– المعاني المبينة أمام كل منها، ما لم يقتض السياق غير ذلك:\nالنظام:\nنظام الأجهزة والمستلزمات الطبية.\nالهيئة:\nالهيئة العامة للغذاء والدواء.\nالمجلس:\nمجلس إدارة الهيئة.\nالرئيس:\nالرئيس التنفيذي للهيئة.\nاللائحة:\nاللائحة التنفيذية للنظام.\nالجهاز الطبي:\nكل آلة أو أداة أو جهاز تطبيق أو جهاز زراعة أو كواشف مخبرية أو مواد معايرة مخبرية أو برامج أو مواد تشغيل للأجهزة الطبية، أو أي أداة شبيهة أو ذات علاقة صنعت لوحدها أو مع أجهزة أخرى؛ تستخدم في تشخيص الأمراض أو الإصابات أو الوقاية منها أو مراقبتها أو التحكم فيها أو علاجها أو تخفيفها أو تسكينها أو التعويض عن الإصابات، وتستخدم كذلك في الفحص أو الإحلال أو التعديل أو الدعم التشريحي أو التأثير على وظائف أعضاء الجسم، ودعم أو تمكين الحياة (الوظائف الحيوية للإنسان) من الاستمرار، وتنظيم الحمل أو المساعدة عليه، وتعقيم الأجهزة والمستلزمات الطبية، وإعطاء المعلومات –لغرض طبي أو تشخيصي– المستخلصة من الفحوصات المخبرية للعينات المأخوذة من جسم الإنسان، وكذلك التي لا يمكن أن تحقق الغرض الذي صنعت من أجله في جسم الإنسان أو عليه بوساطة العقار الدوائي أو العامل المناعي أو التحولات الأيضية، وإنما تساعد في تحقيق مفاعيلها فقط.\nالمستلزم الطبي:\nالمواد والمنتجات الطبية، المستخدمة في التشخيص أو العلاج، أو الاستعاضة، أو التقويم، أو حالات الإعاقة، أو غيرها من الاستخدامات الطبية للإنسان بما في ذلك الغازات الطبية.\nملحقات الجهاز والمستلزم الطبي:\nأي مادة أو منتج يُصنع خاصاً باستخدامه مع جهاز أو مستلزم طبي لتمكينه من تحقيق الغرض الذي صنع من أجله.\nالجهاز والمستلزم الطبي المبتكر:\nجهاز أو مستلزم طبي ذو فكرة مبتكرة في التقنية أو الاستخدام أو الأداء ولم يسبق طرحها في الأسواق داخلياً أو خارجياً.\nالأجهزة والمستلزمات الطبية المجمعة:\nكل ما يجمع في طقم واحد لتحقيق متطلبات المستخدم، وقد تحتوي على أجهزة أو مستلزمات ليست طبية.\nالجهاز والمستلزم الطبي ذو الاستخدام مرة واحدة:\nكل ما يصنع لغرض الاستخدام خلال الإجراء الطبي الواحد على مريض مرة واحدة ثم يُتخلص منه.\nالمواد الطبية المشعة:\nمادة تنطلق منها إشعاعات مؤينة، سواءً منفردة بنفسها أو ضمن أجهزة أو مستلزمات طبية أخرى، تستخدم للتشخيص والعلاج.\nالأجهزة والمستلزمات الطبية المغشوشة:\nهي التي يتعمد تغيير هويتها أو مصدرها بقصد الخداع، ويعد الجهاز والمستلزم الطبي مغشوشاً إذا تغير محتواه بما يؤثر سلباً في مأمونيته وسلامته، أو كان معبأ في عبوات مزيفة.\nإعادة المعالجة:\nإجراءات تنفذ على الجهاز والمستلزم الطبي المستخدم سابقاً؛ لإعادة استخدامه بطريقة آمنة، ومن ذلك: التنظيف، والتطهير، والتعقيم، واختبار واستعادة الوظائف الفنية والسلامة المتعلقة به.\nالمستخدم:\nمن يستخدم الجهاز والمستلزم الطبي سواء كان متخصصاً أو عادياً أو مريضاً.\nالمنشأة:\nكيان نظامي يزاول نشاطاً يتعلق بالأجهزة والمستلزمات الطبية.\nالمصنع:\nأي منشأة وطنية أو أجنبية يكون من أغراضها تصميم الأجهزة أو المستلزمات الطبية أو تصنيعها لطرحها للاستخدام باسمها، سواء كانت داخل المملكة أو خارجها. ويشمل التصنيع: تجديدها، وتجميعها، وتعبئتها، وتغليفها، ووضع المعلومات التعريفية عليها.\nمقدم الرعاية الصحية:\nأي منشأة حكومية أو أهلية تقدم خدمات الرعاية الصحية.\nالممثل المعتمد:\nشخص ذو صفة اعتبارية مقره في المملكة مفوض كتابياً من مصنع مقيم في الخارج لتمثيله داخل المملكة، فيما يتصل بتطبيق أحكام النظام واللائحة.\nتداول الأجهزة والمستلزمات الطبية:\nتوفيرها مجاناً أو بمقابل سواء كان للتوزيع أو للاستخدام.\nالترخيص:\nوثيقة تصدرها الهيئة لمزاولة أي من الأنشطة الخاضعة للنظام.\nالسجل الوطني:\nالسجل الوطني للمنشآت والأجهزة والمستلزمات الطبية المنشأ في الهيئة.\nالتسجيل:\nإجراء تقيد بناءً عليه الأجهزة والمستلزمات الطبية والمنشآت، التي تزاول أي من الأنشطة الخاضعة للنظام، في السجل الوطني.\nالإذن بالتسويق:\nوثيقة تصدرها الهيئة لأي جهاز أو مستلزم طبي تسمح بتداوله في الأسواق.\nشهادة حرية البيع:\nوثيقة تصدرها الهيئة للمصنع تفيد بأن المصنع مسجل في المملكة وأن الأجهزة والمستلزمات الطبية المراد تصديرها حاصلة على الإذن بالتسويق.\nالتحقق من الدراسات السريرية:\nبحث تطبيقي يستخدم فيه جهاز أو مستلزم طبي على إنسان أو أكثر؛ لتقويم مأمونيته وكفايته عند استخدامه.\nنظام التصنيف:\nهو نظام تعتمده الهيئة يعمل على تقويم درجة الخطورة المتعلقة بالجهاز أو المستلزم الطبي، وتقويم مأمونيته.\nنظام إدارة الجودة:\nنظام تعتمده الهيئة للتحقق من جودة وفاعلية ومأمونية الجهاز أو المستلزم الطبي وفقاً للنسخة الحديثة من المواصفة الفنية (الآيزو 13485) أو ما يماثلها، وذلك وفقاً لما تبينه اللائحة.\nتوكيد الجودة:\nمجموعة من الاختبارات والقياسات والمعايرة الفنية تعتمدها الهيئة، للتأكد من مأمونية أجهزة الأشعة الطبية وسلامتها ودقة الصور وجودتها، بما يضمن فاعلية التشخيص والعلاج وكفايتهما.\nاللوائح الفنية:\nوثائق إلزامية تصدرها الهيئة خاصة بالأجهزة والمستلزمات الطبية تحدد مبادئ السلامة والأداء والتصنيع والتعليمات المنظمة لذلك، بما في ذلك: المصطلحات، والرموز، والتعبئة، ومتطلبات المعلومات التعريفية.\nالمواصفات القياسية:\nوثائق غير إلزامية تقرها الهيئة، تتضمن قواعد أو مبادئ توجيهية أو خصائص الأجهزة والمستلزمات الطبية أو عمليات وأساليب الإنتاج المرتبطة بها، بما فيها: المصطلحات، والرموز، والتعبئة، ومتطلبات المعلومات التعريفية.\nالمعلومات التعريفية:\nأي بيان أو معلومة مرسومة أو مصورة مكتوبة أو مطبوعة على الجهاز والمستلزم الطبي، وتشمل المعلومات الخاصة بالتعريف به، والوصف الفني له، وكيفية استخدامه، وطرق تخزينه ونقله.\nالمواصفات الفنية والإكلينيكية:\nمجموعة معايير تحدد جودة وفاعلية ومأمونية استخدام المادة المشعة في التطبيقات الطبية.\nإنذار السلامة:\nإشعار يصدره المركز يوضح الخطر المرتبط بالجهاز أو المستلزم الطبي والإجراءات التصحيحية المطلوب القيام بها؛ تلافياً للخطر المرتبط به.\nالإجراء التصحيحي لإنذار السلامة:\nإجراء يتخذه المصنع للحد من الأخطار التي تؤثر في مأمونية الجهاز أو المستلزم الطبي أو التقليل منها.\nحوادث الأجهزة والمستلزمات الطبية: أي قصور أو تغير في خصائص أو أداء الجهاز أو المستلزم الطبي مما قد يسبب أو يسهم بصورة مباشرة أو غير مباشرة في وفاة أو إصابة خطيرة للمستخدم.\nالمركز:\nالمركز الوطني لبلاغات الأجهزة والمستلزمات الطبية.",
      "status": "active",
      "paragraphs": [
        {
          "marker": "",
          "text": "المادة الأولى:",
          "level": 0
        },
        {
          "marker": "",
          "text": "يقصد بالكلمات والعبارات الآتية –أينما وردت في هذا النظام– المعاني المبينة أمام كل منها، ما لم يقتض السياق غير ذلك:",
          "level": 0
        },
        {
          "marker": "",
          "text": "النظام:",
          "level": 0
        },
        {
          "marker": "",
          "text": "نظام الأجهزة والمستلزمات الطبية.",
          "level": 0
        },
        {
          "marker": "",
          "text": "الهيئة:",
          "level": 0
        },
        {
          "marker": "",
          "text": "الهيئة العامة للغذاء والدواء.",
          "level": 0
        },
        {
          "marker": "",
          "text": "المجلس:",
          "level": 0
        },
        {
          "marker": "",
          "text": "مجلس إدارة الهيئة.",
          "level": 0
        },
        {
          "marker": "",
          "text": "الرئيس:",
          "level": 0
        },
        {
          "marker": "",
          "text": "الرئيس التنفيذي للهيئة.",
          "level": 0
        },
        {
          "marker": "",
          "text": "اللائحة:",
          "level": 0
        },
        {
          "marker": "",
          "text": "اللائحة التنفيذية للنظام.",
          "level": 0
        },
        {
          "marker": "",
          "text": "الجهاز الطبي:",
          "level": 0
        },
        {
          "marker": "",
          "text": "كل آلة أو أداة أو جهاز تطبيق أو جهاز زراعة أو كواشف مخبرية أو مواد معايرة مخبرية أو برامج أو مواد تشغيل للأجهزة الطبية، أو أي أداة شبيهة أو ذات علاقة صنعت لوحدها أو مع أجهزة أخرى؛ تستخدم في تشخيص الأمراض أو الإصابات أو الوقاية منها أو مراقبتها أو التحكم فيها أو علاجها أو تخفيفها أو تسكينها أو التعويض عن الإصابات، وتستخدم كذلك في الفحص أو الإحلال أو التعديل أو الدعم التشريحي أو التأثير على وظائف أعضاء الجسم، ودعم أو تمكين الحياة (الوظائف الحيوية للإنسان) من الاستمرار، وتنظيم الحمل أو المساعدة عليه، وتعقيم الأجهزة والمستلزمات الطبية، وإعطاء المعلومات –لغرض طبي أو تشخيصي– المستخلصة من الفحوصات المخبرية للعينات المأخوذة من جسم الإنسان، وكذلك التي لا يمكن أن تحقق الغرض الذي صنعت من أجله في جسم الإنسان أو عليه بوساطة العقار الدوائي أو العامل المناعي أو التحولات الأيضية، وإنما تساعد في تحقيق مفاعيلها فقط.",
          "level": 0
        },
        {
          "marker": "",
          "text": "المستلزم الطبي:",
          "level": 0
        },
        {
          "marker": "",
          "text": "المواد والمنتجات الطبية، المستخدمة في التشخيص أو العلاج، أو الاستعاضة، أو التقويم، أو حالات الإعاقة، أو غيرها من الاستخدامات الطبية للإنسان بما في ذلك الغازات الطبية.",
          "level": 0
        },
        {
          "marker": "",
          "text": "ملحقات الجهاز والمستلزم الطبي:",
          "level": 0
        },
        {
          "marker": "",
          "text": "أي مادة أو منتج يُصنع خاصاً باستخدامه مع جهاز أو مستلزم طبي لتمكينه من تحقيق الغرض الذي صنع من أجله.",
          "level": 0
        },
        {
          "marker": "",
          "text": "الجهاز والمستلزم الطبي المبتكر:",
          "level": 0
        },
        {
          "marker": "",
          "text": "جهاز أو مستلزم طبي ذو فكرة مبتكرة في التقنية أو الاستخدام أو الأداء ولم يسبق طرحها في الأسواق داخلياً أو خارجياً.",
          "level": 0
        },
        {
          "marker": "",
          "text": "الأجهزة والمستلزمات الطبية المجمعة:",
          "level": 0
        },
        {
          "marker": "",
          "text": "كل ما يجمع في طقم واحد لتحقيق متطلبات المستخدم، وقد تحتوي على أجهزة أو مستلزمات ليست طبية.",
          "level": 0
        },
        {
          "marker": "",
          "text": "الجهاز والمستلزم الطبي ذو الاستخدام مرة واحدة:",
          "level": 0
        },
        {
          "marker": "",
          "text": "كل ما يصنع لغرض الاستخدام خلال الإجراء الطبي الواحد على مريض مرة واحدة ثم يُتخلص منه.",
          "level": 0
        },
        {
          "marker": "",
          "text": "المواد الطبية المشعة:",
          "level": 0
        },
        {
          "marker": "",
          "text": "مادة تنطلق منها إشعاعات مؤينة، سواءً منفردة بنفسها أو ضمن أجهزة أو مستلزمات طبية أخرى، تستخدم للتشخيص والعلاج.",
          "level": 0
        },
        {
          "marker": "",
          "text": "الأجهزة والمستلزمات الطبية المغشوشة:",
          "level": 0
        },
        {
          "marker": "",
          "text": "هي التي يتعمد تغيير هويتها أو مصدرها بقصد الخداع، ويعد الجهاز والمستلزم الطبي مغشوشاً إذا تغير محتواه بما يؤثر سلباً في مأمونيته وسلامته، أو كان معبأ في عبوات مزيفة.",
          "level": 0
        },
        {
          "marker": "",
          "text": "إعادة المعالجة:",
          "level": 0
        },
        {
          "marker": "",
          "text": "إجراءات تنفذ على الجهاز والمستلزم الطبي المستخدم سابقاً؛ لإعادة استخدامه بطريقة آمنة، ومن ذلك: التنظيف، والتطهير، والتعقيم، واختبار واستعادة الوظائف الفنية والسلامة المتعلقة به.",
          "level": 0
        },
        {
          "marker": "",
          "text": "المستخدم:",
          "level": 0
        },
        {
          "marker": "",
          "text": "من يستخدم الجهاز والمستلزم الطبي سواء كان متخصصاً أو عادياً أو مريضاً.",
          "level": 0
        },
        {
          "marker": "",
          "text": "المنشأة:",
          "level": 0
        },
        {
          "marker": "",
          "text": "كيان نظامي يزاول نشاطاً يتعلق بالأجهزة والمستلزمات الطبية.",
          "level": 0
        },
        {
          "marker": "",
          "text": "المصنع:",
          "level": 0
        },
        {
          "marker": "",
          "text": "أي منشأة وطنية أو أجنبية يكون من أغراضها تصميم الأجهزة أو المستلزمات الطبية أو تصنيعها لطرحها للاستخدام باسمها، سواء كانت داخل المملكة أو خارجها. ويشمل التصنيع: تجديدها، وتجميعها، وتعبئتها، وتغليفها، ووضع المعلومات التعريفية عليها.",
          "level": 0
        },
        {
          "marker": "",
          "text": "مقدم الرعاية الصحية:",
          "level": 0
        },
        {
          "marker": "",
          "text": "أي منشأة حكومية أو أهلية تقدم خدمات الرعاية الصحية.",
          "level": 0
        },
        {
          "marker": "",
          "text": "الممثل المعتمد:",
          "level": 0
        },
        {
          "marker": "",
          "text": "شخص ذو صفة اعتبارية مقره في المملكة مفوض كتابياً من مصنع مقيم في الخارج لتمثيله داخل المملكة، فيما يتصل بتطبيق أحكام النظام واللائحة.",
          "level": 0
        },
        {
          "marker": "",
          "text": "تداول الأجهزة والمستلزمات الطبية:",
          "level": 0
        },
        {
          "marker": "",
          "text": "توفيرها مجاناً أو بمقابل سواء كان للتوزيع أو للاستخدام.",
          "level": 0
        },
        {
          "marker": "",
          "text": "الترخيص:",
          "level": 0
        },
        {
          "marker": "",
          "text": "وثيقة تصدرها الهيئة لمزاولة أي من الأنشطة الخاضعة للنظام.",
          "level": 0
        },
        {
          "marker": "",
          "text": "السجل الوطني:",
          "level": 0
        },
        {
          "marker": "",
          "text": "السجل الوطني للمنشآت والأجهزة والمستلزمات الطبية المنشأ في الهيئة.",
          "level": 0
        },
        {
          "marker": "",
          "text": "التسجيل:",
          "level": 0
        },
        {
          "marker": "",
          "text": "إجراء تقيد بناءً عليه الأجهزة والمستلزمات الطبية والمنشآت، التي تزاول أي من الأنشطة الخاضعة للنظام، في السجل الوطني.",
          "level": 0
        },
        {
          "marker": "",
          "text": "الإذن بالتسويق:",
          "level": 0
        },
        {
          "marker": "",
          "text": "وثيقة تصدرها الهيئة لأي جهاز أو مستلزم طبي تسمح بتداوله في الأسواق.",
          "level": 0
        },
        {
          "marker": "",
          "text": "شهادة حرية البيع:",
          "level": 0
        },
        {
          "marker": "",
          "text": "وثيقة تصدرها الهيئة للمصنع تفيد بأن المصنع مسجل في المملكة وأن الأجهزة والمستلزمات الطبية المراد تصديرها حاصلة على الإذن بالتسويق.",
          "level": 0
        },
        {
          "marker": "",
          "text": "التحقق من الدراسات السريرية:",
          "level": 0
        },
        {
          "marker": "",
          "text": "بحث تطبيقي يستخدم فيه جهاز أو مستلزم طبي على إنسان أو أكثر؛ لتقويم مأمونيته وكفايته عند استخدامه.",
          "level": 0
        },
        {
          "marker": "",
          "text": "نظام التصنيف:",
          "level": 0
        },
        {
          "marker": "",
          "text": "هو نظام تعتمده الهيئة يعمل على تقويم درجة الخطورة المتعلقة بالجهاز أو المستلزم الطبي، وتقويم مأمونيته.",
          "level": 0
        },
        {
          "marker": "",
          "text": "نظام إدارة الجودة:",
          "level": 0
        },
        {
          "marker": "",
          "text": "نظام تعتمده الهيئة للتحقق من جودة وفاعلية ومأمونية الجهاز أو المستلزم الطبي وفقاً للنسخة الحديثة من المواصفة الفنية (الآيزو 13485) أو ما يماثلها، وذلك وفقاً لما تبينه اللائحة.",
          "level": 0
        },
        {
          "marker": "",
          "text": "توكيد الجودة:",
          "level": 0
        },
        {
          "marker": "",
          "text": "مجموعة من الاختبارات والقياسات والمعايرة الفنية تعتمدها الهيئة، للتأكد من مأمونية أجهزة الأشعة الطبية وسلامتها ودقة الصور وجودتها، بما يضمن فاعلية التشخيص والعلاج وكفايتهما.",
          "level": 0
        },
        {
          "marker": "",
          "text": "اللوائح الفنية:",
          "level": 0
        },
        {
          "marker": "",
          "text": "وثائق إلزامية تصدرها الهيئة خاصة بالأجهزة والمستلزمات الطبية تحدد مبادئ السلامة والأداء والتصنيع والتعليمات المنظمة لذلك، بما في ذلك: المصطلحات، والرموز، والتعبئة، ومتطلبات المعلومات التعريفية.",
          "level": 0
        },
        {
          "marker": "",
          "text": "المواصفات القياسية:",
          "level": 0
        },
        {
          "marker": "",
          "text": "وثائق غير إلزامية تقرها الهيئة، تتضمن قواعد أو مبادئ توجيهية أو خصائص الأجهزة والمستلزمات الطبية أو عمليات وأساليب الإنتاج المرتبطة بها، بما فيها: المصطلحات، والرموز، والتعبئة، ومتطلبات المعلومات التعريفية.",
          "level": 0
        },
        {
          "marker": "",
          "text": "المعلومات التعريفية:",
          "level": 0
        },
        {
          "marker": "",
          "text": "أي بيان أو معلومة مرسومة أو مصورة مكتوبة أو مطبوعة على الجهاز والمستلزم الطبي، وتشمل المعلومات الخاصة بالتعريف به، والوصف الفني له، وكيفية استخدامه، وطرق تخزينه ونقله.",
          "level": 0
        },
        {
          "marker": "",
          "text": "المواصفات الفنية والإكلينيكية:",
          "level": 0
        },
        {
          "marker": "",
          "text": "مجموعة معايير تحدد جودة وفاعلية ومأمونية استخدام المادة المشعة في التطبيقات الطبية.",
          "level": 0
        },
        {
          "marker": "",
          "text": "إنذار السلامة:",
          "level": 0
        },
        {
          "marker": "",
          "text": "إشعار يصدره المركز يوضح الخطر المرتبط بالجهاز أو المستلزم الطبي والإجراءات التصحيحية المطلوب القيام بها؛ تلافياً للخطر المرتبط به.",
          "level": 0
        },
        {
          "marker": "",
          "text": "الإجراء التصحيحي لإنذار السلامة:",
          "level": 0
        },
        {
          "marker": "",
          "text": "إجراء يتخذه المصنع للحد من الأخطار التي تؤثر في مأمونية الجهاز أو المستلزم الطبي أو التقليل منها.",
          "level": 0
        },
        {
          "marker": "",
          "text": "حوادث الأجهزة والمستلزمات الطبية: أي قصور أو تغير في خصائص أو أداء الجهاز أو المستلزم الطبي مما قد يسبب أو يسهم بصورة مباشرة أو غير مباشرة في وفاة أو إصابة خطيرة للمستخدم.",
          "level": 0
        },
        {
          "marker": "",
          "text": "المركز:",
          "level": 0
        },
        {
          "marker": "",
          "text": "المركز الوطني لبلاغات الأجهزة والمستلزمات الطبية.",
          "level": 0
        }
      ],
      "amendments": [],
      "heading_context": []
    },
    {
      "number": 2,
      "number_text": "المادة الثانية",
      "text": "المادة الثانية: \nتخضع لأحكام النظام الأنشطة الآتية:\n1- تصميم الأجهزة والمستلزمات الطبية، وتصنيعها.\n2- استيراد الأجهزة والمستلزمات الطبية، وتسويقها، وتوزيعها، وتخزينها.\n3- تقديم خدمات التحقق من مطابقة الأجهزة والمستلزمات الطبية للوائح الفنية ونظام إدارة الجودة، والتحقق من توكيد الجودة.\n4- إجراء التحقق من الدراسات السريرية.\n5- تقديم الخدمات الاستشارية الفنية في مجال الأجهزة والمستلزمات الطبية.\n6- تقديم خدمات فحص الأجهزة والمستلزمات الطبية للتأكد من مطابقتها للوائح الفنية والمواصفات القياسية.\n7- تقديم خدمات الصيانة للأجهزة والمستلزمات الطبية.\n8- تمثيل المصنع المقيم خارج المملكة.",
      "original_text": "المادة الثانية: \nتخضع لأحكام النظام الأنشطة الآتية:\n1- تصميم الأجهزة والمستلزمات الطبية، وتصنيعها.\n2- استيراد الأجهزة والمستلزمات الطبية، وتسويقها، وتوزيعها، وتخزينها.\n3- تقديم خدمات التحقق من مطابقة الأجهزة والمستلزمات الطبية للوائح الفنية ونظام إدارة الجودة، والتحقق من توكيد الجودة.\n4- إجراء التحقق من الدراسات السريرية.\n5- تقديم الخدمات الاستشارية الفنية في مجال الأجهزة والمستلزمات الطبية.\n6- تقديم خدمات فحص الأجهزة والمستلزمات الطبية للتأكد من مطابقتها للوائح الفنية والمواصفات القياسية.\n7- تقديم خدمات الصيانة للأجهزة والمستلزمات الطبية.\n8- تمثيل المصنع المقيم خارج المملكة.",
      "status": "active",
      "paragraphs": [
        {
          "marker": "",
          "text": "المادة الثانية:",
          "level": 0
        },
        {
          "marker": "",
          "text": "تخضع لأحكام النظام الأنشطة الآتية:",
          "level": 0
        },
        {
          "marker": "1-",
          "text": "تصميم الأجهزة والمستلزمات الطبية، وتصنيعها.",
          "level": 1
        },
        {
          "marker": "2-",
          "text": "استيراد الأجهزة والمستلزمات الطبية، وتسويقها، وتوزيعها، وتخزينها.",
          "level": 1
        },
        {
          "marker": "3-",
          "text": "تقديم خدمات التحقق من مطابقة الأجهزة والمستلزمات الطبية للوائح الفنية ونظام إدارة الجودة، والتحقق من توكيد الجودة.",
          "level": 1
        },
        {
          "marker": "4-",
          "text": "إجراء التحقق من الدراسات السريرية.",
          "level": 1
        },
        {
          "marker": "5-",
          "text": "تقديم الخدمات الاستشارية الفنية في مجال الأجهزة والمستلزمات الطبية.",
          "level": 1
        },
        {
          "marker": "6-",
          "text": "تقديم خدمات فحص الأجهزة والمستلزمات الطبية للتأكد من مطابقتها للوائح الفنية والمواصفات القياسية.",
          "level": 1
        },
        {
          "marker": "7-",
          "text": "تقديم خدمات الصيانة للأجهزة والمستلزمات الطبية.",
          "level": 1
        },
        {
          "marker": "8-",
          "text": "تمثيل المصنع المقيم خارج المملكة.",
          "level": 1
        }
      ],
      "amendments": [],
      "heading_context": []
    },
    {
      "number": 3,
      "number_text": "المادة الثالثة",
      "text": "المادة الثالثة: \nتعد في حكم الأجهزة والمستلزمات الطبية الخاضعة لأحكام النظام: ملحقاتها، والأجهزة والمستلزمات الطبية المجمعة.",
      "original_text": "المادة الثالثة: \nتعد في حكم الأجهزة والمستلزمات الطبية الخاضعة لأحكام النظام: ملحقاتها، والأجهزة والمستلزمات الطبية المجمعة.",
      "status": "active",
      "paragraphs": [
        {
          "marker": "",
          "text": "المادة الثالثة:",
          "level": 0
        },
        {
          "marker": "",
          "text": "تعد في حكم الأجهزة والمستلزمات الطبية الخاضعة لأحكام النظام: ملحقاتها، والأجهزة والمستلزمات الطبية المجمعة.",
          "level": 0
        }
      ],
      "amendments": [],
      "heading_context": []
    },
    {
      "number": 4,
      "number_text": "المادة الرابعة",
      "text": "المادة الرابعة: \nمع مراعاة اختصاصات هيئة الرقابة النووية والإشعاعية بإصدار التراخيص اللازمة لممارسة الأنشطة المتعلقة باستخدام المواد الطبية المشعة؛ يشترط موافقة الهيئة على المواصفات الفنية والإكلينيكية لتلك المواد قبل ترخيصها من هيئة الرقابة النووية والإشعاعية.",
      "original_text": "المادة الرابعة: \nمع مراعاة اختصاصات هيئة الرقابة النووية والإشعاعية بإصدار التراخيص اللازمة لممارسة الأنشطة المتعلقة باستخدام المواد الطبية المشعة؛ يشترط موافقة الهيئة على المواصفات الفنية والإكلينيكية لتلك المواد قبل ترخيصها من هيئة الرقابة النووية والإشعاعية.",
      "status": "active",
      "paragraphs": [
        {
          "marker": "",
          "text": "المادة الرابعة:",
          "level": 0
        },
        {
          "marker": "",
          "text": "مع مراعاة اختصاصات هيئة الرقابة النووية والإشعاعية بإصدار التراخيص اللازمة لممارسة الأنشطة المتعلقة باستخدام المواد الطبية المشعة؛ يشترط موافقة الهيئة على المواصفات الفنية والإكلينيكية لتلك المواد قبل ترخيصها من هيئة الرقابة النووية والإشعاعية.",
          "level": 0
        }
      ],
      "amendments": [],
      "heading_context": []
    },
    {
      "number": 5,
      "number_text": "المادة الخامسة",
      "text": "المادة الخامسة: \nلا يخل تطبيق أحكام النظام، باختصاصات هيئة الرقابة النووية والإشعاعية فيما يتعلق بإصدار ترخيص الحماية من الإشعاع المؤين الصادر من الأجهزة الطبية.",
      "original_text": "المادة الخامسة: \nلا يخل تطبيق أحكام النظام، باختصاصات هيئة الرقابة النووية والإشعاعية فيما يتعلق بإصدار ترخيص الحماية من الإشعاع المؤين الصادر من الأجهزة الطبية.",
      "status": "active",
      "paragraphs": [
        {
          "marker": "",
          "text": "المادة الخامسة:",
          "level": 0
        },
        {
          "marker": "",
          "text": "لا يخل تطبيق أحكام النظام، باختصاصات هيئة الرقابة النووية والإشعاعية فيما يتعلق بإصدار ترخيص الحماية من الإشعاع المؤين الصادر من الأجهزة الطبية.",
          "level": 0
        }
      ],
      "amendments": [],
      "heading_context": []
    },
    {
      "number": 6,
      "number_text": "المادة السادسة",
      "text": "المادة السادسة: \nمع مراعاة ما ورد في المادة (الرابعة) من النظام؛ لا يجوز لأي منشأة ممارسة أي من الأنشطة الخاضعة للنظام؛ إلا بعد التسجيل، والحصول على الترخيص، إضافة إلى الحصول على الترخيص الصناعي من الجهة المختصة بالنسبة إلى المصانع.",
      "original_text": "المادة السادسة: \nمع مراعاة ما ورد في المادة (الرابعة) من النظام؛ لا يجوز لأي منشأة ممارسة أي من الأنشطة الخاضعة للنظام؛ إلا بعد التسجيل، والحصول على الترخيص، إضافة إلى الحصول على الترخيص الصناعي من الجهة المختصة بالنسبة إلى المصانع.",
      "status": "active",
      "paragraphs": [
        {
          "marker": "",
          "text": "المادة السادسة:",
          "level": 0
        },
        {
          "marker": "",
          "text": "مع مراعاة ما ورد في المادة (الرابعة) من النظام؛ لا يجوز لأي منشأة ممارسة أي من الأنشطة الخاضعة للنظام؛ إلا بعد التسجيل، والحصول على الترخيص، إضافة إلى الحصول على الترخيص الصناعي من الجهة المختصة بالنسبة إلى المصانع.",
          "level": 0
        }
      ],
      "amendments": [],
      "heading_context": []
    },
    {
      "number": 7,
      "number_text": "المادة السابعة",
      "text": "المادة السابعة: \nعلى المرخص له بإجراء التحقق من الدراسات السريرية؛ الحصول على موافقة الهيئة قبل البدء في أي من عمليات التحقق، وفقاً لما تحدده اللائحة.",
      "original_text": "المادة السابعة: \nعلى المرخص له بإجراء التحقق من الدراسات السريرية؛ الحصول على موافقة الهيئة قبل البدء في أي من عمليات التحقق، وفقاً لما تحدده اللائحة.",
      "status": "active",
      "paragraphs": [
        {
          "marker": "",
          "text": "المادة السابعة:",
          "level": 0
        },
        {
          "marker": "",
          "text": "على المرخص له بإجراء التحقق من الدراسات السريرية؛ الحصول على موافقة الهيئة قبل البدء في أي من عمليات التحقق، وفقاً لما تحدده اللائحة.",
          "level": 0
        }
      ],
      "amendments": [],
      "heading_context": []
    },
    {
      "number": 8,
      "number_text": "المادة الثامنة",
      "text": "المادة الثامنة: \nلا يجوز تداول أي جهاز أو مستلزم طبي إلا بعد التسجيل، والحصول على الإذن بالتسويق. وللهيئة استثناء بعض الأجهزة والمستلزمات الطبية من شرط الحصول على الإذن بالتسويق، بعد التأكد من سلامتها، وعدم استخدامها لأغراض تجارية؛ وذلك وفق قواعد يقرها المجلس.",
      "original_text": "المادة الثامنة: \nلا يجوز تداول أي جهاز أو مستلزم طبي إلا بعد التسجيل، والحصول على الإذن بالتسويق. وللهيئة استثناء بعض الأجهزة والمستلزمات الطبية من شرط الحصول على الإذن بالتسويق، بعد التأكد من سلامتها، وعدم استخدامها لأغراض تجارية؛ وذلك وفق قواعد يقرها المجلس.",
      "status": "active",
      "paragraphs": [
        {
          "marker": "",
          "text": "المادة الثامنة:",
          "level": 0
        },
        {
          "marker": "",
          "text": "لا يجوز تداول أي جهاز أو مستلزم طبي إلا بعد التسجيل، والحصول على الإذن بالتسويق. وللهيئة استثناء بعض الأجهزة والمستلزمات الطبية من شرط الحصول على الإذن بالتسويق، بعد التأكد من سلامتها، وعدم استخدامها لأغراض تجارية؛ وذلك وفق قواعد يقرها المجلس.",
          "level": 0
        }
      ],
      "amendments": [],
      "heading_context": []
    },
    {
      "number": 9,
      "number_text": "المادة التاسعة",
      "text": "المادة التاسعة: \nللهيئة استثناء الجهاز أو المستلزم الطبي المبتكر من بعض الشروط والإجراءات اللازمة للحصول على الإذن بالتسويق؛ بما لا يؤثر في مأمونيته وسلامته عند استخدامه، وذلك وفقاً لما تحدده اللائحة.",
      "original_text": "المادة التاسعة: \nللهيئة استثناء الجهاز أو المستلزم الطبي المبتكر من بعض الشروط والإجراءات اللازمة للحصول على الإذن بالتسويق؛ بما لا يؤثر في مأمونيته وسلامته عند استخدامه، وذلك وفقاً لما تحدده اللائحة.",
      "status": "active",
      "paragraphs": [
        {
          "marker": "",
          "text": "المادة التاسعة:",
          "level": 0
        },
        {
          "marker": "",
          "text": "للهيئة استثناء الجهاز أو المستلزم الطبي المبتكر من بعض الشروط والإجراءات اللازمة للحصول على الإذن بالتسويق؛ بما لا يؤثر في مأمونيته وسلامته عند استخدامه، وذلك وفقاً لما تحدده اللائحة.",
          "level": 0
        }
      ],
      "amendments": [],
      "heading_context": []
    },
    {
      "number": 10,
      "number_text": "المادة العاشرة",
      "text": "المادة العاشرة: \nتحدد اللائحة الشروط والإجراءات اللازمة للتسجيل، وإصدار الإذن بالتسويق، والحصول على الترخيص وتجديده وتعديله ونقله وإلغائه.",
      "original_text": "المادة العاشرة: \nتحدد اللائحة الشروط والإجراءات اللازمة للتسجيل، وإصدار الإذن بالتسويق، والحصول على الترخيص وتجديده وتعديله ونقله وإلغائه.",
      "status": "active",
      "paragraphs": [
        {
          "marker": "",
          "text": "المادة العاشرة:",
          "level": 0
        },
        {
          "marker": "",
          "text": "تحدد اللائحة الشروط والإجراءات اللازمة للتسجيل، وإصدار الإذن بالتسويق، والحصول على الترخيص وتجديده وتعديله ونقله وإلغائه.",
          "level": 0
        }
      ],
      "amendments": [],
      "heading_context": []
    },
    {
      "number": 11,
      "number_text": "المادة الحادية عشرة",
      "text": "المادة الحادية عشرة: \nلا يجوز فسح الأجهزة والمستلزمات الطبية المستوردة إلا بعد موافقة الهيئة.",
      "original_text": "المادة الحادية عشرة: \nلا يجوز فسح الأجهزة والمستلزمات الطبية المستوردة إلا بعد موافقة الهيئة.",
      "status": "active",
      "paragraphs": [
        {
          "marker": "",
          "text": "المادة الحادية عشرة:",
          "level": 0
        },
        {
          "marker": "",
          "text": "لا يجوز فسح الأجهزة والمستلزمات الطبية المستوردة إلا بعد موافقة الهيئة.",
          "level": 0
        }
      ],
      "amendments": [],
      "heading_context": []
    },
    {
      "number": 12,
      "number_text": "المادة الثانية عشرة",
      "text": "المادة الثانية  عشرة:\nتحدد اللائحة الشروط اللازمة لإصدار شهادة حرية البيع.",
      "original_text": "المادة الثانية  عشرة:\nتحدد اللائحة الشروط اللازمة لإصدار شهادة حرية البيع.",
      "status": "active",
      "paragraphs": [
        {
          "marker": "",
          "text": "المادة الثانية  عشرة:",
          "level": 0
        },
        {
          "marker": "",
          "text": "تحدد اللائحة الشروط اللازمة لإصدار شهادة حرية البيع.",
          "level": 0
        }
      ],
      "amendments": [],
      "heading_context": []
    },
    {
      "number": 13,
      "number_text": "المادة الثالثة عشرة",
      "text": "المادة الثالثة  عشرة:\nللهيئة السماح بدخول الأجهزة والمستلزمات الطبية ذات الاستخدام الشخصي؛ بناءً على تقرير طبي وبكميات محدودة، على ألا تُستخدم لأي غرض تجاري.",
      "original_text": "المادة الثالثة  عشرة:\nللهيئة السماح بدخول الأجهزة والمستلزمات الطبية ذات الاستخدام الشخصي؛ بناءً على تقرير طبي وبكميات محدودة، على ألا تُستخدم لأي غرض تجاري.",
      "status": "active",
      "paragraphs": [
        {
          "marker": "",
          "text": "المادة الثالثة  عشرة:",
          "level": 0
        },
        {
          "marker": "",
          "text": "للهيئة السماح بدخول الأجهزة والمستلزمات الطبية ذات الاستخدام الشخصي؛ بناءً على تقرير طبي وبكميات محدودة، على ألا تُستخدم لأي غرض تجاري.",
          "level": 0
        }
      ],
      "amendments": [],
      "heading_context": []
    },
    {
      "number": 14,
      "number_text": "المادة الرابعة عشرة",
      "text": "المادة الرابعة  عشرة:\nعلى كل من صرف أو باع جهازاً أو مستلزماً طبياً مغشوشاً، أو غير مسجل، أو غير حاصل على الإذن بالتسويق، إبلاغ الهيئة –فور علمه بذلك– بالمعلومات التي تتعلق بما صُرف أو بِيع وكميته، واسم من صُرِف أو بِيع له الجهاز أو المستلزم الطبي وعنوانه، ويلتزم بإعادة الثمن للمشتري.",
      "original_text": "المادة الرابعة  عشرة:\nعلى كل من صرف أو باع جهازاً أو مستلزماً طبياً مغشوشاً، أو غير مسجل، أو غير حاصل على الإذن بالتسويق، إبلاغ الهيئة –فور علمه بذلك– بالمعلومات التي تتعلق بما صُرف أو بِيع وكميته، واسم من صُرِف أو بِيع له الجهاز أو المستلزم الطبي وعنوانه، ويلتزم بإعادة الثمن للمشتري.",
      "status": "active",
      "paragraphs": [
        {
          "marker": "",
          "text": "المادة الرابعة  عشرة:",
          "level": 0
        },
        {
          "marker": "",
          "text": "على كل من صرف أو باع جهازاً أو مستلزماً طبياً مغشوشاً، أو غير مسجل، أو غير حاصل على الإذن بالتسويق، إبلاغ الهيئة –فور علمه بذلك– بالمعلومات التي تتعلق بما صُرف أو بِيع وكميته، واسم من صُرِف أو بِيع له الجهاز أو المستلزم الطبي وعنوانه، ويلتزم بإعادة الثمن للمشتري.",
          "level": 0
        }
      ],
      "amendments": [],
      "heading_context": []
    },
    {
      "number": 15,
      "number_text": "المادة الخامسة عشرة",
      "text": "المادة الخامسة  عشرة:\nمع مراعاة الأحكام الواردة في نظام الوكالات التجارية؛ يتعين على المصنع المقيم خارج المملكة –عند رغبته في تداول منتجاته في المملكة– تعيين ممثل معتمد له. وتحدد اللائحة الشروط اللازم توافرها في الممثل المعتمد، وكذلك التزامات الطرفين ومسؤولياتهما.",
      "original_text": "المادة الخامسة  عشرة:\nمع مراعاة الأحكام الواردة في نظام الوكالات التجارية؛ يتعين على المصنع المقيم خارج المملكة –عند رغبته في تداول منتجاته في المملكة– تعيين ممثل معتمد له. وتحدد اللائحة الشروط اللازم توافرها في الممثل المعتمد، وكذلك التزامات الطرفين ومسؤولياتهما.",
      "status": "active",
      "paragraphs": [
        {
          "marker": "",
          "text": "المادة الخامسة  عشرة:",
          "level": 0
        },
        {
          "marker": "",
          "text": "مع مراعاة الأحكام الواردة في نظام الوكالات التجارية؛ يتعين على المصنع المقيم خارج المملكة –عند رغبته في تداول منتجاته في المملكة– تعيين ممثل معتمد له. وتحدد اللائحة الشروط اللازم توافرها في الممثل المعتمد، وكذلك التزامات الطرفين ومسؤولياتهما.",
          "level": 0
        }
      ],
      "amendments": [],
      "heading_context": []
    },
    {
      "number": 16,
      "number_text": "المادة السادسة عشرة",
      "text": "المادة السادسة  عشرة:\nعلى المصنع توفير خدمات ما بعد البيع للأجهزة والمستلزمات الطبية التابعة له، وتطبق في هذا الشأن الأحكام المنصوص عليها في النظام واللائحة.",
      "original_text": "المادة السادسة  عشرة:\nعلى المصنع توفير خدمات ما بعد البيع للأجهزة والمستلزمات الطبية التابعة له، وتطبق في هذا الشأن الأحكام المنصوص عليها في النظام واللائحة.",
      "status": "active",
      "paragraphs": [
        {
          "marker": "",
          "text": "المادة السادسة  عشرة:",
          "level": 0
        },
        {
          "marker": "",
          "text": "على المصنع توفير خدمات ما بعد البيع للأجهزة والمستلزمات الطبية التابعة له، وتطبق في هذا الشأن الأحكام المنصوص عليها في النظام واللائحة.",
          "level": 0
        }
      ],
      "amendments": [],
      "heading_context": []
    },
    {
      "number": 17,
      "number_text": "المادة السابعة عشرة",
      "text": "المادة السابعة  عشرة:\nعلى المنشآت الالتزام بالمعلومات التعريفية الواجب توافرها على الأجهزة والمستلزمات الطبية، وتحدد اللائحة تلك المعلومات.",
      "original_text": "المادة السابعة  عشرة:\nعلى المنشآت الالتزام بالمعلومات التعريفية الواجب توافرها على الأجهزة والمستلزمات الطبية، وتحدد اللائحة تلك المعلومات.",
      "status": "active",
      "paragraphs": [
        {
          "marker": "",
          "text": "المادة السابعة  عشرة:",
          "level": 0
        },
        {
          "marker": "",
          "text": "على المنشآت الالتزام بالمعلومات التعريفية الواجب توافرها على الأجهزة والمستلزمات الطبية، وتحدد اللائحة تلك المعلومات.",
          "level": 0
        }
      ],
      "amendments": [],
      "heading_context": []
    },
    {
      "number": 18,
      "number_text": "المادة الثامنة عشرة",
      "text": "المادة الثامنة  عشرة:\nيلتزم مقدم الرعاية الصحية بألا يتعامل مع أي منشأة تزاول أياً من الأنشطة الخاضعة للنظام؛ ما لم تكن مسجلة وحاصلة على ترخيص في مجال التعامل نفسه.",
      "original_text": "المادة الثامنة  عشرة:\nيلتزم مقدم الرعاية الصحية بألا يتعامل مع أي منشأة تزاول أياً من الأنشطة الخاضعة للنظام؛ ما لم تكن مسجلة وحاصلة على ترخيص في مجال التعامل نفسه.",
      "status": "active",
      "paragraphs": [
        {
          "marker": "",
          "text": "المادة الثامنة  عشرة:",
          "level": 0
        },
        {
          "marker": "",
          "text": "يلتزم مقدم الرعاية الصحية بألا يتعامل مع أي منشأة تزاول أياً من الأنشطة الخاضعة للنظام؛ ما لم تكن مسجلة وحاصلة على ترخيص في مجال التعامل نفسه.",
          "level": 0
        }
      ],
      "amendments": [],
      "heading_context": []
    },
    {
      "number": 19,
      "number_text": "المادة التاسعة عشرة",
      "text": "المادة التاسعة  عشرة:\nلا تجوز إعادة معالجة الأجهزة أو المستلزمات الطبية ذات الاستخدام مرة واحدة.",
      "original_text": "المادة التاسعة  عشرة:\nلا تجوز إعادة معالجة الأجهزة أو المستلزمات الطبية ذات الاستخدام مرة واحدة.",
      "status": "active",
      "paragraphs": [
        {
          "marker": "",
          "text": "المادة التاسعة  عشرة:",
          "level": 0
        },
        {
          "marker": "",
          "text": "لا تجوز إعادة معالجة الأجهزة أو المستلزمات الطبية ذات الاستخدام مرة واحدة.",
          "level": 0
        }
      ],
      "amendments": [],
      "heading_context": []
    },
    {
      "number": 20,
      "number_text": "المادة العشرون",
      "text": "المادة العشرون: \nلا يجوز إتلاف الأجهزة أو المستلزمات الطبية المستخدمة، ولا إعادة معالجتها، ولا تجديدها، ولا إعادة بيعها، ولا إعارتها، ولا التبرع بها؛ إلا وفقاً للشروط التي تحددها اللائحة.",
      "original_text": "المادة العشرون: \nلا يجوز إتلاف الأجهزة أو المستلزمات الطبية المستخدمة، ولا إعادة معالجتها، ولا تجديدها، ولا إعادة بيعها، ولا إعارتها، ولا التبرع بها؛ إلا وفقاً للشروط التي تحددها اللائحة.",
      "status": "active",
      "paragraphs": [
        {
          "marker": "",
          "text": "المادة العشرون:",
          "level": 0
        },
        {
          "marker": "",
          "text": "لا يجوز إتلاف الأجهزة أو المستلزمات الطبية المستخدمة، ولا إعادة معالجتها، ولا تجديدها، ولا إعادة بيعها، ولا إعارتها، ولا التبرع بها؛ إلا وفقاً للشروط التي تحددها اللائحة.",
          "level": 0
        }
      ],
      "amendments": [],
      "heading_context": []
    },
    {
      "number": 21,
      "number_text": "المادة 21",
      "text": "المادة الحادية والعشرون: \nيلتزم المصنع بتصنيف الأجهزة والمستلزمات الطبية وفقاً لنظام التصنيف.",
      "original_text": "المادة الحادية والعشرون: \nيلتزم المصنع بتصنيف الأجهزة والمستلزمات الطبية وفقاً لنظام التصنيف.",
      "status": "active",
      "paragraphs": [
        {
          "marker": "",
          "text": "المادة الحادية والعشرون:",
          "level": 0
        },
        {
          "marker": "",
          "text": "يلتزم المصنع بتصنيف الأجهزة والمستلزمات الطبية وفقاً لنظام التصنيف.",
          "level": 0
        }
      ],
      "amendments": [],
      "heading_context": []
    },
    {
      "number": 22,
      "number_text": "المادة 22",
      "text": "المادة الثانية  والعشرون:\nعلى المنشآت الراغبة في تداول الأجهزة أو المستلزمات الطبية في المملكة الالتزام بتطبيق نظام إدارة الجودة.",
      "original_text": "المادة الثانية  والعشرون:\nعلى المنشآت الراغبة في تداول الأجهزة أو المستلزمات الطبية في المملكة الالتزام بتطبيق نظام إدارة الجودة.",
      "status": "active",
      "paragraphs": [
        {
          "marker": "",
          "text": "المادة الثانية  والعشرون:",
          "level": 0
        },
        {
          "marker": "",
          "text": "على المنشآت الراغبة في تداول الأجهزة أو المستلزمات الطبية في المملكة الالتزام بتطبيق نظام إدارة الجودة.",
          "level": 0
        }
      ],
      "amendments": [],
      "heading_context": []
    },
    {
      "number": 23,
      "number_text": "المادة 23",
      "text": "المادة الثالثة  والعشرون:\nلا يجوز صرف الأجهزة أو المستلزمات الطبية المصنفة عالية الخطورة –وفقاً لنظام التصنيف– للاستخدام خارج منشأة مقدم الرعاية الصحية؛ دون وصفة طبية. وتصدر الهيئة قائمة بتلك الأجهزة والمستلزمات الطبية.",
      "original_text": "المادة الثالثة  والعشرون:\nلا يجوز صرف الأجهزة أو المستلزمات الطبية المصنفة عالية الخطورة –وفقاً لنظام التصنيف– للاستخدام خارج منشأة مقدم الرعاية الصحية؛ دون وصفة طبية. وتصدر الهيئة قائمة بتلك الأجهزة والمستلزمات الطبية.",
      "status": "active",
      "paragraphs": [
        {
          "marker": "",
          "text": "المادة الثالثة  والعشرون:",
          "level": 0
        },
        {
          "marker": "",
          "text": "لا يجوز صرف الأجهزة أو المستلزمات الطبية المصنفة عالية الخطورة –وفقاً لنظام التصنيف– للاستخدام خارج منشأة مقدم الرعاية الصحية؛ دون وصفة طبية. وتصدر الهيئة قائمة بتلك الأجهزة والمستلزمات الطبية.",
          "level": 0
        }
      ],
      "amendments": [],
      "heading_context": []
    },
    {
      "number": 24,
      "number_text": "المادة 24",
      "text": "المادة الرابعة  والعشرون:\nلا تجوز الدعاية للأجهزة أو المستلزمات الطبية ولا الإعلان عنها ولا الترويج لها، إلا بعد موافقة الهيئة ووفقاً للشروط التي تحددها اللائحة.",
      "original_text": "المادة الرابعة  والعشرون:\nلا تجوز الدعاية للأجهزة أو المستلزمات الطبية ولا الإعلان عنها ولا الترويج لها، إلا بعد موافقة الهيئة ووفقاً للشروط التي تحددها اللائحة.",
      "status": "active",
      "paragraphs": [
        {
          "marker": "",
          "text": "المادة الرابعة  والعشرون:",
          "level": 0
        },
        {
          "marker": "",
          "text": "لا تجوز الدعاية للأجهزة أو المستلزمات الطبية ولا الإعلان عنها ولا الترويج لها، إلا بعد موافقة الهيئة ووفقاً للشروط التي تحددها اللائحة.",
          "level": 0
        }
      ],
      "amendments": [],
      "heading_context": []
    },
    {
      "number": 25,
      "number_text": "المادة 25",
      "text": "المادة الخامسة  والعشرون:\nلا تجوز إقامة حملات توعية أو حملات خيرية أو ما في حكمهما متعلقة بالأجهزة والمستلزمات الطبية، إلا بعد موافقة الهيئة ووفقاً للشروط التي تحددها اللائحة.",
      "original_text": "المادة الخامسة  والعشرون:\nلا تجوز إقامة حملات توعية أو حملات خيرية أو ما في حكمهما متعلقة بالأجهزة والمستلزمات الطبية، إلا بعد موافقة الهيئة ووفقاً للشروط التي تحددها اللائحة.",
      "status": "active",
      "paragraphs": [
        {
          "marker": "",
          "text": "المادة الخامسة  والعشرون:",
          "level": 0
        },
        {
          "marker": "",
          "text": "لا تجوز إقامة حملات توعية أو حملات خيرية أو ما في حكمهما متعلقة بالأجهزة والمستلزمات الطبية، إلا بعد موافقة الهيئة ووفقاً للشروط التي تحددها اللائحة.",
          "level": 0
        }
      ],
      "amendments": [],
      "heading_context": []
    },
    {
      "number": 26,
      "number_text": "المادة 26",
      "text": "المادة السادسة  والعشرون:\nتراقب الهيئة التزام مقدمي الرعاية الصحية بتطبيق اللوائح الفنية داخل مرافق الرعاية الصحية، للتأكد من سلامة الأجهزة والمستلزمات الطبية ومأمونيتها وكفايتها في التشخيص والعلاج.",
      "original_text": "المادة السادسة  والعشرون:\nتراقب الهيئة التزام مقدمي الرعاية الصحية بتطبيق اللوائح الفنية داخل مرافق الرعاية الصحية، للتأكد من سلامة الأجهزة والمستلزمات الطبية ومأمونيتها وكفايتها في التشخيص والعلاج.",
      "status": "active",
      "paragraphs": [
        {
          "marker": "",
          "text": "المادة السادسة  والعشرون:",
          "level": 0
        },
        {
          "marker": "",
          "text": "تراقب الهيئة التزام مقدمي الرعاية الصحية بتطبيق اللوائح الفنية داخل مرافق الرعاية الصحية، للتأكد من سلامة الأجهزة والمستلزمات الطبية ومأمونيتها وكفايتها في التشخيص والعلاج.",
          "level": 0
        }
      ],
      "amendments": [],
      "heading_context": []
    },
    {
      "number": 27,
      "number_text": "المادة 27",
      "text": "المادة السابعة  والعشرون:\nعلى المنشأة والممثل المعتمد تزويد الهيئة بكل وثيقة أو معلومة تطلبها للقيام باختصاصاتها المنصوص عليها في النظام واللائحة.",
      "original_text": "المادة السابعة  والعشرون:\nعلى المنشأة والممثل المعتمد تزويد الهيئة بكل وثيقة أو معلومة تطلبها للقيام باختصاصاتها المنصوص عليها في النظام واللائحة.",
      "status": "active",
      "paragraphs": [
        {
          "marker": "",
          "text": "المادة السابعة  والعشرون:",
          "level": 0
        },
        {
          "marker": "",
          "text": "على المنشأة والممثل المعتمد تزويد الهيئة بكل وثيقة أو معلومة تطلبها للقيام باختصاصاتها المنصوص عليها في النظام واللائحة.",
          "level": 0
        }
      ],
      "amendments": [],
      "heading_context": []
    },
    {
      "number": 28,
      "number_text": "المادة 28",
      "text": "المادة الثامنة  والعشرون:\nعلى المصنع والممثل المعتمد ومقدم الرعاية الصحية الالتزام بإبلاغ المركز عن حوادث الأجهزة والمستلزمات الطبية التابعة لهم.",
      "original_text": "المادة الثامنة  والعشرون:\nعلى المصنع والممثل المعتمد ومقدم الرعاية الصحية الالتزام بإبلاغ المركز عن حوادث الأجهزة والمستلزمات الطبية التابعة لهم.",
      "status": "active",
      "paragraphs": [
        {
          "marker": "",
          "text": "المادة الثامنة  والعشرون:",
          "level": 0
        },
        {
          "marker": "",
          "text": "على المصنع والممثل المعتمد ومقدم الرعاية الصحية الالتزام بإبلاغ المركز عن حوادث الأجهزة والمستلزمات الطبية التابعة لهم.",
          "level": 0
        }
      ],
      "amendments": [],
      "heading_context": []
    },
    {
      "number": 29,
      "number_text": "المادة 29",
      "text": "المادة التاسعة  والعشرون:\nيصدر المركز إنذار السلامة لتنبيه المستخدم ومقدم الرعاية الصحية بالأخطار الناتجة من استخدام الأجهزة والمستلزمات الطبية.",
      "original_text": "المادة التاسعة  والعشرون:\nيصدر المركز إنذار السلامة لتنبيه المستخدم ومقدم الرعاية الصحية بالأخطار الناتجة من استخدام الأجهزة والمستلزمات الطبية.",
      "status": "active",
      "paragraphs": [
        {
          "marker": "",
          "text": "المادة التاسعة  والعشرون:",
          "level": 0
        },
        {
          "marker": "",
          "text": "يصدر المركز إنذار السلامة لتنبيه المستخدم ومقدم الرعاية الصحية بالأخطار الناتجة من استخدام الأجهزة والمستلزمات الطبية.",
          "level": 0
        }
      ],
      "amendments": [],
      "heading_context": []
    },
    {
      "number": 30,
      "number_text": "المادة 30",
      "text": "المادة الثلاثون: \nيلتزم المصنع والممثل المعتمد بإبلاغ المركز فيما يتصل بالأجهزة والمستلزمات الطبية التابعة لهما عن الآتي:\n1- إنذارات السلامة الصادرة من الجهات الرقابية المماثلة خارج المملكة.\n2- الأخطار التي تؤثر في مأمونية الجهاز أو المستلزم الطبي.\n3- الانتهاء من الإجراء التصحيحي لإنذار السلامة.\nالمادة الحادية والثلاثون:\nعلى المنشأة ومقدم الرعاية الصحية في حال صدور إنذار السلامة إيقاف تداول الأجهزة والمستلزمات الطبية، حتى صدور إشعار من المركز بالانتهاء من الإجراء التصحيحي لإنذار السلامة.",
      "original_text": "المادة الثلاثون: \nيلتزم المصنع والممثل المعتمد بإبلاغ المركز فيما يتصل بالأجهزة والمستلزمات الطبية التابعة لهما عن الآتي:\n1- إنذارات السلامة الصادرة من الجهات الرقابية المماثلة خارج المملكة.\n2- الأخطار التي تؤثر في مأمونية الجهاز أو المستلزم الطبي.\n3- الانتهاء من الإجراء التصحيحي لإنذار السلامة.\nالمادة الحادية والثلاثون:\nعلى المنشأة ومقدم الرعاية الصحية في حال صدور إنذار السلامة إيقاف تداول الأجهزة والمستلزمات الطبية، حتى صدور إشعار من المركز بالانتهاء من الإجراء التصحيحي لإنذار السلامة.",
      "status": "active",
      "paragraphs": [
        {
          "marker": "",
          "text": "المادة الثلاثون:",
          "level": 0
        },
        {
          "marker": "",
          "text": "يلتزم المصنع والممثل المعتمد بإبلاغ المركز فيما يتصل بالأجهزة والمستلزمات الطبية التابعة لهما عن الآتي:",
          "level": 0
        },
        {
          "marker": "1-",
          "text": "إنذارات السلامة الصادرة من الجهات الرقابية المماثلة خارج المملكة.",
          "level": 1
        },
        {
          "marker": "2-",
          "text": "الأخطار التي تؤثر في مأمونية الجهاز أو المستلزم الطبي.",
          "level": 1
        },
        {
          "marker": "3-",
          "text": "الانتهاء من الإجراء التصحيحي لإنذار السلامة.",
          "level": 1
        },
        {
          "marker": "",
          "text": "المادة الحادية والثلاثون:",
          "level": 0
        },
        {
          "marker": "",
          "text": "على المنشأة ومقدم الرعاية الصحية في حال صدور إنذار السلامة إيقاف تداول الأجهزة والمستلزمات الطبية، حتى صدور إشعار من المركز بالانتهاء من الإجراء التصحيحي لإنذار السلامة.",
          "level": 0
        }
      ],
      "amendments": [],
      "heading_context": []
    },
    {
      "number": 31,
      "number_text": "المادة 31",
      "text": "المادة الثانية  والثلاثون:\nعلى المنشأة والممثل المعتمد الاستجابة لطلب الهيئة في اقتفاء أثر الأجهزة والمستلزمات الطبية. وتحدد اللائحة الإجراءات المتعلقة بذلك.",
      "original_text": "المادة الثانية  والثلاثون:\nعلى المنشأة والممثل المعتمد الاستجابة لطلب الهيئة في اقتفاء أثر الأجهزة والمستلزمات الطبية. وتحدد اللائحة الإجراءات المتعلقة بذلك.",
      "status": "active",
      "paragraphs": [
        {
          "marker": "",
          "text": "المادة الثانية  والثلاثون:",
          "level": 0
        },
        {
          "marker": "",
          "text": "على المنشأة والممثل المعتمد الاستجابة لطلب الهيئة في اقتفاء أثر الأجهزة والمستلزمات الطبية. وتحدد اللائحة الإجراءات المتعلقة بذلك.",
          "level": 0
        }
      ],
      "amendments": [],
      "heading_context": []
    },
    {
      "number": 32,
      "number_text": "المادة 32",
      "text": "المادة الثالثة  والثلاثون:\nتتولى الهيئة التفتيش على المنشآت وعلى الأجهزة والمستلزمات الطبية؛ للتأكد من تطبيق أحكام النظام واللائحة واللوائح الفنية، وذلك من خلال مفتشين يعدون من رجال الضبط الجنائي يصدر بتسميتهم قرار من رئيس المجلس، ويكون لهم ما يأتي:\n1- ضبط الأجهزة والمستلزمات الطبية المخالفة لأحكام النظام.\n2- التعامل مع المضبوطات المخالفة، وذلك وفقاً لما يأتي:\nأ- التحفظ عليها وعلى المستندات المتعلقة بها، عند الاقتضاء.\nب- أخذ العينات للتحليل.\nج- التوصية بإتلاف ما يثبت غشه، أو ضرره.\nويكون الإتلاف بعد صدور قرار به من الهيئة، وذلك وفقاً للأصول الفنية المتعارف عليها، وتتولى تنفيذه لجنة –أو أكثر- تكوَّن لهذا الغرض بقرار من رئيس المجلس. ويتحمل المخالف تكاليف عملية الإتلاف.",
      "original_text": "المادة الثالثة  والثلاثون:\nتتولى الهيئة التفتيش على المنشآت وعلى الأجهزة والمستلزمات الطبية؛ للتأكد من تطبيق أحكام النظام واللائحة واللوائح الفنية، وذلك من خلال مفتشين يعدون من رجال الضبط الجنائي يصدر بتسميتهم قرار من رئيس المجلس، ويكون لهم ما يأتي:\n1- ضبط الأجهزة والمستلزمات الطبية المخالفة لأحكام النظام.\n2- التعامل مع المضبوطات المخالفة، وذلك وفقاً لما يأتي:\nأ- التحفظ عليها وعلى المستندات المتعلقة بها، عند الاقتضاء.\nب- أخذ العينات للتحليل.\nج- التوصية بإتلاف ما يثبت غشه، أو ضرره.\nويكون الإتلاف بعد صدور قرار به من الهيئة، وذلك وفقاً للأصول الفنية المتعارف عليها، وتتولى تنفيذه لجنة –أو أكثر- تكوَّن لهذا الغرض بقرار من رئيس المجلس. ويتحمل المخالف تكاليف عملية الإتلاف.",
      "status": "active",
      "paragraphs": [
        {
          "marker": "",
          "text": "المادة الثالثة  والثلاثون:",
          "level": 0
        },
        {
          "marker": "",
          "text": "تتولى الهيئة التفتيش على المنشآت وعلى الأجهزة والمستلزمات الطبية؛ للتأكد من تطبيق أحكام النظام واللائحة واللوائح الفنية، وذلك من خلال مفتشين يعدون من رجال الضبط الجنائي يصدر بتسميتهم قرار من رئيس المجلس، ويكون لهم ما يأتي:",
          "level": 0
        },
        {
          "marker": "1-",
          "text": "ضبط الأجهزة والمستلزمات الطبية المخالفة لأحكام النظام.",
          "level": 1
        },
        {
          "marker": "2-",
          "text": "التعامل مع المضبوطات المخالفة، وذلك وفقاً لما يأتي:",
          "level": 1
        },
        {
          "marker": "أ-",
          "text": "التحفظ عليها وعلى المستندات المتعلقة بها، عند الاقتضاء.",
          "level": 1
        },
        {
          "marker": "ب-",
          "text": "أخذ العينات للتحليل.",
          "level": 1
        },
        {
          "marker": "ج-",
          "text": "التوصية بإتلاف ما يثبت غشه، أو ضرره.",
          "level": 1
        },
        {
          "marker": "",
          "text": "ويكون الإتلاف بعد صدور قرار به من الهيئة، وذلك وفقاً للأصول الفنية المتعارف عليها، وتتولى تنفيذه لجنة –أو أكثر- تكوَّن لهذا الغرض بقرار من رئيس المجلس. ويتحمل المخالف تكاليف عملية الإتلاف.",
          "level": 0
        }
      ],
      "amendments": [],
      "heading_context": []
    },
    {
      "number": 33,
      "number_text": "المادة 33",
      "text": "المادة الرابعة  والثلاثون:\nيلتزم كل من يخضع لأحكام النظام بالمحافظة على سرية المعلومات التي قد يحصل عليها بحكم مهمته.",
      "original_text": "المادة الرابعة  والثلاثون:\nيلتزم كل من يخضع لأحكام النظام بالمحافظة على سرية المعلومات التي قد يحصل عليها بحكم مهمته.",
      "status": "active",
      "paragraphs": [
        {
          "marker": "",
          "text": "المادة الرابعة  والثلاثون:",
          "level": 0
        },
        {
          "marker": "",
          "text": "يلتزم كل من يخضع لأحكام النظام بالمحافظة على سرية المعلومات التي قد يحصل عليها بحكم مهمته.",
          "level": 0
        }
      ],
      "amendments": [],
      "heading_context": []
    },
    {
      "number": 34,
      "number_text": "المادة 34",
      "text": "المادة الخامسة  والثلاثون:\nعلى المفتش إبراز بطاقته الوظيفية عند تأديته لأعمال التفتيش والضبط، وعلى المنشأة تمكينه من أداء عمله، وعدم إعاقته.",
      "original_text": "المادة الخامسة  والثلاثون:\nعلى المفتش إبراز بطاقته الوظيفية عند تأديته لأعمال التفتيش والضبط، وعلى المنشأة تمكينه من أداء عمله، وعدم إعاقته.",
      "status": "active",
      "paragraphs": [
        {
          "marker": "",
          "text": "المادة الخامسة  والثلاثون:",
          "level": 0
        },
        {
          "marker": "",
          "text": "على المفتش إبراز بطاقته الوظيفية عند تأديته لأعمال التفتيش والضبط، وعلى المنشأة تمكينه من أداء عمله، وعدم إعاقته.",
          "level": 0
        }
      ],
      "amendments": [],
      "heading_context": []
    },
    {
      "number": 35,
      "number_text": "المادة 35",
      "text": "المادة السادسة  والثلاثون:\nيجوز-بقرار من الرئيس– منح مفتشي الهيئة مكافآت مالية نظير ما يقدمونه من أعمال.",
      "original_text": "المادة السادسة  والثلاثون:\nيجوز-بقرار من الرئيس– منح مفتشي الهيئة مكافآت مالية نظير ما يقدمونه من أعمال.",
      "status": "active",
      "paragraphs": [
        {
          "marker": "",
          "text": "المادة السادسة  والثلاثون:",
          "level": 0
        },
        {
          "marker": "",
          "text": "يجوز-بقرار من الرئيس– منح مفتشي الهيئة مكافآت مالية نظير ما يقدمونه من أعمال.",
          "level": 0
        }
      ],
      "amendments": [],
      "heading_context": []
    },
    {
      "number": 36,
      "number_text": "المادة 36",
      "text": "المادة السابعة  والثلاثون:\nيجوز –بقرار من الرئيس– منح مكافأة تشجيعية بنسبة لا تزيد على (25%) من مقدار الغرامة المستحقة، لمن يساعد –من غير مفتشي الهيئة– في الكشف عن مخالفة لأحكام النظام واللائحة.",
      "original_text": "المادة السابعة  والثلاثون:\nيجوز –بقرار من الرئيس– منح مكافأة تشجيعية بنسبة لا تزيد على (25%) من مقدار الغرامة المستحقة، لمن يساعد –من غير مفتشي الهيئة– في الكشف عن مخالفة لأحكام النظام واللائحة.",
      "status": "active",
      "paragraphs": [
        {
          "marker": "",
          "text": "المادة السابعة  والثلاثون:",
          "level": 0
        },
        {
          "marker": "",
          "text": "يجوز –بقرار من الرئيس– منح مكافأة تشجيعية بنسبة لا تزيد على (25%) من مقدار الغرامة المستحقة، لمن يساعد –من غير مفتشي الهيئة– في الكشف عن مخالفة لأحكام النظام واللائحة.",
          "level": 0
        }
      ],
      "amendments": [],
      "heading_context": []
    },
    {
      "number": 37,
      "number_text": "المادة 37",
      "text": "المادة الثامنة  والثلاثون:\nتضع الهيئة بالاتفاق مع وزارة المالية الضوابط المنظمة لمنح المكافآت المشار إليها في المادتين (السادسة والثلاثين) و(السابعة والثلاثين) من النظام.",
      "original_text": "المادة الثامنة  والثلاثون:\nتضع الهيئة بالاتفاق مع وزارة المالية الضوابط المنظمة لمنح المكافآت المشار إليها في المادتين (السادسة والثلاثين) و(السابعة والثلاثين) من النظام.",
      "status": "active",
      "paragraphs": [
        {
          "marker": "",
          "text": "المادة الثامنة  والثلاثون:",
          "level": 0
        },
        {
          "marker": "",
          "text": "تضع الهيئة بالاتفاق مع وزارة المالية الضوابط المنظمة لمنح المكافآت المشار إليها في المادتين (السادسة والثلاثين) و(السابعة والثلاثين) من النظام.",
          "level": 0
        }
      ],
      "amendments": [],
      "heading_context": []
    },
    {
      "number": 38,
      "number_text": "المادة 38",
      "text": "المادة التاسعة  والثلاثون:\nللهيئة اتخاذ التدابير الاحترازية اللازمة في حال الاعتقاد بوجود ضرر أو ادعاء مضلل أو تأثير على سلامة الأجهزة والمستلزمات الطبية ومأمونيتها وكفايتها، وفقاً لما تحدده اللائحة.\nالمادة الأربعون:\nلا يجوز تداول الأجهزة والمستلزمات الطبية إذا قررت الهيئة سحبها من السوق أو حظر تداولها.\nالمادة الحادية والأربعون:\nيعد مخالفاً لأحكام النظام كل مَن:\n1- غش أو شرع في غش أي جهاز أو مستلزم طبي.\n2- باع، أو صرف، أو حاز بقصد الاتجار أجهزة أو مستلزمات طبية مغشوشة مع علمه بذلك.\n3- أدخل إلى المملكة جهازاً أو مستلزماً طبياً غير مسجل، أو مغشوشاً، أو غير حاصل على إذن تسويق، أو حاول إدخال أيٍٍّ من ذلك.\n4- صنع جهازاً أو مستلزماً طبياً بالمخالفة لأي حكم من أحكام النظام واللائحة واللوائح الفنية.\n5- استعمل للترويج للأجهزة والمستلزمات الطبية معلومات غير حقيقية، سواءً عليها، أو في الدعاية لها.\n6- نقل أو خزن جهازاً أو مستلزماً طبياً بالمخالفة لشروط النقل والتخزين التي تحددها الهيئة.\n7- أدخل إلى المملكة عبوات أو أغلفة لجهاز أو مستلزم طبي بقصد الغش، أو حاول إدخال أي من ذلك.\n8- صنع أو طبع أو حاز أو باع أو عرض عبوات أو أغلفة لجهاز أو مستلزم طبي بقصد الغش.\n9- ارتكب أي مخالفة أخرى لأحكام النظام.",
      "original_text": "المادة التاسعة  والثلاثون:\nللهيئة اتخاذ التدابير الاحترازية اللازمة في حال الاعتقاد بوجود ضرر أو ادعاء مضلل أو تأثير على سلامة الأجهزة والمستلزمات الطبية ومأمونيتها وكفايتها، وفقاً لما تحدده اللائحة.\nالمادة الأربعون:\nلا يجوز تداول الأجهزة والمستلزمات الطبية إذا قررت الهيئة سحبها من السوق أو حظر تداولها.\nالمادة الحادية والأربعون:\nيعد مخالفاً لأحكام النظام كل مَن:\n1- غش أو شرع في غش أي جهاز أو مستلزم طبي.\n2- باع، أو صرف، أو حاز بقصد الاتجار أجهزة أو مستلزمات طبية مغشوشة مع علمه بذلك.\n3- أدخل إلى المملكة جهازاً أو مستلزماً طبياً غير مسجل، أو مغشوشاً، أو غير حاصل على إذن تسويق، أو حاول إدخال أيٍٍّ من ذلك.\n4- صنع جهازاً أو مستلزماً طبياً بالمخالفة لأي حكم من أحكام النظام واللائحة واللوائح الفنية.\n5- استعمل للترويج للأجهزة والمستلزمات الطبية معلومات غير حقيقية، سواءً عليها، أو في الدعاية لها.\n6- نقل أو خزن جهازاً أو مستلزماً طبياً بالمخالفة لشروط النقل والتخزين التي تحددها الهيئة.\n7- أدخل إلى المملكة عبوات أو أغلفة لجهاز أو مستلزم طبي بقصد الغش، أو حاول إدخال أي من ذلك.\n8- صنع أو طبع أو حاز أو باع أو عرض عبوات أو أغلفة لجهاز أو مستلزم طبي بقصد الغش.\n9- ارتكب أي مخالفة أخرى لأحكام النظام.",
      "status": "active",
      "paragraphs": [
        {
          "marker": "",
          "text": "المادة التاسعة  والثلاثون:",
          "level": 0
        },
        {
          "marker": "",
          "text": "للهيئة اتخاذ التدابير الاحترازية اللازمة في حال الاعتقاد بوجود ضرر أو ادعاء مضلل أو تأثير على سلامة الأجهزة والمستلزمات الطبية ومأمونيتها وكفايتها، وفقاً لما تحدده اللائحة.",
          "level": 0
        },
        {
          "marker": "",
          "text": "المادة الأربعون:",
          "level": 0
        },
        {
          "marker": "",
          "text": "لا يجوز تداول الأجهزة والمستلزمات الطبية إذا قررت الهيئة سحبها من السوق أو حظر تداولها.",
          "level": 0
        },
        {
          "marker": "",
          "text": "المادة الحادية والأربعون:",
          "level": 0
        },
        {
          "marker": "",
          "text": "يعد مخالفاً لأحكام النظام كل مَن:",
          "level": 0
        },
        {
          "marker": "1-",
          "text": "غش أو شرع في غش أي جهاز أو مستلزم طبي.",
          "level": 1
        },
        {
          "marker": "2-",
          "text": "باع، أو صرف، أو حاز بقصد الاتجار أجهزة أو مستلزمات طبية مغشوشة مع علمه بذلك.",
          "level": 1
        },
        {
          "marker": "3-",
          "text": "أدخل إلى المملكة جهازاً أو مستلزماً طبياً غير مسجل، أو مغشوشاً، أو غير حاصل على إذن تسويق، أو حاول إدخال أيٍٍّ من ذلك.",
          "level": 1
        },
        {
          "marker": "4-",
          "text": "صنع جهازاً أو مستلزماً طبياً بالمخالفة لأي حكم من أحكام النظام واللائحة واللوائح الفنية.",
          "level": 1
        },
        {
          "marker": "5-",
          "text": "استعمل للترويج للأجهزة والمستلزمات الطبية معلومات غير حقيقية، سواءً عليها، أو في الدعاية لها.",
          "level": 1
        },
        {
          "marker": "6-",
          "text": "نقل أو خزن جهازاً أو مستلزماً طبياً بالمخالفة لشروط النقل والتخزين التي تحددها الهيئة.",
          "level": 1
        },
        {
          "marker": "7-",
          "text": "أدخل إلى المملكة عبوات أو أغلفة لجهاز أو مستلزم طبي بقصد الغش، أو حاول إدخال أي من ذلك.",
          "level": 1
        },
        {
          "marker": "8-",
          "text": "صنع أو طبع أو حاز أو باع أو عرض عبوات أو أغلفة لجهاز أو مستلزم طبي بقصد الغش.",
          "level": 1
        },
        {
          "marker": "9-",
          "text": "ارتكب أي مخالفة أخرى لأحكام النظام.",
          "level": 1
        }
      ],
      "amendments": [],
      "heading_context": []
    },
    {
      "number": 39,
      "number_text": "المادة 39",
      "text": "المادة الثانية  والأربعون:\n1- دون إخلال بأي عقوبة أشد ينص عليها أي نظام آخر، يعاقب كل من يرتكب أي مخالفة لأحكام النظام أو اللائحة، بواحدة أو أكثر من العقوبات الآتية:\nأ- غرامة لا تزيد على (خمسة ملايين) ريال.\nب- إغلاق المنشأة مؤقتاً لمدة لا تتجاوز (مائة وثمانين) يوماً.\nج- تعليق الإذن بالتسويق للأجهزة والمستلزمات الطبية –محل المخالفة- لمدة لا تتجاوز عاماً.\nد- إلغاء الإذن بالتسويق للأجهزة والمستلزمات الطبية محل المخالفة.\nهـ - منع المخالف من ممارسة أي نشاط يتعلق بالأجهزة والمستلزمات الطبية، وذلك لمدة لا تتجاوز (مائة وثمانين) يوماً.\nو- إلغاء الترخيص.\nوتجوز مضاعفة العقوبة المحكوم بها وفقاً للفقرات الفرعية (أ) و(ب) و(ج) و(هـ) من هذه الفقرة في حالة تكرار ارتكاب المخالفة، وتعد المخالفة مكررة في حال ارتكابها خلال سنة من تاريخ ارتكاب المخالفة الأولى.\n2- إذا كانت المخالفة تتمثل في ارتكاب أي من الأفعال المنصوص عليها في الفقرات (1) و(2) و(3) و(7) و(8) من المادة (الحادية والأربعين) من النظام، فتكون العقوبة السجن مدة لا تزيد على (عشر) سنوات، أو غرامة لا تزيد على (عشرة ملايين) ريال، أو بهما معاً. ويجوز –إضافةً إلى ذلك– إيقاع أي من العقوبات المنصوص عليها في الفقرات (ب) و(ج) و(د) و(هـ) و(و) من الفقرة (1) من هذه المادة، وتضاعف العقوبة في حال العود.",
      "original_text": "المادة الثانية  والأربعون:\n1- دون إخلال بأي عقوبة أشد ينص عليها أي نظام آخر، يعاقب كل من يرتكب أي مخالفة لأحكام النظام أو اللائحة، بواحدة أو أكثر من العقوبات الآتية:\nأ- غرامة لا تزيد على (خمسة ملايين) ريال.\nب- إغلاق المنشأة مؤقتاً لمدة لا تتجاوز (مائة وثمانين) يوماً.\nج- تعليق الإذن بالتسويق للأجهزة والمستلزمات الطبية –محل المخالفة- لمدة لا تتجاوز عاماً.\nد- إلغاء الإذن بالتسويق للأجهزة والمستلزمات الطبية محل المخالفة.\nهـ - منع المخالف من ممارسة أي نشاط يتعلق بالأجهزة والمستلزمات الطبية، وذلك لمدة لا تتجاوز (مائة وثمانين) يوماً.\nو- إلغاء الترخيص.\nوتجوز مضاعفة العقوبة المحكوم بها وفقاً للفقرات الفرعية (أ) و(ب) و(ج) و(هـ) من هذه الفقرة في حالة تكرار ارتكاب المخالفة، وتعد المخالفة مكررة في حال ارتكابها خلال سنة من تاريخ ارتكاب المخالفة الأولى.\n2- إذا كانت المخالفة تتمثل في ارتكاب أي من الأفعال المنصوص عليها في الفقرات (1) و(2) و(3) و(7) و(8) من المادة (الحادية والأربعين) من النظام، فتكون العقوبة السجن مدة لا تزيد على (عشر) سنوات، أو غرامة لا تزيد على (عشرة ملايين) ريال، أو بهما معاً. ويجوز –إضافةً إلى ذلك– إيقاع أي من العقوبات المنصوص عليها في الفقرات (ب) و(ج) و(د) و(هـ) و(و) من الفقرة (1) من هذه المادة، وتضاعف العقوبة في حال العود.",
      "status": "active",
      "paragraphs": [
        {
          "marker": "",
          "text": "المادة الثانية  والأربعون:",
          "level": 0
        },
        {
          "marker": "1-",
          "text": "دون إخلال بأي عقوبة أشد ينص عليها أي نظام آخر، يعاقب كل من يرتكب أي مخالفة لأحكام النظام أو اللائحة، بواحدة أو أكثر من العقوبات الآتية:",
          "level": 1
        },
        {
          "marker": "أ-",
          "text": "غرامة لا تزيد على (خمسة ملايين) ريال.",
          "level": 1
        },
        {
          "marker": "ب-",
          "text": "إغلاق المنشأة مؤقتاً لمدة لا تتجاوز (مائة وثمانين) يوماً.",
          "level": 1
        },
        {
          "marker": "ج-",
          "text": "تعليق الإذن بالتسويق للأجهزة والمستلزمات الطبية –محل المخالفة- لمدة لا تتجاوز عاماً.",
          "level": 1
        },
        {
          "marker": "د-",
          "text": "إلغاء الإذن بالتسويق للأجهزة والمستلزمات الطبية محل المخالفة.",
          "level": 1
        },
        {
          "marker": "",
          "text": "هـ - منع المخالف من ممارسة أي نشاط يتعلق بالأجهزة والمستلزمات الطبية، وذلك لمدة لا تتجاوز (مائة وثمانين) يوماً.",
          "level": 0
        },
        {
          "marker": "و-",
          "text": "إلغاء الترخيص.",
          "level": 1
        },
        {
          "marker": "",
          "text": "وتجوز مضاعفة العقوبة المحكوم بها وفقاً للفقرات الفرعية (أ) و(ب) و(ج) و(هـ) من هذه الفقرة في حالة تكرار ارتكاب المخالفة، وتعد المخالفة مكررة في حال ارتكابها خلال سنة من تاريخ ارتكاب المخالفة الأولى.",
          "level": 0
        },
        {
          "marker": "2-",
          "text": "إذا كانت المخالفة تتمثل في ارتكاب أي من الأفعال المنصوص عليها في الفقرات (1) و(2) و(3) و(7) و(8) من المادة (الحادية والأربعين) من النظام، فتكون العقوبة السجن مدة لا تزيد على (عشر) سنوات، أو غرامة لا تزيد على (عشرة ملايين) ريال، أو بهما معاً. ويجوز –إضافةً إلى ذلك– إيقاع أي من العقوبات المنصوص عليها في الفقرات (ب) و(ج) و(د) و(هـ) و(و) من الفقرة (1) من هذه المادة، وتضاعف العقوبة في حال العود.",
          "level": 1
        }
      ],
      "amendments": [],
      "heading_context": []
    },
    {
      "number": 40,
      "number_text": "المادة 40",
      "text": "المادة الثالثة  والأربعون:\nتتولى الهيئة توقيع العقوبات المنصوص عليها في الفقرة (1) من المادة (الثانية والأربعين) من النظام، وذلك وفقاً لجدول يصدره المجلس يتضمن تصنيفاً للمخالفات والعقوبات المحددة لكل منها، ويراعى في ذلك طبيعة النشاط والمخالفة المرتكبة وجسامتها في كل حالة على حدة والظروف المشددة والمخففة لها. وتعتمد هذه العقوبات بقرار من الرئيس أو من يفوضه. وفي جميع الأحوال، يكون للهيئة –عند الضرورة– اتخاذ ما تراه من تدابير احترازية.",
      "original_text": "المادة الثالثة  والأربعون:\nتتولى الهيئة توقيع العقوبات المنصوص عليها في الفقرة (1) من المادة (الثانية والأربعين) من النظام، وذلك وفقاً لجدول يصدره المجلس يتضمن تصنيفاً للمخالفات والعقوبات المحددة لكل منها، ويراعى في ذلك طبيعة النشاط والمخالفة المرتكبة وجسامتها في كل حالة على حدة والظروف المشددة والمخففة لها. وتعتمد هذه العقوبات بقرار من الرئيس أو من يفوضه. وفي جميع الأحوال، يكون للهيئة –عند الضرورة– اتخاذ ما تراه من تدابير احترازية.",
      "status": "active",
      "paragraphs": [
        {
          "marker": "",
          "text": "المادة الثالثة  والأربعون:",
          "level": 0
        },
        {
          "marker": "",
          "text": "تتولى الهيئة توقيع العقوبات المنصوص عليها في الفقرة (1) من المادة (الثانية والأربعين) من النظام، وذلك وفقاً لجدول يصدره المجلس يتضمن تصنيفاً للمخالفات والعقوبات المحددة لكل منها، ويراعى في ذلك طبيعة النشاط والمخالفة المرتكبة وجسامتها في كل حالة على حدة والظروف المشددة والمخففة لها. وتعتمد هذه العقوبات بقرار من الرئيس أو من يفوضه. وفي جميع الأحوال، يكون للهيئة –عند الضرورة– اتخاذ ما تراه من تدابير احترازية.",
          "level": 0
        }
      ],
      "amendments": [],
      "heading_context": []
    },
    {
      "number": 41,
      "number_text": "المادة 41",
      "text": "المادة الرابعة  والأربعون:\n1- تكوَّن بقرار من المجلس لجنة (أو أكثر) لا يقل عدد أعضائها عن (ثلاثة)، يكون أحدهم –على الأقل– مستشاراً نظامياً؛ للنظر في التظلمات التي تقدم إلى الهيئة من قرارات توقيع العقوبات الصادرة وفقاً للفقرة (1) من المادة (الثانية والأربعين) من النظام.\n2- تحدد قواعد وإجراءات عمل اللجنة ومكافآت أعضائها بقرار من المجلس.\n3- يجوز الاعتراض على قرارات اللجنة أمام المحكمة الإدارية.",
      "original_text": "المادة الرابعة  والأربعون:\n1- تكوَّن بقرار من المجلس لجنة (أو أكثر) لا يقل عدد أعضائها عن (ثلاثة)، يكون أحدهم –على الأقل– مستشاراً نظامياً؛ للنظر في التظلمات التي تقدم إلى الهيئة من قرارات توقيع العقوبات الصادرة وفقاً للفقرة (1) من المادة (الثانية والأربعين) من النظام.\n2- تحدد قواعد وإجراءات عمل اللجنة ومكافآت أعضائها بقرار من المجلس.\n3- يجوز الاعتراض على قرارات اللجنة أمام المحكمة الإدارية.",
      "status": "active",
      "paragraphs": [
        {
          "marker": "",
          "text": "المادة الرابعة  والأربعون:",
          "level": 0
        },
        {
          "marker": "1-",
          "text": "تكوَّن بقرار من المجلس لجنة (أو أكثر) لا يقل عدد أعضائها عن (ثلاثة)، يكون أحدهم –على الأقل– مستشاراً نظامياً؛ للنظر في التظلمات التي تقدم إلى الهيئة من قرارات توقيع العقوبات الصادرة وفقاً للفقرة (1) من المادة (الثانية والأربعين) من النظام.",
          "level": 1
        },
        {
          "marker": "2-",
          "text": "تحدد قواعد وإجراءات عمل اللجنة ومكافآت أعضائها بقرار من المجلس.",
          "level": 1
        },
        {
          "marker": "3-",
          "text": "يجوز الاعتراض على قرارات اللجنة أمام المحكمة الإدارية.",
          "level": 1
        }
      ],
      "amendments": [],
      "heading_context": []
    },
    {
      "number": 42,
      "number_text": "المادة 42",
      "text": "المادة الخامسة  والأربعون:\nإذا كانت المخالفة مشمولة بحكم الفقرة (2) من المادة (الثانية والأربعين) من النظام، فتحال إلى النيابة العامة؛ للتحقيق فيها، وإحالتها إلى المحكمة المختصة وفقاً للإجراءات النظامية.",
      "original_text": "المادة الخامسة  والأربعون:\nإذا كانت المخالفة مشمولة بحكم الفقرة (2) من المادة (الثانية والأربعين) من النظام، فتحال إلى النيابة العامة؛ للتحقيق فيها، وإحالتها إلى المحكمة المختصة وفقاً للإجراءات النظامية.",
      "status": "active",
      "paragraphs": [
        {
          "marker": "",
          "text": "المادة الخامسة  والأربعون:",
          "level": 0
        },
        {
          "marker": "",
          "text": "إذا كانت المخالفة مشمولة بحكم الفقرة (2) من المادة (الثانية والأربعين) من النظام، فتحال إلى النيابة العامة؛ للتحقيق فيها، وإحالتها إلى المحكمة المختصة وفقاً للإجراءات النظامية.",
          "level": 0
        }
      ],
      "amendments": [],
      "heading_context": []
    },
    {
      "number": 43,
      "number_text": "المادة 43",
      "text": "المادة السادسة  والأربعون:\nيجوز تضمين الحكم أو القرار الصادر بالعقوبة –بحسب الأحوال- النص على نشر منطوقه على نفقة المخالف في صحيفة محلية تصدر في مقر إقامته، فإن لم تكن في مقره صحيفة ففي أقرب منطقة إليه، أو على نشره في أي وسيلة أخرى مناسبة، وذلك بحسب نوع المخالفة المرتكبة وجسامتها وتأثيرها؛ على أن يكون النشر بعد اكتساب الحكم الصفة القطعية، أو تحصُّن القرار بفوات ميعاد التظلم منه، أو صدور حكم نهائي برفض التظلم منه.",
      "original_text": "المادة السادسة  والأربعون:\nيجوز تضمين الحكم أو القرار الصادر بالعقوبة –بحسب الأحوال- النص على نشر منطوقه على نفقة المخالف في صحيفة محلية تصدر في مقر إقامته، فإن لم تكن في مقره صحيفة ففي أقرب منطقة إليه، أو على نشره في أي وسيلة أخرى مناسبة، وذلك بحسب نوع المخالفة المرتكبة وجسامتها وتأثيرها؛ على أن يكون النشر بعد اكتساب الحكم الصفة القطعية، أو تحصُّن القرار بفوات ميعاد التظلم منه، أو صدور حكم نهائي برفض التظلم منه.",
      "status": "active",
      "paragraphs": [
        {
          "marker": "",
          "text": "المادة السادسة  والأربعون:",
          "level": 0
        },
        {
          "marker": "",
          "text": "يجوز تضمين الحكم أو القرار الصادر بالعقوبة –بحسب الأحوال- النص على نشر منطوقه على نفقة المخالف في صحيفة محلية تصدر في مقر إقامته، فإن لم تكن في مقره صحيفة ففي أقرب منطقة إليه، أو على نشره في أي وسيلة أخرى مناسبة، وذلك بحسب نوع المخالفة المرتكبة وجسامتها وتأثيرها؛ على أن يكون النشر بعد اكتساب الحكم الصفة القطعية، أو تحصُّن القرار بفوات ميعاد التظلم منه، أو صدور حكم نهائي برفض التظلم منه.",
          "level": 0
        }
      ],
      "amendments": [],
      "heading_context": []
    },
    {
      "number": 44,
      "number_text": "المادة 44",
      "text": "المادة السابعة  والأربعون:\nللمتضرر من أي مخالفة لأحكام النظام، الحق في المطالبة أمام المحكمة المختصة بالتعويض عن الأضرار التي تسببت فيها تلك المخالفة.",
      "original_text": "المادة السابعة  والأربعون:\nللمتضرر من أي مخالفة لأحكام النظام، الحق في المطالبة أمام المحكمة المختصة بالتعويض عن الأضرار التي تسببت فيها تلك المخالفة.",
      "status": "active",
      "paragraphs": [
        {
          "marker": "",
          "text": "المادة السابعة  والأربعون:",
          "level": 0
        },
        {
          "marker": "",
          "text": "للمتضرر من أي مخالفة لأحكام النظام، الحق في المطالبة أمام المحكمة المختصة بالتعويض عن الأضرار التي تسببت فيها تلك المخالفة.",
          "level": 0
        }
      ],
      "amendments": [],
      "heading_context": []
    },
    {
      "number": 45,
      "number_text": "المادة 45",
      "text": "المادة الثامنة  والأربعون:\nيصدر المجلس اللائحة خلال (مائة وثمانين) يوماً من تاريخ نشر النظام في الجريدة الرسمية، ويعمل بها من تاريخ نفاذه.",
      "original_text": "المادة الثامنة  والأربعون:\nيصدر المجلس اللائحة خلال (مائة وثمانين) يوماً من تاريخ نشر النظام في الجريدة الرسمية، ويعمل بها من تاريخ نفاذه.",
      "status": "active",
      "paragraphs": [
        {
          "marker": "",
          "text": "المادة الثامنة  والأربعون:",
          "level": 0
        },
        {
          "marker": "",
          "text": "يصدر المجلس اللائحة خلال (مائة وثمانين) يوماً من تاريخ نشر النظام في الجريدة الرسمية، ويعمل بها من تاريخ نفاذه.",
          "level": 0
        }
      ],
      "amendments": [],
      "heading_context": []
    },
    {
      "number": 46,
      "number_text": "المادة 46",
      "text": "المادة التاسعة  والأربعون:\nيعمل بالنظام بعد (مائة وثمانين) يوماً من تاريخ نشره في الجريدة الرسمية.",
      "original_text": "المادة التاسعة  والأربعون:\nيعمل بالنظام بعد (مائة وثمانين) يوماً من تاريخ نشره في الجريدة الرسمية.",
      "status": "active",
      "paragraphs": [
        {
          "marker": "",
          "text": "المادة التاسعة  والأربعون:",
          "level": 0
        },
        {
          "marker": "",
          "text": "يعمل بالنظام بعد (مائة وثمانين) يوماً من تاريخ نشره في الجريدة الرسمية.",
          "level": 0
        }
      ],
      "amendments": [],
      "heading_context": []
    }
  ]
}