{
  "law_id": "uqn_17597",
  "law_name": "دمج هيئتي الزكاة والدخل والجمارك في هيئة واحدة والموافقة على تنظيمها",
  "title": "دمج هيئتي الزكاة والدخل والجمارك في هيئة واحدة والموافقة على تنظيمها",
  "jurisdiction_ar": "السعودية",
  "doc_type": "official_text",
  "category": "decision",
  "primary_source_id": "uqn",
  "status": "ساري",
  "issue_date_hijri": "1442/10/02",
  "issue_date_gregorian": "14/05/2021",
  "publish_date_hijri": "1442/10/02",
  "publish_date_gregorian": "14/05/2021",
  "issuing_authority": "قرارات مجلس الوزراء",
  "links": [
    {
      "source_id": "uqn",
      "url": "https://www.uqn.gov.sa/details?p=17597",
      "label_ar": "جريدة أم القرى الرسمية"
    }
  ],
  "total_articles": 1,
  "articles": [
    {
      "number": 1,
      "number_text": "المادة الأولى",
      "text": "قرار رقم (570) وتاريخ 22 /09/ 1442هـ\nإن مجلس الوزراء\nبعد الاطلاع على المعاملة الواردة من الديوان الملكي برقم 32486 وتاريخ 14 /6/ 1442هـ، المشتملة على خطاب معالي وزير المالية رئيس مجلس إدارة الهيئة العامة للزكاة والدخل ورئيس مجلس إدارة الهيئة العامة للجمارك رقم 4430\nوتاريخ 30 /4/ 1442هـ، في شأن دراسة مدى مناسبة دمج الهيئة العامة للزكاة والدخل مع الهيئة العامة للجمارك.\nوبعد الاطلاع على تنظيم الهيئة العامة للزكاة والدخل، الصادر بقرار مجلس الوزراء رقم (465) وتاريخ 20 /7/ 1438هـ.\nوبعد الاطلاع على تنظيم الهيئة العامة للجمارك، الصادر بقرار مجلس الوزراء رقم (352) وتاريخ 3 /7/ 1439هـ.\nوبعد الاطلاع على المذكرتين رقم (1248) وتاريخ 26 /7/ 1442هـ، ورقم (1513) وتاريخ 3 /9/ 1442هـ، المعدتين في هيئة الخبراء بمجلس الوزراء.\nوبعد الاطلاع على التوصية رقم (6-42/13/د) وتاريخ 5 /8/ 1442هـ، والمحضر رقم (42/307/م)\nوتاريخ 10 /9/ 1442هـ، المعدين في مجلس الشؤون الاقتصادية والتنمية.\nوبعد الاطلاع على توصية اللجنة العامة لمجلس الوزراء رقم (6471) وتاريخ 15 /9/ 1442هـ.\nيقرر ما يلي:\nأولاً: دمج الهيئة العامة للزكاة والدخل والهيئة العامة للجمارك في هيئة واحدة باسم (هيئة الزكاة والضريبة والجمارك).\nثانيـاً: الموافقة على تنظيم هيئة الزكاة والضريبة والجمارك،\nبالصيغة المرافقة.\nثالثـاً: استمرار تطبيق اللوائح المالية والإدارية في كل من الهيئة العامة للزكاة والدخل والهيئة العامة للجمارك على العاملين فيهما، وذلك إلى حين اعتماد مجلس إدارة هيئة الزكاة والضريبة والجمارك لوائح الهيئة، ووضع الأحكام الانتقالية الخاصة بالعاملين فيها.\nرابعـــاً: يمارس مجلس إدارة هيئة الزكاة والضريبة والجمارك صلاحيته المنصوص عليها في الفقرة (12) من المادة (الخامسة) من تنظيم الهيئة بالاتفاق مع وزارة المالية ومركز تنمية الإيرادات غير النفطية، وذلك إلى حين صدور لائحة ممارسات الهيئات والمؤسسات العامة وما في حكمها فرض المقابل المالي للخدمات والأعمال التي تقدمها، والعمل بموجبها.\nخامسـاً: يباشر رئيس مجلس إدارة هيئة الزكاة والضريبة والجمارك مهمات مجلس الإدارة إلى حين تشكيله، على أن يقتصر ذلك على ممارسة اختصاصات المجلس المتصلة بتسيير أعماله، دون أن يشمل ذلك الاختصاصات المتعلقة بإقرار السياسات واللوائح المالية والإدارية.\nسادسـاً: تتكون الجمعيات العامة (العادية وغير العادية) للشركات التي تؤسسها هيئة الزكاة والضريبة والجمارك -وفقاً لعجز المادة (الثالثة) من تنظيمها– من معالي وزير المالية رئيس مجلس إدارة هيئة الزكاة والضريبة والجمارك.\nسابعـاً: تحل هيئة الزكاة والضريبة والجمارك محل الهيئة العامة للزكاة والدخل، والهيئة العامة للجمارك، في جميع مالهما من مسؤوليات وصلاحيات وحقوق والتزامات ونحوها.\nثامنـــاً: إحلال عبارة (هيئة الزكاة والضريبة والجمارك) محل عبارة (الهيئة العامة للزكاة والدخل) وعبارة (الهيئة العامة للجمارك)، وإحلال عبارة (محافظ هيئة الزكاة والضريبة والجمارك) محل عبارة (محافظ الهيئة العامة للزكاة والدخل) وعبارة (محافظ الهيئة العامة للجمارك)، أينما وردت في الأنظمة والتنظيمات والأوامر والمراسيم الملكية والقرارات واللوائح.\nتاسعاً: تستمر هيئة الزكاة والضريبة والجمارك في مراجعة الأنظمة والتنظيمات والأوامر والمراسيم الملكية والقرارات ذات الصلة، وإذا تبينت لها الحاجة إلى تعديل أي من أحكامها –التي تتصل اتصالاً مباشراً أو غير مباشر بعملها– فترفع بما تراه في هذا الشأن.\nرئيس مجلس الوزراء",
      "original_text": "قرار رقم (570) وتاريخ 22 /09/ 1442هـ\nإن مجلس الوزراء\nبعد الاطلاع على المعاملة الواردة من الديوان الملكي برقم 32486 وتاريخ 14 /6/ 1442هـ، المشتملة على خطاب معالي وزير المالية رئيس مجلس إدارة الهيئة العامة للزكاة والدخل ورئيس مجلس إدارة الهيئة العامة للجمارك رقم 4430\nوتاريخ 30 /4/ 1442هـ، في شأن دراسة مدى مناسبة دمج الهيئة العامة للزكاة والدخل مع الهيئة العامة للجمارك.\nوبعد الاطلاع على تنظيم الهيئة العامة للزكاة والدخل، الصادر بقرار مجلس الوزراء رقم (465) وتاريخ 20 /7/ 1438هـ.\nوبعد الاطلاع على تنظيم الهيئة العامة للجمارك، الصادر بقرار مجلس الوزراء رقم (352) وتاريخ 3 /7/ 1439هـ.\nوبعد الاطلاع على المذكرتين رقم (1248) وتاريخ 26 /7/ 1442هـ، ورقم (1513) وتاريخ 3 /9/ 1442هـ، المعدتين في هيئة الخبراء بمجلس الوزراء.\nوبعد الاطلاع على التوصية رقم (6-42/13/د) وتاريخ 5 /8/ 1442هـ، والمحضر رقم (42/307/م)\nوتاريخ 10 /9/ 1442هـ، المعدين في مجلس الشؤون الاقتصادية والتنمية.\nوبعد الاطلاع على توصية اللجنة العامة لمجلس الوزراء رقم (6471) وتاريخ 15 /9/ 1442هـ.\nيقرر ما يلي:\nأولاً: دمج الهيئة العامة للزكاة والدخل والهيئة العامة للجمارك في هيئة واحدة باسم (هيئة الزكاة والضريبة والجمارك).\nثانيـاً: الموافقة على تنظيم هيئة الزكاة والضريبة والجمارك،\nبالصيغة المرافقة.\nثالثـاً: استمرار تطبيق اللوائح المالية والإدارية في كل من الهيئة العامة للزكاة والدخل والهيئة العامة للجمارك على العاملين فيهما، وذلك إلى حين اعتماد مجلس إدارة هيئة الزكاة والضريبة والجمارك لوائح الهيئة، ووضع الأحكام الانتقالية الخاصة بالعاملين فيها.\nرابعـــاً: يمارس مجلس إدارة هيئة الزكاة والضريبة والجمارك صلاحيته المنصوص عليها في الفقرة (12) من المادة (الخامسة) من تنظيم الهيئة بالاتفاق مع وزارة المالية ومركز تنمية الإيرادات غير النفطية، وذلك إلى حين صدور لائحة ممارسات الهيئات والمؤسسات العامة وما في حكمها فرض المقابل المالي للخدمات والأعمال التي تقدمها، والعمل بموجبها.\nخامسـاً: يباشر رئيس مجلس إدارة هيئة الزكاة والضريبة والجمارك مهمات مجلس الإدارة إلى حين تشكيله، على أن يقتصر ذلك على ممارسة اختصاصات المجلس المتصلة بتسيير أعماله، دون أن يشمل ذلك الاختصاصات المتعلقة بإقرار السياسات واللوائح المالية والإدارية.\nسادسـاً: تتكون الجمعيات العامة (العادية وغير العادية) للشركات التي تؤسسها هيئة الزكاة والضريبة والجمارك -وفقاً لعجز المادة (الثالثة) من تنظيمها– من معالي وزير المالية رئيس مجلس إدارة هيئة الزكاة والضريبة والجمارك.\nسابعـاً: تحل هيئة الزكاة والضريبة والجمارك محل الهيئة العامة للزكاة والدخل، والهيئة العامة للجمارك، في جميع مالهما من مسؤوليات وصلاحيات وحقوق والتزامات ونحوها.\nثامنـــاً: إحلال عبارة (هيئة الزكاة والضريبة والجمارك) محل عبارة (الهيئة العامة للزكاة والدخل) وعبارة (الهيئة العامة للجمارك)، وإحلال عبارة (محافظ هيئة الزكاة والضريبة والجمارك) محل عبارة (محافظ الهيئة العامة للزكاة والدخل) وعبارة (محافظ الهيئة العامة للجمارك)، أينما وردت في الأنظمة والتنظيمات والأوامر والمراسيم الملكية والقرارات واللوائح.\nتاسعاً: تستمر هيئة الزكاة والضريبة والجمارك في مراجعة الأنظمة والتنظيمات والأوامر والمراسيم الملكية والقرارات ذات الصلة، وإذا تبينت لها الحاجة إلى تعديل أي من أحكامها –التي تتصل اتصالاً مباشراً أو غير مباشر بعملها– فترفع بما تراه في هذا الشأن.\nرئيس مجلس الوزراء",
      "status": "active",
      "paragraphs": [
        {
          "marker": "",
          "text": "قرار رقم (570) وتاريخ 22 /09/ 1442هـ",
          "level": 0
        },
        {
          "marker": "",
          "text": "إن مجلس الوزراء",
          "level": 0
        },
        {
          "marker": "",
          "text": "بعد الاطلاع على المعاملة الواردة من الديوان الملكي برقم 32486 وتاريخ 14 /6/ 1442هـ، المشتملة على خطاب معالي وزير المالية رئيس مجلس إدارة الهيئة العامة للزكاة والدخل ورئيس مجلس إدارة الهيئة العامة للجمارك رقم 4430",
          "level": 0
        },
        {
          "marker": "",
          "text": "وتاريخ 30 /4/ 1442هـ، في شأن دراسة مدى مناسبة دمج الهيئة العامة للزكاة والدخل مع الهيئة العامة للجمارك.",
          "level": 0
        },
        {
          "marker": "",
          "text": "وبعد الاطلاع على تنظيم الهيئة العامة للزكاة والدخل، الصادر بقرار مجلس الوزراء رقم (465) وتاريخ 20 /7/ 1438هـ.",
          "level": 0
        },
        {
          "marker": "",
          "text": "وبعد الاطلاع على تنظيم الهيئة العامة للجمارك، الصادر بقرار مجلس الوزراء رقم (352) وتاريخ 3 /7/ 1439هـ.",
          "level": 0
        },
        {
          "marker": "",
          "text": "وبعد الاطلاع على المذكرتين رقم (1248) وتاريخ 26 /7/ 1442هـ، ورقم (1513) وتاريخ 3 /9/ 1442هـ، المعدتين في هيئة الخبراء بمجلس الوزراء.",
          "level": 0
        },
        {
          "marker": "",
          "text": "وبعد الاطلاع على التوصية رقم (6-42/13/د) وتاريخ 5 /8/ 1442هـ، والمحضر رقم (42/307/م)",
          "level": 0
        },
        {
          "marker": "",
          "text": "وتاريخ 10 /9/ 1442هـ، المعدين في مجلس الشؤون الاقتصادية والتنمية.",
          "level": 0
        },
        {
          "marker": "",
          "text": "وبعد الاطلاع على توصية اللجنة العامة لمجلس الوزراء رقم (6471) وتاريخ 15 /9/ 1442هـ.",
          "level": 0
        },
        {
          "marker": "",
          "text": "يقرر ما يلي:",
          "level": 0
        },
        {
          "marker": "",
          "text": "أولاً: دمج الهيئة العامة للزكاة والدخل والهيئة العامة للجمارك في هيئة واحدة باسم (هيئة الزكاة والضريبة والجمارك).",
          "level": 0
        },
        {
          "marker": "",
          "text": "ثانيـاً: الموافقة على تنظيم هيئة الزكاة والضريبة والجمارك،",
          "level": 0
        },
        {
          "marker": "",
          "text": "بالصيغة المرافقة.",
          "level": 0
        },
        {
          "marker": "",
          "text": "ثالثـاً: استمرار تطبيق اللوائح المالية والإدارية في كل من الهيئة العامة للزكاة والدخل والهيئة العامة للجمارك على العاملين فيهما، وذلك إلى حين اعتماد مجلس إدارة هيئة الزكاة والضريبة والجمارك لوائح الهيئة، ووضع الأحكام الانتقالية الخاصة بالعاملين فيها.",
          "level": 0
        },
        {
          "marker": "",
          "text": "رابعـــاً: يمارس مجلس إدارة هيئة الزكاة والضريبة والجمارك صلاحيته المنصوص عليها في الفقرة (12) من المادة (الخامسة) من تنظيم الهيئة بالاتفاق مع وزارة المالية ومركز تنمية الإيرادات غير النفطية، وذلك إلى حين صدور لائحة ممارسات الهيئات والمؤسسات العامة وما في حكمها فرض المقابل المالي للخدمات والأعمال التي تقدمها، والعمل بموجبها.",
          "level": 0
        },
        {
          "marker": "",
          "text": "خامسـاً: يباشر رئيس مجلس إدارة هيئة الزكاة والضريبة والجمارك مهمات مجلس الإدارة إلى حين تشكيله، على أن يقتصر ذلك على ممارسة اختصاصات المجلس المتصلة بتسيير أعماله، دون أن يشمل ذلك الاختصاصات المتعلقة بإقرار السياسات واللوائح المالية والإدارية.",
          "level": 0
        },
        {
          "marker": "",
          "text": "سادسـاً: تتكون الجمعيات العامة (العادية وغير العادية) للشركات التي تؤسسها هيئة الزكاة والضريبة والجمارك -وفقاً لعجز المادة (الثالثة) من تنظيمها– من معالي وزير المالية رئيس مجلس إدارة هيئة الزكاة والضريبة والجمارك.",
          "level": 0
        },
        {
          "marker": "",
          "text": "سابعـاً: تحل هيئة الزكاة والضريبة والجمارك محل الهيئة العامة للزكاة والدخل، والهيئة العامة للجمارك، في جميع مالهما من مسؤوليات وصلاحيات وحقوق والتزامات ونحوها.",
          "level": 0
        },
        {
          "marker": "",
          "text": "ثامنـــاً: إحلال عبارة (هيئة الزكاة والضريبة والجمارك) محل عبارة (الهيئة العامة للزكاة والدخل) وعبارة (الهيئة العامة للجمارك)، وإحلال عبارة (محافظ هيئة الزكاة والضريبة والجمارك) محل عبارة (محافظ الهيئة العامة للزكاة والدخل) وعبارة (محافظ الهيئة العامة للجمارك)، أينما وردت في الأنظمة والتنظيمات والأوامر والمراسيم الملكية والقرارات واللوائح.",
          "level": 0
        },
        {
          "marker": "",
          "text": "تاسعاً: تستمر هيئة الزكاة والضريبة والجمارك في مراجعة الأنظمة والتنظيمات والأوامر والمراسيم الملكية والقرارات ذات الصلة، وإذا تبينت لها الحاجة إلى تعديل أي من أحكامها –التي تتصل اتصالاً مباشراً أو غير مباشر بعملها– فترفع بما تراه في هذا الشأن.",
          "level": 0
        },
        {
          "marker": "",
          "text": "رئيس مجلس الوزراء",
          "level": 0
        }
      ],
      "amendments": [],
      "heading_context": []
    }
  ]
}