{
  "law_id": "uqn_26662",
  "law_name": "الضوابط والإجراءات لليخوت الزائرة",
  "title": "الضوابط والإجراءات لليخوت الزائرة",
  "jurisdiction_ar": "السعودية",
  "doc_type": "official_text",
  "category": "regulation",
  "primary_source_id": "uqn",
  "status": "ساري",
  "issue_date_hijri": "1446/04/20",
  "issue_date_gregorian": "23/10/2024",
  "publish_date_hijri": "1446/04/20",
  "publish_date_gregorian": "23/10/2024",
  "issuing_authority": "لوائح وأنظمة",
  "links": [
    {
      "source_id": "uqn",
      "url": "https://www.uqn.gov.sa/details?p=26662",
      "label_ar": "جريدة أم القرى الرسمية"
    }
  ],
  "total_articles": 14,
  "articles": [
    {
      "number": 0,
      "number_text": "مقدمة",
      "text": "رقم 4 ت- 2024 وتاريخ 28 /02 /1446هـ الموافق 1 /09 /2024م",
      "original_text": "رقم 4 ت- 2024 وتاريخ 28 /02 /1446هـ الموافق 1 /09 /2024م",
      "status": "active",
      "paragraphs": [
        {
          "marker": "",
          "text": "رقم 4 ت- 2024 وتاريخ 28 /02 /1446هـ الموافق 1 /09 /2024م",
          "level": 0
        }
      ],
      "amendments": [],
      "heading_context": []
    },
    {
      "number": 1,
      "number_text": "المادة الأولى",
      "text": "المادة الأولى:  التعريفات\nيُقصد بالعبارات والألفاظ الآتية -أينما وردت في هذه الضوابط والإجراءات- المعاني المبيّنة أمام كل منها، ما لم يقتضِ سياق النص غير ذلك:\nالمملكة\nالمملكة العربية السعودية\nالمجلس\nمجلس إدارة الهيئة السعودية للبحر الأحمر\nالهيئة\nالهيئة السعودية للبحر الأحمر\nاللائحة\nالتنظيمية\nاللائحة التنظيمية لليخوت الزائرة\nالضوابط   والإجراءات\nالضوابط والإجراءات لليخوت الزائرة\nالنطاق   الجغرافي\nالبحر الإقليمي التابع للمملكة العربية السعودية في البحر الأحمر، الذي تمارس   فيه الأنشطة الملاحية والأنشطة البحرية، والجزء من اليابسة المرتبط بممارسة تلك الأنشطة؛   عدا المناطق العسكرية\nوالأمنية وغيرها فيهما\nالوكيلظ الملاحي السياحي\nالشخص ذو الصفة   الاعتبارية المرخص له من الهيئة بتقديم الخدمات للواسطة البحرية لممارسة الأنشطة   الملاحية في النطاق الجغرافي\nالواسطة   البحرية\nكل واسطة عائمة معدة للعمل فوق   المسطحات المائية أو تحتها تستخدم لأغراض سياحية أو ترفيهية. وتعد ملحقات   الواسطة البحرية اللازمة لاستغلالها جزءاً منها\nاليخت   الزائر\nأي يخت يرفع علم دولة أجنبية أيّاً   كان نوعه وحجمه والذي يزور ويُبحِر داخل النطاق الجغرافي بغرض السياحة، أو   الصيانة، أو التزود بالوقود، أو الحصول على التوريدات أو المشاركة في المعارض   البحرية\nالترخيص   الملاحي\nوثيقة تصدر   من الهيئة العامة للنقل تتضمن صلاحية الواسطة البحرية للملاحة البحرية في النطاق   الجغرافي، بعد استيفائه كافة متطلبات الأمن والسلامة والاشتراطات البيئية   اللازمة\nالترخيص   الفني (السياحي والترفيهي)\nوثيقة   تصدر من الهيئة تسمح للواسطة البحرية بالدخول والإبحار والتنقل داخل النطاق الجغرافي   لغرض السياحة\nتصريح   رحلة سياحية\nموافقة   مكتوبة دورية تصدر من الهيئة بحيث تسمح للواسطة البحرية من التنقل بين الوجهات،   والغرض منه التأكد من اتباع إجراءات الأمن والسلامة، على أن يتضمن التصريح   معلومات الواسطة البحرية ومحددة به المدة الزمنية وتاريخ الرحلة، ومواقع ومسارات   الرحلة مع تحديد نقطة الذهاب والعودة، وكذلك تحديد الطاقم والركاب والغرض من   الرحلة\nتصريح   المغادرة\nموافقة مكتوبة تسمح   للواسطة البحرية بالمغادرة من نقطة خروج محددة، على أن يتضمن التصريح معلومات   الواسطة البحرية ومحددة به المدة الزمنية وتاريخ الرحلة، ومواقع ومسارات الرحلة،   وكذلك تحديد الطاقم والركاب والغرض من الرحلة\nتصريح   مرور\nموافقة مكتوبة تسمح   للواسطة البحرية بالدخول للمرسى البحري السياحي لمدة محددة، وأغراض محددة، على   أن يتضمن التصريح معلومات الواسطة البحرية، ومسار الرحلة، وكذلك تحديد الطاقم   والركاب\nالمرسى البحري السياحي\nالمنطقة المستخدمة لتوقف أو رسو   الواسطة البحرية في النطاق الجغرافي\nقارب التنقل\nقارب لنقل الركاب من اليخت إلى الشاطئ أو   المرسى البحري السياحي ذهاباً وإياباً\nالمالك\nالشخص   الذي يشغّل السفينة لحسابه بوصفه مالكاً، أو مستأجراً، أو مديراً للشيوع\nالرُبَّان\nالشخص   المؤهل لقيادة السفينة والمسؤول عن إدارتها\nطاقم   اليخت\nجميع الأشخاص العاملين على متن اليخت بأي صفة،   بمن في ذلك الرُبَّان وكبير الضباط والمهندسين\nالألعاب   المائية\nتعني المركبات المائية الصغيرة أو الشخصية أو الملحقات   على اليخت التي تستخدم لأغراض ترفيهية\nالمنطقة   البحرية المحمية\nمنطقة جغرافية تُعرف كمنطقة محمية بأنظمة خاصة   من قبل الجهات المختصة في المملكة\nعقد   الرصيف\nالعقد بين مشغّل   المرسى ومالك اليخت أو الوكيل الملاحي السياحي\nالذي\nيسمح لليخت باستخدام الرصيف لمدة محددة\nالمنصة   الإلكترونية\nمنصة حكومية تابعة للهيئة تُقدِّم جميع   الخدمات المتعلقة بسياحة الوسائط البحرية",
      "original_text": "المادة الأولى:  التعريفات\nيُقصد بالعبارات والألفاظ الآتية -أينما وردت في هذه الضوابط والإجراءات- المعاني المبيّنة أمام كل منها، ما لم يقتضِ سياق النص غير ذلك:\nالمملكة\nالمملكة العربية السعودية\nالمجلس\nمجلس إدارة الهيئة السعودية للبحر الأحمر\nالهيئة\nالهيئة السعودية للبحر الأحمر\nاللائحة\nالتنظيمية\nاللائحة التنظيمية لليخوت الزائرة\nالضوابط   والإجراءات\nالضوابط والإجراءات لليخوت الزائرة\nالنطاق   الجغرافي\nالبحر الإقليمي التابع للمملكة العربية السعودية في البحر الأحمر، الذي تمارس   فيه الأنشطة الملاحية والأنشطة البحرية، والجزء من اليابسة المرتبط بممارسة تلك الأنشطة؛   عدا المناطق العسكرية\nوالأمنية وغيرها فيهما\nالوكيلظ الملاحي السياحي\nالشخص ذو الصفة   الاعتبارية المرخص له من الهيئة بتقديم الخدمات للواسطة البحرية لممارسة الأنشطة   الملاحية في النطاق الجغرافي\nالواسطة   البحرية\nكل واسطة عائمة معدة للعمل فوق   المسطحات المائية أو تحتها تستخدم لأغراض سياحية أو ترفيهية. وتعد ملحقات   الواسطة البحرية اللازمة لاستغلالها جزءاً منها\nاليخت   الزائر\nأي يخت يرفع علم دولة أجنبية أيّاً   كان نوعه وحجمه والذي يزور ويُبحِر داخل النطاق الجغرافي بغرض السياحة، أو   الصيانة، أو التزود بالوقود، أو الحصول على التوريدات أو المشاركة في المعارض   البحرية\nالترخيص   الملاحي\nوثيقة تصدر   من الهيئة العامة للنقل تتضمن صلاحية الواسطة البحرية للملاحة البحرية في النطاق   الجغرافي، بعد استيفائه كافة متطلبات الأمن والسلامة والاشتراطات البيئية   اللازمة\nالترخيص   الفني (السياحي والترفيهي)\nوثيقة   تصدر من الهيئة تسمح للواسطة البحرية بالدخول والإبحار والتنقل داخل النطاق الجغرافي   لغرض السياحة\nتصريح   رحلة سياحية\nموافقة   مكتوبة دورية تصدر من الهيئة بحيث تسمح للواسطة البحرية من التنقل بين الوجهات،   والغرض منه التأكد من اتباع إجراءات الأمن والسلامة، على أن يتضمن التصريح   معلومات الواسطة البحرية ومحددة به المدة الزمنية وتاريخ الرحلة، ومواقع ومسارات   الرحلة مع تحديد نقطة الذهاب والعودة، وكذلك تحديد الطاقم والركاب والغرض من   الرحلة\nتصريح   المغادرة\nموافقة مكتوبة تسمح   للواسطة البحرية بالمغادرة من نقطة خروج محددة، على أن يتضمن التصريح معلومات   الواسطة البحرية ومحددة به المدة الزمنية وتاريخ الرحلة، ومواقع ومسارات الرحلة،   وكذلك تحديد الطاقم والركاب والغرض من الرحلة\nتصريح   مرور\nموافقة مكتوبة تسمح   للواسطة البحرية بالدخول للمرسى البحري السياحي لمدة محددة، وأغراض محددة، على   أن يتضمن التصريح معلومات الواسطة البحرية، ومسار الرحلة، وكذلك تحديد الطاقم   والركاب\nالمرسى البحري السياحي\nالمنطقة المستخدمة لتوقف أو رسو   الواسطة البحرية في النطاق الجغرافي\nقارب التنقل\nقارب لنقل الركاب من اليخت إلى الشاطئ أو   المرسى البحري السياحي ذهاباً وإياباً\nالمالك\nالشخص   الذي يشغّل السفينة لحسابه بوصفه مالكاً، أو مستأجراً، أو مديراً للشيوع\nالرُبَّان\nالشخص   المؤهل لقيادة السفينة والمسؤول عن إدارتها\nطاقم   اليخت\nجميع الأشخاص العاملين على متن اليخت بأي صفة،   بمن في ذلك الرُبَّان وكبير الضباط والمهندسين\nالألعاب   المائية\nتعني المركبات المائية الصغيرة أو الشخصية أو الملحقات   على اليخت التي تستخدم لأغراض ترفيهية\nالمنطقة   البحرية المحمية\nمنطقة جغرافية تُعرف كمنطقة محمية بأنظمة خاصة   من قبل الجهات المختصة في المملكة\nعقد   الرصيف\nالعقد بين مشغّل   المرسى ومالك اليخت أو الوكيل الملاحي السياحي\nالذي\nيسمح لليخت باستخدام الرصيف لمدة محددة\nالمنصة   الإلكترونية\nمنصة حكومية تابعة للهيئة تُقدِّم جميع   الخدمات المتعلقة بسياحة الوسائط البحرية",
      "status": "active",
      "paragraphs": [
        {
          "marker": "",
          "text": "المادة الأولى:  التعريفات",
          "level": 0
        },
        {
          "marker": "",
          "text": "يُقصد بالعبارات والألفاظ الآتية -أينما وردت في هذه الضوابط والإجراءات- المعاني المبيّنة أمام كل منها، ما لم يقتضِ سياق النص غير ذلك:",
          "level": 0
        },
        {
          "marker": "",
          "text": "المملكة",
          "level": 0
        },
        {
          "marker": "",
          "text": "المملكة العربية السعودية",
          "level": 0
        },
        {
          "marker": "",
          "text": "المجلس",
          "level": 0
        },
        {
          "marker": "",
          "text": "مجلس إدارة الهيئة السعودية للبحر الأحمر",
          "level": 0
        },
        {
          "marker": "",
          "text": "الهيئة",
          "level": 0
        },
        {
          "marker": "",
          "text": "الهيئة السعودية للبحر الأحمر",
          "level": 0
        },
        {
          "marker": "",
          "text": "اللائحة",
          "level": 0
        },
        {
          "marker": "",
          "text": "التنظيمية",
          "level": 0
        },
        {
          "marker": "",
          "text": "اللائحة التنظيمية لليخوت الزائرة",
          "level": 0
        },
        {
          "marker": "",
          "text": "الضوابط   والإجراءات",
          "level": 0
        },
        {
          "marker": "",
          "text": "الضوابط والإجراءات لليخوت الزائرة",
          "level": 0
        },
        {
          "marker": "",
          "text": "النطاق   الجغرافي",
          "level": 0
        },
        {
          "marker": "",
          "text": "البحر الإقليمي التابع للمملكة العربية السعودية في البحر الأحمر، الذي تمارس   فيه الأنشطة الملاحية والأنشطة البحرية، والجزء من اليابسة المرتبط بممارسة تلك الأنشطة؛   عدا المناطق العسكرية",
          "level": 0
        },
        {
          "marker": "",
          "text": "والأمنية وغيرها فيهما",
          "level": 0
        },
        {
          "marker": "",
          "text": "الوكيلظ الملاحي السياحي",
          "level": 0
        },
        {
          "marker": "",
          "text": "الشخص ذو الصفة   الاعتبارية المرخص له من الهيئة بتقديم الخدمات للواسطة البحرية لممارسة الأنشطة   الملاحية في النطاق الجغرافي",
          "level": 0
        },
        {
          "marker": "",
          "text": "الواسطة   البحرية",
          "level": 0
        },
        {
          "marker": "",
          "text": "كل واسطة عائمة معدة للعمل فوق   المسطحات المائية أو تحتها تستخدم لأغراض سياحية أو ترفيهية. وتعد ملحقات   الواسطة البحرية اللازمة لاستغلالها جزءاً منها",
          "level": 0
        },
        {
          "marker": "",
          "text": "اليخت   الزائر",
          "level": 0
        },
        {
          "marker": "",
          "text": "أي يخت يرفع علم دولة أجنبية أيّاً   كان نوعه وحجمه والذي يزور ويُبحِر داخل النطاق الجغرافي بغرض السياحة، أو   الصيانة، أو التزود بالوقود، أو الحصول على التوريدات أو المشاركة في المعارض   البحرية",
          "level": 0
        },
        {
          "marker": "",
          "text": "الترخيص   الملاحي",
          "level": 0
        },
        {
          "marker": "",
          "text": "وثيقة تصدر   من الهيئة العامة للنقل تتضمن صلاحية الواسطة البحرية للملاحة البحرية في النطاق   الجغرافي، بعد استيفائه كافة متطلبات الأمن والسلامة والاشتراطات البيئية   اللازمة",
          "level": 0
        },
        {
          "marker": "",
          "text": "الترخيص   الفني (السياحي والترفيهي)",
          "level": 0
        },
        {
          "marker": "",
          "text": "وثيقة   تصدر من الهيئة تسمح للواسطة البحرية بالدخول والإبحار والتنقل داخل النطاق الجغرافي   لغرض السياحة",
          "level": 0
        },
        {
          "marker": "",
          "text": "تصريح   رحلة سياحية",
          "level": 0
        },
        {
          "marker": "",
          "text": "موافقة   مكتوبة دورية تصدر من الهيئة بحيث تسمح للواسطة البحرية من التنقل بين الوجهات،   والغرض منه التأكد من اتباع إجراءات الأمن والسلامة، على أن يتضمن التصريح   معلومات الواسطة البحرية ومحددة به المدة الزمنية وتاريخ الرحلة، ومواقع ومسارات   الرحلة مع تحديد نقطة الذهاب والعودة، وكذلك تحديد الطاقم والركاب والغرض من   الرحلة",
          "level": 0
        },
        {
          "marker": "",
          "text": "تصريح   المغادرة",
          "level": 0
        },
        {
          "marker": "",
          "text": "موافقة مكتوبة تسمح   للواسطة البحرية بالمغادرة من نقطة خروج محددة، على أن يتضمن التصريح معلومات   الواسطة البحرية ومحددة به المدة الزمنية وتاريخ الرحلة، ومواقع ومسارات الرحلة،   وكذلك تحديد الطاقم والركاب والغرض من الرحلة",
          "level": 0
        },
        {
          "marker": "",
          "text": "تصريح   مرور",
          "level": 0
        },
        {
          "marker": "",
          "text": "موافقة مكتوبة تسمح   للواسطة البحرية بالدخول للمرسى البحري السياحي لمدة محددة، وأغراض محددة، على   أن يتضمن التصريح معلومات الواسطة البحرية، ومسار الرحلة، وكذلك تحديد الطاقم   والركاب",
          "level": 0
        },
        {
          "marker": "",
          "text": "المرسى البحري السياحي",
          "level": 0
        },
        {
          "marker": "",
          "text": "المنطقة المستخدمة لتوقف أو رسو   الواسطة البحرية في النطاق الجغرافي",
          "level": 0
        },
        {
          "marker": "",
          "text": "قارب التنقل",
          "level": 0
        },
        {
          "marker": "",
          "text": "قارب لنقل الركاب من اليخت إلى الشاطئ أو   المرسى البحري السياحي ذهاباً وإياباً",
          "level": 0
        },
        {
          "marker": "",
          "text": "المالك",
          "level": 0
        },
        {
          "marker": "",
          "text": "الشخص   الذي يشغّل السفينة لحسابه بوصفه مالكاً، أو مستأجراً، أو مديراً للشيوع",
          "level": 0
        },
        {
          "marker": "",
          "text": "الرُبَّان",
          "level": 0
        },
        {
          "marker": "",
          "text": "الشخص   المؤهل لقيادة السفينة والمسؤول عن إدارتها",
          "level": 0
        },
        {
          "marker": "",
          "text": "طاقم   اليخت",
          "level": 0
        },
        {
          "marker": "",
          "text": "جميع الأشخاص العاملين على متن اليخت بأي صفة،   بمن في ذلك الرُبَّان وكبير الضباط والمهندسين",
          "level": 0
        },
        {
          "marker": "",
          "text": "الألعاب   المائية",
          "level": 0
        },
        {
          "marker": "",
          "text": "تعني المركبات المائية الصغيرة أو الشخصية أو الملحقات   على اليخت التي تستخدم لأغراض ترفيهية",
          "level": 0
        },
        {
          "marker": "",
          "text": "المنطقة   البحرية المحمية",
          "level": 0
        },
        {
          "marker": "",
          "text": "منطقة جغرافية تُعرف كمنطقة محمية بأنظمة خاصة   من قبل الجهات المختصة في المملكة",
          "level": 0
        },
        {
          "marker": "",
          "text": "عقد   الرصيف",
          "level": 0
        },
        {
          "marker": "",
          "text": "العقد بين مشغّل   المرسى ومالك اليخت أو الوكيل الملاحي السياحي",
          "level": 0
        },
        {
          "marker": "",
          "text": "الذي",
          "level": 0
        },
        {
          "marker": "",
          "text": "يسمح لليخت باستخدام الرصيف لمدة محددة",
          "level": 0
        },
        {
          "marker": "",
          "text": "المنصة   الإلكترونية",
          "level": 0
        },
        {
          "marker": "",
          "text": "منصة حكومية تابعة للهيئة تُقدِّم جميع   الخدمات المتعلقة بسياحة الوسائط البحرية",
          "level": 0
        }
      ],
      "amendments": [],
      "heading_context": []
    },
    {
      "number": 2,
      "number_text": "المادة الثانية",
      "text": "المادة الثانية:  الهدف\nتهدف الضوابط والإجراءات لتوضيح أحكام اللائحة التنظيمية لليخوت الزائرة الراغبة في الدخول والخروج و/أو الإبحار في النطاق الجغرافي، بما في ذلك السياحة والصيانة والتزود بالوقود والحصول على الإمدادات أو المشاركة في المعارض البحرية ونحوها.",
      "original_text": "المادة الثانية:  الهدف\nتهدف الضوابط والإجراءات لتوضيح أحكام اللائحة التنظيمية لليخوت الزائرة الراغبة في الدخول والخروج و/أو الإبحار في النطاق الجغرافي، بما في ذلك السياحة والصيانة والتزود بالوقود والحصول على الإمدادات أو المشاركة في المعارض البحرية ونحوها.",
      "status": "active",
      "paragraphs": [
        {
          "marker": "",
          "text": "المادة الثانية:  الهدف",
          "level": 0
        },
        {
          "marker": "",
          "text": "تهدف الضوابط والإجراءات لتوضيح أحكام اللائحة التنظيمية لليخوت الزائرة الراغبة في الدخول والخروج و/أو الإبحار في النطاق الجغرافي، بما في ذلك السياحة والصيانة والتزود بالوقود والحصول على الإمدادات أو المشاركة في المعارض البحرية ونحوها.",
          "level": 0
        }
      ],
      "amendments": [],
      "heading_context": []
    },
    {
      "number": 3,
      "number_text": "المادة الثالثة",
      "text": "المادة الثالثة:  نطاق التطبيق\nتطبق أحكام هذه الضوابط والإجراءات على المالك والطاقم والركاب والوكيل الملاحي السياحي ومشغلي المراسي السياحية البحرية لليخوت الزائرة في النطاق الجغرافي وفقاً للائحة التنظيمية والضوابط والإجراءات والتعليمات والتعاميم ذات العلاقة الصادرة عن الهيئة.",
      "original_text": "المادة الثالثة:  نطاق التطبيق\nتطبق أحكام هذه الضوابط والإجراءات على المالك والطاقم والركاب والوكيل الملاحي السياحي ومشغلي المراسي السياحية البحرية لليخوت الزائرة في النطاق الجغرافي وفقاً للائحة التنظيمية والضوابط والإجراءات والتعليمات والتعاميم ذات العلاقة الصادرة عن الهيئة.",
      "status": "active",
      "paragraphs": [
        {
          "marker": "",
          "text": "المادة الثالثة:  نطاق التطبيق",
          "level": 0
        },
        {
          "marker": "",
          "text": "تطبق أحكام هذه الضوابط والإجراءات على المالك والطاقم والركاب والوكيل الملاحي السياحي ومشغلي المراسي السياحية البحرية لليخوت الزائرة في النطاق الجغرافي وفقاً للائحة التنظيمية والضوابط والإجراءات والتعليمات والتعاميم ذات العلاقة الصادرة عن الهيئة.",
          "level": 0
        }
      ],
      "amendments": [],
      "heading_context": []
    },
    {
      "number": 4,
      "number_text": "المادة الرابعة",
      "text": "المادة الرابعة:  أحكام عامة\nيجب على اليخت الزائر الذي يرغب في الدخول و/أو الزيارة و/أو التنقل في النطاق الجغرافي الالتزام بما يلي:\n1- تعيين وتفويض وكيل ملاحي سياحي لليخت قبل دخول النطاق الجغرافي، ويكون هو الممثل الرسمي لليخت بين اليخت والهيئة والجهات ذات العلاقة.\n2- الحصول على الترخيص الفني (السياحي الترفيهي) من الهيئة والترخيص الملاحي من الهيئة العامة للنقل قبل دخول النطاق الجغرافي، والذي يجب أن يظل سارياً طوال مدة إقامة اليخت الزائر في النطاق الجغرافي.\n3- يجب على الوكيل الملاحي السياحي أن يقوم بمسؤولياته نيابة عن اليخت الزائر بأعلى معايير الجودة، بالإضافة إلى أي مسؤوليات أخرى منصوص عليها في اللائحة التنظيمية للوكيل الملاحي السياحي وضوابطها وإجراءاتها الصادرة عن الهيئة.\n4- حيازة وثيقة تأمين سارية المفعول طوال مدة إقامة اليخت الزائر تشمل التأمين على المسؤولية تجاه الغير، وعلى الهيكل والآلات وإزالة الحطام بما في ذلك الأضرار التي تلحق بالأرصفة الثابتة أو العائمة أو الأضرار البيئية والتلوث الزيتي.\n5- عدم ممارسة أي نشاط تجاري من قبل اليخت الزائر قبل الحصول على التراخيص والتصاريح اللازمة من الهيئة يخوّله بذلك.\n6- حصول جميع الركاب وأفراد الطاقم على متن اليخت على تأشيرات صالحة لدخول المملكة.\n7- تعيين وكيل ملاحي سياحي لا يُعفِي المالك أو رُبَّان اليخت الزائر من مسؤولياتهم والتزاماتهم بموجب اللائحة التنظيمية والضوابط والإجراءات والتعليمات والتعاميم ذات العلاقة.\n8- الإبلاغ فوراً عن أي تغيير في التفاصيل والمستندات المقدمة في طلب الترخيص الفني (السياحي الترفيهي).",
      "original_text": "المادة الرابعة:  أحكام عامة\nيجب على اليخت الزائر الذي يرغب في الدخول و/أو الزيارة و/أو التنقل في النطاق الجغرافي الالتزام بما يلي:\n1- تعيين وتفويض وكيل ملاحي سياحي لليخت قبل دخول النطاق الجغرافي، ويكون هو الممثل الرسمي لليخت بين اليخت والهيئة والجهات ذات العلاقة.\n2- الحصول على الترخيص الفني (السياحي الترفيهي) من الهيئة والترخيص الملاحي من الهيئة العامة للنقل قبل دخول النطاق الجغرافي، والذي يجب أن يظل سارياً طوال مدة إقامة اليخت الزائر في النطاق الجغرافي.\n3- يجب على الوكيل الملاحي السياحي أن يقوم بمسؤولياته نيابة عن اليخت الزائر بأعلى معايير الجودة، بالإضافة إلى أي مسؤوليات أخرى منصوص عليها في اللائحة التنظيمية للوكيل الملاحي السياحي وضوابطها وإجراءاتها الصادرة عن الهيئة.\n4- حيازة وثيقة تأمين سارية المفعول طوال مدة إقامة اليخت الزائر تشمل التأمين على المسؤولية تجاه الغير، وعلى الهيكل والآلات وإزالة الحطام بما في ذلك الأضرار التي تلحق بالأرصفة الثابتة أو العائمة أو الأضرار البيئية والتلوث الزيتي.\n5- عدم ممارسة أي نشاط تجاري من قبل اليخت الزائر قبل الحصول على التراخيص والتصاريح اللازمة من الهيئة يخوّله بذلك.\n6- حصول جميع الركاب وأفراد الطاقم على متن اليخت على تأشيرات صالحة لدخول المملكة.\n7- تعيين وكيل ملاحي سياحي لا يُعفِي المالك أو رُبَّان اليخت الزائر من مسؤولياتهم والتزاماتهم بموجب اللائحة التنظيمية والضوابط والإجراءات والتعليمات والتعاميم ذات العلاقة.\n8- الإبلاغ فوراً عن أي تغيير في التفاصيل والمستندات المقدمة في طلب الترخيص الفني (السياحي الترفيهي).",
      "status": "active",
      "paragraphs": [
        {
          "marker": "",
          "text": "المادة الرابعة:  أحكام عامة",
          "level": 0
        },
        {
          "marker": "",
          "text": "يجب على اليخت الزائر الذي يرغب في الدخول و/أو الزيارة و/أو التنقل في النطاق الجغرافي الالتزام بما يلي:",
          "level": 0
        },
        {
          "marker": "1-",
          "text": "تعيين وتفويض وكيل ملاحي سياحي لليخت قبل دخول النطاق الجغرافي، ويكون هو الممثل الرسمي لليخت بين اليخت والهيئة والجهات ذات العلاقة.",
          "level": 1
        },
        {
          "marker": "2-",
          "text": "الحصول على الترخيص الفني (السياحي الترفيهي) من الهيئة والترخيص الملاحي من الهيئة العامة للنقل قبل دخول النطاق الجغرافي، والذي يجب أن يظل سارياً طوال مدة إقامة اليخت الزائر في النطاق الجغرافي.",
          "level": 1
        },
        {
          "marker": "3-",
          "text": "يجب على الوكيل الملاحي السياحي أن يقوم بمسؤولياته نيابة عن اليخت الزائر بأعلى معايير الجودة، بالإضافة إلى أي مسؤوليات أخرى منصوص عليها في اللائحة التنظيمية للوكيل الملاحي السياحي وضوابطها وإجراءاتها الصادرة عن الهيئة.",
          "level": 1
        },
        {
          "marker": "4-",
          "text": "حيازة وثيقة تأمين سارية المفعول طوال مدة إقامة اليخت الزائر تشمل التأمين على المسؤولية تجاه الغير، وعلى الهيكل والآلات وإزالة الحطام بما في ذلك الأضرار التي تلحق بالأرصفة الثابتة أو العائمة أو الأضرار البيئية والتلوث الزيتي.",
          "level": 1
        },
        {
          "marker": "5-",
          "text": "عدم ممارسة أي نشاط تجاري من قبل اليخت الزائر قبل الحصول على التراخيص والتصاريح اللازمة من الهيئة يخوّله بذلك.",
          "level": 1
        },
        {
          "marker": "6-",
          "text": "حصول جميع الركاب وأفراد الطاقم على متن اليخت على تأشيرات صالحة لدخول المملكة.",
          "level": 1
        },
        {
          "marker": "7-",
          "text": "تعيين وكيل ملاحي سياحي لا يُعفِي المالك أو رُبَّان اليخت الزائر من مسؤولياتهم والتزاماتهم بموجب اللائحة التنظيمية والضوابط والإجراءات والتعليمات والتعاميم ذات العلاقة.",
          "level": 1
        },
        {
          "marker": "8-",
          "text": "الإبلاغ فوراً عن أي تغيير في التفاصيل والمستندات المقدمة في طلب الترخيص الفني (السياحي الترفيهي).",
          "level": 1
        }
      ],
      "amendments": [],
      "heading_context": []
    },
    {
      "number": 5,
      "number_text": "المادة الخامسة",
      "text": "المادة الخامسة:  إجراءات التقديم على تصريح المرور\n1- يجب على الوكيل الملاحي السياحي المفوض تقديم طلب إلكتروني عبر المنصة الإلكترونية وإدخال المعلومات التالية:\n‌أ- شهادة التسجيل لليخت الزائر.\n‌ب- قائمة بأفراد الطاقم والركاب.\n‌ج- وثيقة تأمين شامل سارية المفعول في النطاق الجغرافي، المسؤولية تجاه الغير، وعلى الهيكل والآلات وإزالة الحطام بما في ذلك الأضرار التي تلحق بالأرصفة الثابتة أو العائمة أو الأضرار البيئية والتلوث الزيتي.\n‌د- تحديد الغرض من زيارة اليخت إلى النطاق الجغرافي والذي قد يشمل تغيير الطاقم، أو الصيانة، أو التزود بالوقود، أو الحصول على الإمدادات.\n2- تصدر الهيئة تصريح المرور لمدة (4) أيام، وفي حال الحاجة إلى تجاوز هذه المدة يتوجب التقديم على الترخيص الفني (السياحي الترفيهي).",
      "original_text": "المادة الخامسة:  إجراءات التقديم على تصريح المرور\n1- يجب على الوكيل الملاحي السياحي المفوض تقديم طلب إلكتروني عبر المنصة الإلكترونية وإدخال المعلومات التالية:\n‌أ- شهادة التسجيل لليخت الزائر.\n‌ب- قائمة بأفراد الطاقم والركاب.\n‌ج- وثيقة تأمين شامل سارية المفعول في النطاق الجغرافي، المسؤولية تجاه الغير، وعلى الهيكل والآلات وإزالة الحطام بما في ذلك الأضرار التي تلحق بالأرصفة الثابتة أو العائمة أو الأضرار البيئية والتلوث الزيتي.\n‌د- تحديد الغرض من زيارة اليخت إلى النطاق الجغرافي والذي قد يشمل تغيير الطاقم، أو الصيانة، أو التزود بالوقود، أو الحصول على الإمدادات.\n2- تصدر الهيئة تصريح المرور لمدة (4) أيام، وفي حال الحاجة إلى تجاوز هذه المدة يتوجب التقديم على الترخيص الفني (السياحي الترفيهي).",
      "status": "active",
      "paragraphs": [
        {
          "marker": "",
          "text": "المادة الخامسة:  إجراءات التقديم على تصريح المرور",
          "level": 0
        },
        {
          "marker": "1-",
          "text": "يجب على الوكيل الملاحي السياحي المفوض تقديم طلب إلكتروني عبر المنصة الإلكترونية وإدخال المعلومات التالية:",
          "level": 1
        },
        {
          "marker": "",
          "text": "‌أ- شهادة التسجيل لليخت الزائر.",
          "level": 0
        },
        {
          "marker": "",
          "text": "‌ب- قائمة بأفراد الطاقم والركاب.",
          "level": 0
        },
        {
          "marker": "",
          "text": "‌ج- وثيقة تأمين شامل سارية المفعول في النطاق الجغرافي، المسؤولية تجاه الغير، وعلى الهيكل والآلات وإزالة الحطام بما في ذلك الأضرار التي تلحق بالأرصفة الثابتة أو العائمة أو الأضرار البيئية والتلوث الزيتي.",
          "level": 0
        },
        {
          "marker": "",
          "text": "‌د- تحديد الغرض من زيارة اليخت إلى النطاق الجغرافي والذي قد يشمل تغيير الطاقم، أو الصيانة، أو التزود بالوقود، أو الحصول على الإمدادات.",
          "level": 0
        },
        {
          "marker": "2-",
          "text": "تصدر الهيئة تصريح المرور لمدة (4) أيام، وفي حال الحاجة إلى تجاوز هذه المدة يتوجب التقديم على الترخيص الفني (السياحي الترفيهي).",
          "level": 1
        }
      ],
      "amendments": [],
      "heading_context": []
    },
    {
      "number": 6,
      "number_text": "المادة السادسة",
      "text": "المادة السادسة:  إجراءات التقديم على الترخيص الفني (السياحي الترفيهي)\n1- يجب على الوكيل الملاحي السياحي المفوض تقديم طلب إلكتروني عبر المنصة الإلكترونية مع إرفاق نسخة واضحة من المستندات الداعمة -باللغة العربية أو الإنجليزية- وفقاً للآتي:\n‌أ- نسخة من شهادة تسجيل اليخت الزائر.\n‌ب- نسخة من تقرير الفحص العام (يجب ألا يكون قد مضى على إصداره سنة عند تقديم الطلب).\n‌ج- نسخة من شهادات الامتثال الصادرة من دولة العلم أو هيئة التصنيف التي تدل على صلاحية اليخت الزائر للإبحار.\n‌د- نسخة من قائمة بيانات الطاقم وقائمة الركاب.\n‌هـ- نسخة من جوازات سفر قبطان وطاقم اليخت الزائر.\n‌و- نسخة من البيانات التعريفية لمالك اليخت الزائر.\n‌ز- نسخة من عقد الرصيف.\n‌ح- وثيقة تأمين شامل سارية المفعول في النطاق الجغرافي، تغطي المسؤولية المدنية الكاملة للمؤمن والناشئة عن الوفاة أو الإصابة البدنية أو الأضرار المادية التي تنتج عن السفينة وإزالة الحطام.\n‌ط- نسخة من شهادات الرُبَّان والطاقم.\n‌ي- نسخة من رخصة اللاسلكي للسفينة (Ship Station License) موضح فيها الأجهزة الأساسية (AIS، Marine VHF, EPIRB).\n‌ك- مُستند يوضّح خط سير اليخت المخطط له ومدة إقامة اليخت ومناطق الإبحار داخل النطاق الجغرافي.\n‌ل- الإفصاح عن جميع ملحقات اليخت وعلى سبيل المثال: الألعاب المائية، الدرون، الدراجات المائية، الواسطة الجوي (الهليكوبتر)، والحصول على التراخيص والتصاريح اللازمة من الجهات ذات العلاقة.\n‌م- الإفصاح عن جميع الأنشطة البحرية التي سيتم ممارستها في النطاق الجغرافي، على سبيل المثال الغوص، الصيد الترفيهي.\n‌ن- تقديم أي متطلبات أخرى ترى الهيئة أنها ضرورية للحصول على الترخيص الفني (السياحي الترفيهي).\n2- في حال عدم توفر أي مستند باللغتين المذكورتين، يمكن تقديم نسخة مترجمة إلى العربية عبر مترجم معتمد مع نسخة من المستند الأصلي.\n3- توافق الهيئة على طلب الترخيص الفني (السياحي الترفيهي) بعد صدور الترخيص الملاحي من الهيئة العامة للنقل خلال مدة لا تتجاوز (24) أربعاً وعشرين ساعة من اكتمال الطلب.\n4- للهيئة الحق في إضافة أو إلغاء أي من معايير الأهلية أو المستندات المطلوبة لطلب الترخيص الفني (السياحي الترفيهي) بناءً على تقييمها لمُقدم الطلب.\n5- تقوم الهيئة في حال رفض الترخيص بإشعار المتقدم بذلك، وللمتقدم إعادة تقديم الطلب بعد استيفاء المتطلبات.",
      "original_text": "المادة السادسة:  إجراءات التقديم على الترخيص الفني (السياحي الترفيهي)\n1- يجب على الوكيل الملاحي السياحي المفوض تقديم طلب إلكتروني عبر المنصة الإلكترونية مع إرفاق نسخة واضحة من المستندات الداعمة -باللغة العربية أو الإنجليزية- وفقاً للآتي:\n‌أ- نسخة من شهادة تسجيل اليخت الزائر.\n‌ب- نسخة من تقرير الفحص العام (يجب ألا يكون قد مضى على إصداره سنة عند تقديم الطلب).\n‌ج- نسخة من شهادات الامتثال الصادرة من دولة العلم أو هيئة التصنيف التي تدل على صلاحية اليخت الزائر للإبحار.\n‌د- نسخة من قائمة بيانات الطاقم وقائمة الركاب.\n‌هـ- نسخة من جوازات سفر قبطان وطاقم اليخت الزائر.\n‌و- نسخة من البيانات التعريفية لمالك اليخت الزائر.\n‌ز- نسخة من عقد الرصيف.\n‌ح- وثيقة تأمين شامل سارية المفعول في النطاق الجغرافي، تغطي المسؤولية المدنية الكاملة للمؤمن والناشئة عن الوفاة أو الإصابة البدنية أو الأضرار المادية التي تنتج عن السفينة وإزالة الحطام.\n‌ط- نسخة من شهادات الرُبَّان والطاقم.\n‌ي- نسخة من رخصة اللاسلكي للسفينة (Ship Station License) موضح فيها الأجهزة الأساسية (AIS، Marine VHF, EPIRB).\n‌ك- مُستند يوضّح خط سير اليخت المخطط له ومدة إقامة اليخت ومناطق الإبحار داخل النطاق الجغرافي.\n‌ل- الإفصاح عن جميع ملحقات اليخت وعلى سبيل المثال: الألعاب المائية، الدرون، الدراجات المائية، الواسطة الجوي (الهليكوبتر)، والحصول على التراخيص والتصاريح اللازمة من الجهات ذات العلاقة.\n‌م- الإفصاح عن جميع الأنشطة البحرية التي سيتم ممارستها في النطاق الجغرافي، على سبيل المثال الغوص، الصيد الترفيهي.\n‌ن- تقديم أي متطلبات أخرى ترى الهيئة أنها ضرورية للحصول على الترخيص الفني (السياحي الترفيهي).\n2- في حال عدم توفر أي مستند باللغتين المذكورتين، يمكن تقديم نسخة مترجمة إلى العربية عبر مترجم معتمد مع نسخة من المستند الأصلي.\n3- توافق الهيئة على طلب الترخيص الفني (السياحي الترفيهي) بعد صدور الترخيص الملاحي من الهيئة العامة للنقل خلال مدة لا تتجاوز (24) أربعاً وعشرين ساعة من اكتمال الطلب.\n4- للهيئة الحق في إضافة أو إلغاء أي من معايير الأهلية أو المستندات المطلوبة لطلب الترخيص الفني (السياحي الترفيهي) بناءً على تقييمها لمُقدم الطلب.\n5- تقوم الهيئة في حال رفض الترخيص بإشعار المتقدم بذلك، وللمتقدم إعادة تقديم الطلب بعد استيفاء المتطلبات.",
      "status": "active",
      "paragraphs": [
        {
          "marker": "",
          "text": "المادة السادسة:  إجراءات التقديم على الترخيص الفني (السياحي الترفيهي)",
          "level": 0
        },
        {
          "marker": "1-",
          "text": "يجب على الوكيل الملاحي السياحي المفوض تقديم طلب إلكتروني عبر المنصة الإلكترونية مع إرفاق نسخة واضحة من المستندات الداعمة -باللغة العربية أو الإنجليزية- وفقاً للآتي:",
          "level": 1
        },
        {
          "marker": "",
          "text": "‌أ- نسخة من شهادة تسجيل اليخت الزائر.",
          "level": 0
        },
        {
          "marker": "",
          "text": "‌ب- نسخة من تقرير الفحص العام (يجب ألا يكون قد مضى على إصداره سنة عند تقديم الطلب).",
          "level": 0
        },
        {
          "marker": "",
          "text": "‌ج- نسخة من شهادات الامتثال الصادرة من دولة العلم أو هيئة التصنيف التي تدل على صلاحية اليخت الزائر للإبحار.",
          "level": 0
        },
        {
          "marker": "",
          "text": "‌د- نسخة من قائمة بيانات الطاقم وقائمة الركاب.",
          "level": 0
        },
        {
          "marker": "",
          "text": "‌هـ- نسخة من جوازات سفر قبطان وطاقم اليخت الزائر.",
          "level": 0
        },
        {
          "marker": "",
          "text": "‌و- نسخة من البيانات التعريفية لمالك اليخت الزائر.",
          "level": 0
        },
        {
          "marker": "",
          "text": "‌ز- نسخة من عقد الرصيف.",
          "level": 0
        },
        {
          "marker": "",
          "text": "‌ح- وثيقة تأمين شامل سارية المفعول في النطاق الجغرافي، تغطي المسؤولية المدنية الكاملة للمؤمن والناشئة عن الوفاة أو الإصابة البدنية أو الأضرار المادية التي تنتج عن السفينة وإزالة الحطام.",
          "level": 0
        },
        {
          "marker": "",
          "text": "‌ط- نسخة من شهادات الرُبَّان والطاقم.",
          "level": 0
        },
        {
          "marker": "",
          "text": "‌ي- نسخة من رخصة اللاسلكي للسفينة (Ship Station License) موضح فيها الأجهزة الأساسية (AIS، Marine VHF, EPIRB).",
          "level": 0
        },
        {
          "marker": "",
          "text": "‌ك- مُستند يوضّح خط سير اليخت المخطط له ومدة إقامة اليخت ومناطق الإبحار داخل النطاق الجغرافي.",
          "level": 0
        },
        {
          "marker": "",
          "text": "‌ل- الإفصاح عن جميع ملحقات اليخت وعلى سبيل المثال: الألعاب المائية، الدرون، الدراجات المائية، الواسطة الجوي (الهليكوبتر)، والحصول على التراخيص والتصاريح اللازمة من الجهات ذات العلاقة.",
          "level": 0
        },
        {
          "marker": "",
          "text": "‌م- الإفصاح عن جميع الأنشطة البحرية التي سيتم ممارستها في النطاق الجغرافي، على سبيل المثال الغوص، الصيد الترفيهي.",
          "level": 0
        },
        {
          "marker": "",
          "text": "‌ن- تقديم أي متطلبات أخرى ترى الهيئة أنها ضرورية للحصول على الترخيص الفني (السياحي الترفيهي).",
          "level": 0
        },
        {
          "marker": "2-",
          "text": "في حال عدم توفر أي مستند باللغتين المذكورتين، يمكن تقديم نسخة مترجمة إلى العربية عبر مترجم معتمد مع نسخة من المستند الأصلي.",
          "level": 1
        },
        {
          "marker": "3-",
          "text": "توافق الهيئة على طلب الترخيص الفني (السياحي الترفيهي) بعد صدور الترخيص الملاحي من الهيئة العامة للنقل خلال مدة لا تتجاوز (24) أربعاً وعشرين ساعة من اكتمال الطلب.",
          "level": 1
        },
        {
          "marker": "4-",
          "text": "للهيئة الحق في إضافة أو إلغاء أي من معايير الأهلية أو المستندات المطلوبة لطلب الترخيص الفني (السياحي الترفيهي) بناءً على تقييمها لمُقدم الطلب.",
          "level": 1
        },
        {
          "marker": "5-",
          "text": "تقوم الهيئة في حال رفض الترخيص بإشعار المتقدم بذلك، وللمتقدم إعادة تقديم الطلب بعد استيفاء المتطلبات.",
          "level": 1
        }
      ],
      "amendments": [],
      "heading_context": []
    },
    {
      "number": 7,
      "number_text": "المادة السابعة",
      "text": "المادة السابعة:  الشروط والمتطلبات العامة لإصدار الترخيص الفني (السياحي الترفيهي)\n1- يلتزم اليخت الزائر خلال مدة إقامته في النطاق الجغرافي بالامتثال للتعليمات ذات العلاقة بما في ذلك على سبيل المثال:\nأ- أي متطلبات فنية منصوص عليها في اللائحة التنظيمية لليخوت الزائرة أو ما تصدره الهيئة من تعليمات أو تعاميم.\nب- إبقاء اليخت الزائر في حالة جيدة وصالحة للإبحار، وبما يتوافق مع جميع الخطط والجداول الزمنية الموصى بها من قبل الشركة المصنّعة وصلاحية الشهادات المطلوبة، كما هو مطلوب من قبل دولة العلم.\nج- الالتزام بالحد الأقصى لعدد الركاب المحدد في شهادة المسح التجاري أو شهادة التسجيل لليخوت الضخمة بحد أقصى (12) راكباً أو (36) راكباً، حسب ما ينطبق على متطلبات دولة علم اليخت الزائر، ويُستثنى -بعد التنسيق مع الهيئة- الأشخاص الإضافيون على متن اليخت أثناء المناسبات الاجتماعية عندما يكون اليخت بجانب الرصيف أو منطقة الرسو التي يديرها ويتحكم بها المرسى البحري السياحي.\nد- توفير سترات النجاة بما يتناسب مع حمولة الركاب المسموح بها، بالإضافة إلى عدد احتياطي يساوي 10% من عدد السترات، على أن تحمل كل سترة نجاة اسم اليخت وتحتوي على صافرة وإضاءة ليلية وشريط عاكس؛ كما يجب أن تكون سترات نجاة الأطفال في الأماكن المخصصة لها، ومطابقة للمواصفات الدولية.\nهـ- إصلاح أو استبدال معدات السلامة والملاحة، والاتصالات اللاسلكية، ومعدات الكشف عن الحرائق ومكافحتها، أو أي معدات أخرى قد تتطلب صيانة أو استبدالاً.\nو- عدم السماح بممارسة أنشطة الغوص إلا بعد استيفاء المتطلبات الواردة في اللوائح ذات الصلة من الجهات ذات العلاقة.\nز- عدم السماح بممارسة أي نشاط للسباحة أو استخدام الألعاب المائية من غروب الشمس إلى شروقها.\n2- يجب أن يكون الترخيص الفني (السياحي الترفيهي) سارياً طيلة إقامة اليخت (حتى ستة أشهر)، ويجب على المالك أو الوكيل الملاحي السياحي لليخت الزائر تشغيله وفقاً لذلك.\n3- عند انتهاء صلاحية الترخيص الفني (السياحي الترفيهي)، يجوز لليخت الزائر البقاء في النطاق الجغرافي خلال فترة السماح التي لا تتجاوز مدة (72) اثنتين وسبعين ساعة كحد أقصى من تاريخ انتهاء صلاحية الترخيص.\n4- في حال الإخلال بأحد الاشتراطات أو المتطلبات، يحق للإدارة المختصة بالهيئة تعليق أو إلغاء الترخيص وإبلاغ الجهات ذات العلاقة بشكل فوري بذلك.",
      "original_text": "المادة السابعة:  الشروط والمتطلبات العامة لإصدار الترخيص الفني (السياحي الترفيهي)\n1- يلتزم اليخت الزائر خلال مدة إقامته في النطاق الجغرافي بالامتثال للتعليمات ذات العلاقة بما في ذلك على سبيل المثال:\nأ- أي متطلبات فنية منصوص عليها في اللائحة التنظيمية لليخوت الزائرة أو ما تصدره الهيئة من تعليمات أو تعاميم.\nب- إبقاء اليخت الزائر في حالة جيدة وصالحة للإبحار، وبما يتوافق مع جميع الخطط والجداول الزمنية الموصى بها من قبل الشركة المصنّعة وصلاحية الشهادات المطلوبة، كما هو مطلوب من قبل دولة العلم.\nج- الالتزام بالحد الأقصى لعدد الركاب المحدد في شهادة المسح التجاري أو شهادة التسجيل لليخوت الضخمة بحد أقصى (12) راكباً أو (36) راكباً، حسب ما ينطبق على متطلبات دولة علم اليخت الزائر، ويُستثنى -بعد التنسيق مع الهيئة- الأشخاص الإضافيون على متن اليخت أثناء المناسبات الاجتماعية عندما يكون اليخت بجانب الرصيف أو منطقة الرسو التي يديرها ويتحكم بها المرسى البحري السياحي.\nد- توفير سترات النجاة بما يتناسب مع حمولة الركاب المسموح بها، بالإضافة إلى عدد احتياطي يساوي 10% من عدد السترات، على أن تحمل كل سترة نجاة اسم اليخت وتحتوي على صافرة وإضاءة ليلية وشريط عاكس؛ كما يجب أن تكون سترات نجاة الأطفال في الأماكن المخصصة لها، ومطابقة للمواصفات الدولية.\nهـ- إصلاح أو استبدال معدات السلامة والملاحة، والاتصالات اللاسلكية، ومعدات الكشف عن الحرائق ومكافحتها، أو أي معدات أخرى قد تتطلب صيانة أو استبدالاً.\nو- عدم السماح بممارسة أنشطة الغوص إلا بعد استيفاء المتطلبات الواردة في اللوائح ذات الصلة من الجهات ذات العلاقة.\nز- عدم السماح بممارسة أي نشاط للسباحة أو استخدام الألعاب المائية من غروب الشمس إلى شروقها.\n2- يجب أن يكون الترخيص الفني (السياحي الترفيهي) سارياً طيلة إقامة اليخت (حتى ستة أشهر)، ويجب على المالك أو الوكيل الملاحي السياحي لليخت الزائر تشغيله وفقاً لذلك.\n3- عند انتهاء صلاحية الترخيص الفني (السياحي الترفيهي)، يجوز لليخت الزائر البقاء في النطاق الجغرافي خلال فترة السماح التي لا تتجاوز مدة (72) اثنتين وسبعين ساعة كحد أقصى من تاريخ انتهاء صلاحية الترخيص.\n4- في حال الإخلال بأحد الاشتراطات أو المتطلبات، يحق للإدارة المختصة بالهيئة تعليق أو إلغاء الترخيص وإبلاغ الجهات ذات العلاقة بشكل فوري بذلك.",
      "status": "active",
      "paragraphs": [
        {
          "marker": "",
          "text": "المادة السابعة:  الشروط والمتطلبات العامة لإصدار الترخيص الفني (السياحي الترفيهي)",
          "level": 0
        },
        {
          "marker": "1-",
          "text": "يلتزم اليخت الزائر خلال مدة إقامته في النطاق الجغرافي بالامتثال للتعليمات ذات العلاقة بما في ذلك على سبيل المثال:",
          "level": 1
        },
        {
          "marker": "أ-",
          "text": "أي متطلبات فنية منصوص عليها في اللائحة التنظيمية لليخوت الزائرة أو ما تصدره الهيئة من تعليمات أو تعاميم.",
          "level": 1
        },
        {
          "marker": "ب-",
          "text": "إبقاء اليخت الزائر في حالة جيدة وصالحة للإبحار، وبما يتوافق مع جميع الخطط والجداول الزمنية الموصى بها من قبل الشركة المصنّعة وصلاحية الشهادات المطلوبة، كما هو مطلوب من قبل دولة العلم.",
          "level": 1
        },
        {
          "marker": "ج-",
          "text": "الالتزام بالحد الأقصى لعدد الركاب المحدد في شهادة المسح التجاري أو شهادة التسجيل لليخوت الضخمة بحد أقصى (12) راكباً أو (36) راكباً، حسب ما ينطبق على متطلبات دولة علم اليخت الزائر، ويُستثنى -بعد التنسيق مع الهيئة- الأشخاص الإضافيون على متن اليخت أثناء المناسبات الاجتماعية عندما يكون اليخت بجانب الرصيف أو منطقة الرسو التي يديرها ويتحكم بها المرسى البحري السياحي.",
          "level": 1
        },
        {
          "marker": "د-",
          "text": "توفير سترات النجاة بما يتناسب مع حمولة الركاب المسموح بها، بالإضافة إلى عدد احتياطي يساوي 10% من عدد السترات، على أن تحمل كل سترة نجاة اسم اليخت وتحتوي على صافرة وإضاءة ليلية وشريط عاكس؛ كما يجب أن تكون سترات نجاة الأطفال في الأماكن المخصصة لها، ومطابقة للمواصفات الدولية.",
          "level": 1
        },
        {
          "marker": "",
          "text": "هـ- إصلاح أو استبدال معدات السلامة والملاحة، والاتصالات اللاسلكية، ومعدات الكشف عن الحرائق ومكافحتها، أو أي معدات أخرى قد تتطلب صيانة أو استبدالاً.",
          "level": 0
        },
        {
          "marker": "و-",
          "text": "عدم السماح بممارسة أنشطة الغوص إلا بعد استيفاء المتطلبات الواردة في اللوائح ذات الصلة من الجهات ذات العلاقة.",
          "level": 1
        },
        {
          "marker": "ز-",
          "text": "عدم السماح بممارسة أي نشاط للسباحة أو استخدام الألعاب المائية من غروب الشمس إلى شروقها.",
          "level": 1
        },
        {
          "marker": "2-",
          "text": "يجب أن يكون الترخيص الفني (السياحي الترفيهي) سارياً طيلة إقامة اليخت (حتى ستة أشهر)، ويجب على المالك أو الوكيل الملاحي السياحي لليخت الزائر تشغيله وفقاً لذلك.",
          "level": 1
        },
        {
          "marker": "3-",
          "text": "عند انتهاء صلاحية الترخيص الفني (السياحي الترفيهي)، يجوز لليخت الزائر البقاء في النطاق الجغرافي خلال فترة السماح التي لا تتجاوز مدة (72) اثنتين وسبعين ساعة كحد أقصى من تاريخ انتهاء صلاحية الترخيص.",
          "level": 1
        },
        {
          "marker": "4-",
          "text": "في حال الإخلال بأحد الاشتراطات أو المتطلبات، يحق للإدارة المختصة بالهيئة تعليق أو إلغاء الترخيص وإبلاغ الجهات ذات العلاقة بشكل فوري بذلك.",
          "level": 1
        }
      ],
      "amendments": [],
      "heading_context": []
    },
    {
      "number": 8,
      "number_text": "المادة الثامنة",
      "text": "المادة الثامنة:  إجراءات التقديم على تصريح رحلة سياحية\nيجب على الوكيل الملاحي السياحي المفوض تقديم طلب إلكتروني عبر المنصة الإلكترونية وإدخال المعلومات التالية:\n1- في حال كانت رحلة خاصة:\nأ- بيان بأسماء الطاقم والركاب ومعلوماتهم.\nب- تحديد مواقع ومسارات الرحلة.\nج- المدة الزمنية.\nد- تاريخ الرحلة.\nهـ- معلومات الواسطة البحرية.\nو- نقطة الذهاب والعودة.\nز- الغرض من الرحلة.\n2- في حال كانت رحلة تأجير، يجب تقديم المستندات الواردة في الفقرة (أ) و(ب) من الفقرة (1) من هذه المادة إلى عقد التأجير.\n3- يجب على مُشَغِّل المرسى البحري السياحي التأكد من مطابقة البيانات قبل مغادرة اليخت من المرسى البحري السياحي.",
      "original_text": "المادة الثامنة:  إجراءات التقديم على تصريح رحلة سياحية\nيجب على الوكيل الملاحي السياحي المفوض تقديم طلب إلكتروني عبر المنصة الإلكترونية وإدخال المعلومات التالية:\n1- في حال كانت رحلة خاصة:\nأ- بيان بأسماء الطاقم والركاب ومعلوماتهم.\nب- تحديد مواقع ومسارات الرحلة.\nج- المدة الزمنية.\nد- تاريخ الرحلة.\nهـ- معلومات الواسطة البحرية.\nو- نقطة الذهاب والعودة.\nز- الغرض من الرحلة.\n2- في حال كانت رحلة تأجير، يجب تقديم المستندات الواردة في الفقرة (أ) و(ب) من الفقرة (1) من هذه المادة إلى عقد التأجير.\n3- يجب على مُشَغِّل المرسى البحري السياحي التأكد من مطابقة البيانات قبل مغادرة اليخت من المرسى البحري السياحي.",
      "status": "active",
      "paragraphs": [
        {
          "marker": "",
          "text": "المادة الثامنة:  إجراءات التقديم على تصريح رحلة سياحية",
          "level": 0
        },
        {
          "marker": "",
          "text": "يجب على الوكيل الملاحي السياحي المفوض تقديم طلب إلكتروني عبر المنصة الإلكترونية وإدخال المعلومات التالية:",
          "level": 0
        },
        {
          "marker": "1-",
          "text": "في حال كانت رحلة خاصة:",
          "level": 1
        },
        {
          "marker": "أ-",
          "text": "بيان بأسماء الطاقم والركاب ومعلوماتهم.",
          "level": 1
        },
        {
          "marker": "ب-",
          "text": "تحديد مواقع ومسارات الرحلة.",
          "level": 1
        },
        {
          "marker": "ج-",
          "text": "المدة الزمنية.",
          "level": 1
        },
        {
          "marker": "د-",
          "text": "تاريخ الرحلة.",
          "level": 1
        },
        {
          "marker": "",
          "text": "هـ- معلومات الواسطة البحرية.",
          "level": 0
        },
        {
          "marker": "و-",
          "text": "نقطة الذهاب والعودة.",
          "level": 1
        },
        {
          "marker": "ز-",
          "text": "الغرض من الرحلة.",
          "level": 1
        },
        {
          "marker": "2-",
          "text": "في حال كانت رحلة تأجير، يجب تقديم المستندات الواردة في الفقرة (أ) و(ب) من الفقرة (1) من هذه المادة إلى عقد التأجير.",
          "level": 1
        },
        {
          "marker": "3-",
          "text": "يجب على مُشَغِّل المرسى البحري السياحي التأكد من مطابقة البيانات قبل مغادرة اليخت من المرسى البحري السياحي.",
          "level": 1
        }
      ],
      "amendments": [],
      "heading_context": []
    },
    {
      "number": 9,
      "number_text": "المادة التاسعة",
      "text": "المادة التاسعة:  إجراءات التقديم على تصريح المغادرة\n1- يجب على الوكيل الملاحي السياحي المفوض تقديم طلب إلكتروني عبر المنصة الإلكترونية وإدخال المعلومات التالية:\nأ- بيان بأسماء الطاقم والركاب ومعلوماتهم.\nب- تحديد نقطة الخروج.\nج- تاريخ المغادرة.\nد- وقت المغادرة.\nهـ- معلومات الواسطة البحرية.\nو- وجهة الوصول.\n2- بعد استيفاء كافة متطلبات ( (Port clearanceيجب على مُشَغِّل المرسى البحري السياحي التأكد من مطابقة البيانات وإصدار تصريح المغادرة.\n3- يُلغى الترخيص بمجرد مغادرة الواسطة البحرية النطاق الجغرافي حتى لو لم تنتهِ مدته، ويحق للهيئة الاستثناء من ذلك بحسب ما تقتضيه الحاجة.",
      "original_text": "المادة التاسعة:  إجراءات التقديم على تصريح المغادرة\n1- يجب على الوكيل الملاحي السياحي المفوض تقديم طلب إلكتروني عبر المنصة الإلكترونية وإدخال المعلومات التالية:\nأ- بيان بأسماء الطاقم والركاب ومعلوماتهم.\nب- تحديد نقطة الخروج.\nج- تاريخ المغادرة.\nد- وقت المغادرة.\nهـ- معلومات الواسطة البحرية.\nو- وجهة الوصول.\n2- بعد استيفاء كافة متطلبات ( (Port clearanceيجب على مُشَغِّل المرسى البحري السياحي التأكد من مطابقة البيانات وإصدار تصريح المغادرة.\n3- يُلغى الترخيص بمجرد مغادرة الواسطة البحرية النطاق الجغرافي حتى لو لم تنتهِ مدته، ويحق للهيئة الاستثناء من ذلك بحسب ما تقتضيه الحاجة.",
      "status": "active",
      "paragraphs": [
        {
          "marker": "",
          "text": "المادة التاسعة:  إجراءات التقديم على تصريح المغادرة",
          "level": 0
        },
        {
          "marker": "1-",
          "text": "يجب على الوكيل الملاحي السياحي المفوض تقديم طلب إلكتروني عبر المنصة الإلكترونية وإدخال المعلومات التالية:",
          "level": 1
        },
        {
          "marker": "أ-",
          "text": "بيان بأسماء الطاقم والركاب ومعلوماتهم.",
          "level": 1
        },
        {
          "marker": "ب-",
          "text": "تحديد نقطة الخروج.",
          "level": 1
        },
        {
          "marker": "ج-",
          "text": "تاريخ المغادرة.",
          "level": 1
        },
        {
          "marker": "د-",
          "text": "وقت المغادرة.",
          "level": 1
        },
        {
          "marker": "",
          "text": "هـ- معلومات الواسطة البحرية.",
          "level": 0
        },
        {
          "marker": "و-",
          "text": "وجهة الوصول.",
          "level": 1
        },
        {
          "marker": "2-",
          "text": "بعد استيفاء كافة متطلبات ( (Port clearanceيجب على مُشَغِّل المرسى البحري السياحي التأكد من مطابقة البيانات وإصدار تصريح المغادرة.",
          "level": 1
        },
        {
          "marker": "3-",
          "text": "يُلغى الترخيص بمجرد مغادرة الواسطة البحرية النطاق الجغرافي حتى لو لم تنتهِ مدته، ويحق للهيئة الاستثناء من ذلك بحسب ما تقتضيه الحاجة.",
          "level": 1
        }
      ],
      "amendments": [],
      "heading_context": []
    },
    {
      "number": 10,
      "number_text": "المادة العاشرة",
      "text": "المادة العاشرة:  قواعد السلامة والملاحة الآمنة وحماية البيئة البحرية\n1- يجب على اليخت الزائر وطاقمه الالتزام التام بجميع الأنظمة واللوائح والاتفاقيات الدولية البحرية المعمول بها في المملكة.\n2- الالتزام بتعليمات الملاحة والسلامة الخاصة بالمراسي البحرية السياحية والموانئ.\n3- الحفاظ بشكل مستمر على جهاز نظام التعرف الآلي (AIS) لليخت الزائر في حالة تشغيلية خلال فترة التواجد في النطاق الجغرافي.\n4- يجب على اليخت الزائر أن تقتصر أنشطته الملاحية والإرساء على المناطق المخصصة والمصرحة له من قبل الهيئة أو المرسى البحري السياحي وعدم دخول المناطق المحظورة أو المحمية أو غير المصرحة له.\n5- يجب الالتزام بالسرعة المحددة وعدم استخدام السرعة المفرطة التي قد تتسبب في وقوع حادث أو تسبب تموج مياه البحر مما يؤدي لإلحاق الضرر بأي يخت آخر أو سفينة أو ملكية أخرى.\n6- يجب أن يكون اليخت الزائر مجهزاً بمعدات السلامة والملاحة، والاتصالات اللاسلكية، ومعدات حماية البيئة وفقاً للمتطلبات والاتفاقيات والمعاهدات الدولية المعمول بها في المملكة.\n7- يجب أن يكون اليخت الزائر مجهزاً بمعدات الكشف عن الحرائق ومعدات مكافحة الحرائق.\n8- يجب أن يتوفر في اليخت الزائر معدات السلامة اللازمة، بما في ذلك سترات وطوق النجاة، وطفايات الحريق، وإشارات الاستغاثة، ولوازم الإسعافات الأولية، وذلك بحسب حجم اليخت وسعته.\n9- يجب إجراء تدريبات مكافحة الحرائق والطوارئ بانتظام مع التأكد من أن جميع أفراد الطاقم على دراية بإجراءات الطوارئ، وطرق الإخلاء، وبروتوكولات السلامة.\n10- يمنع منعاً باتاً تصريف أي مخلفات، بما في ذلك مياه الصرف الصحي، والنفايات، والمواد الزيتية في النطاق الجغرافي.\n11- تعزيز الممارسات البيئية المستدامة والتقليل من استخدام المواد البلاستيكية ذات الاستخدام الواحد على متن اليخت الزائر.\n12- يمنع استخدام واقي الشمس الضار بالشعاب المرجانية والبيئة البحرية، ويمكن استبداله بأي منتجات أخرى عضوية صديقة للبيئة.\n13- الالتزام بالمحافظة على مسافة آمنة من الموائل البحرية عند الإبحار أو الرسو بجانبها.\n14- يجب أن يتم الإرساء بعناية فائقة، واستخدام العوامات البحرية المخصصة لتجنب الإضرار بالنظم البيئية تحت الماء وعدم الإرساء في مناطق محظورة أو محمية.\n15- يجب الاحتفاظ بتصريح رحلة سياحية عند مغادرة المرسى البحري السياحي.\n16- التأكد من أن استخدام الألعاب المائية يتوافق مع المعايير العمرية المناسبة أو المعتمدة، والقيود المفروضة على المعايير المحددة لنسبة الضوضاء، وأن تجهز بمعدات السلامة المناسبة، وأن يشرف عليها طاقم مدرب.\n17- التأكد من عدم بقاء أي ألعاب مائية ثابتة في عرض البحر أو تركها في أي منطقة غير مصرح بها.\n18- يُحظر التخلص من مياه الصابورة (التوازن) أو النفايات الصلبة والسائلة إلا في المرافق المخصصة للمرسى البحري السياحي.\n19- يُحظر إجراء سباقات من أي نوع كان إلا في المناطق المخصصة لذلك والمصرح بها من قبل الجهات ذات العلاقة بالمملكة.\n20- يُحظر إرساء أو إبحار اليخت الزائر أو أي ألعاب مائية في المناطق المحمية.\n21- في حال صيد الأسماك فيكون ذلك لغرض الاستهلاك الشخصي فقط، ووفق الضوابط التي تضعها الجهة المنظمة لنشاط الصيد الترفيهي حسب النوع والمواسم والكميات وأساليب الصيد، كما يحظر تداولها وبيعها في جميع أسواق ومحلات بيع الأسماك على كافة أنواعها.\n22- عدم صيد أسماك القرش أو الدلافين أو أي أسماك أخرى محمية أو محظور اصطيادها مهما كان نوعها وحجمها على مدار العام.\n23- عدم استخدام الشباك، أو بنادق الصيد البحري أو أي أدوات ومعدات صيد أخرى محظورة.\n24- الالتزام بالأنظمة واللوائح والتعليمات ذات العلاقة لحماية البيئة البحرية، والثروات المائية الحيّة، والحفاظ على التنوع البيولوجي البحري.\n25- عند مغادرة النطاق الجغرافي، يلتزم رُبَّان اليخت الزائر والوكيل الملاحي السياحي بتسجيل خروجه لدى أقرب ميناء أو مرسى بحري سياحي وطلب إلغاء الترخيص الفني (السياحي والترفيهي).",
      "original_text": "المادة العاشرة:  قواعد السلامة والملاحة الآمنة وحماية البيئة البحرية\n1- يجب على اليخت الزائر وطاقمه الالتزام التام بجميع الأنظمة واللوائح والاتفاقيات الدولية البحرية المعمول بها في المملكة.\n2- الالتزام بتعليمات الملاحة والسلامة الخاصة بالمراسي البحرية السياحية والموانئ.\n3- الحفاظ بشكل مستمر على جهاز نظام التعرف الآلي (AIS) لليخت الزائر في حالة تشغيلية خلال فترة التواجد في النطاق الجغرافي.\n4- يجب على اليخت الزائر أن تقتصر أنشطته الملاحية والإرساء على المناطق المخصصة والمصرحة له من قبل الهيئة أو المرسى البحري السياحي وعدم دخول المناطق المحظورة أو المحمية أو غير المصرحة له.\n5- يجب الالتزام بالسرعة المحددة وعدم استخدام السرعة المفرطة التي قد تتسبب في وقوع حادث أو تسبب تموج مياه البحر مما يؤدي لإلحاق الضرر بأي يخت آخر أو سفينة أو ملكية أخرى.\n6- يجب أن يكون اليخت الزائر مجهزاً بمعدات السلامة والملاحة، والاتصالات اللاسلكية، ومعدات حماية البيئة وفقاً للمتطلبات والاتفاقيات والمعاهدات الدولية المعمول بها في المملكة.\n7- يجب أن يكون اليخت الزائر مجهزاً بمعدات الكشف عن الحرائق ومعدات مكافحة الحرائق.\n8- يجب أن يتوفر في اليخت الزائر معدات السلامة اللازمة، بما في ذلك سترات وطوق النجاة، وطفايات الحريق، وإشارات الاستغاثة، ولوازم الإسعافات الأولية، وذلك بحسب حجم اليخت وسعته.\n9- يجب إجراء تدريبات مكافحة الحرائق والطوارئ بانتظام مع التأكد من أن جميع أفراد الطاقم على دراية بإجراءات الطوارئ، وطرق الإخلاء، وبروتوكولات السلامة.\n10- يمنع منعاً باتاً تصريف أي مخلفات، بما في ذلك مياه الصرف الصحي، والنفايات، والمواد الزيتية في النطاق الجغرافي.\n11- تعزيز الممارسات البيئية المستدامة والتقليل من استخدام المواد البلاستيكية ذات الاستخدام الواحد على متن اليخت الزائر.\n12- يمنع استخدام واقي الشمس الضار بالشعاب المرجانية والبيئة البحرية، ويمكن استبداله بأي منتجات أخرى عضوية صديقة للبيئة.\n13- الالتزام بالمحافظة على مسافة آمنة من الموائل البحرية عند الإبحار أو الرسو بجانبها.\n14- يجب أن يتم الإرساء بعناية فائقة، واستخدام العوامات البحرية المخصصة لتجنب الإضرار بالنظم البيئية تحت الماء وعدم الإرساء في مناطق محظورة أو محمية.\n15- يجب الاحتفاظ بتصريح رحلة سياحية عند مغادرة المرسى البحري السياحي.\n16- التأكد من أن استخدام الألعاب المائية يتوافق مع المعايير العمرية المناسبة أو المعتمدة، والقيود المفروضة على المعايير المحددة لنسبة الضوضاء، وأن تجهز بمعدات السلامة المناسبة، وأن يشرف عليها طاقم مدرب.\n17- التأكد من عدم بقاء أي ألعاب مائية ثابتة في عرض البحر أو تركها في أي منطقة غير مصرح بها.\n18- يُحظر التخلص من مياه الصابورة (التوازن) أو النفايات الصلبة والسائلة إلا في المرافق المخصصة للمرسى البحري السياحي.\n19- يُحظر إجراء سباقات من أي نوع كان إلا في المناطق المخصصة لذلك والمصرح بها من قبل الجهات ذات العلاقة بالمملكة.\n20- يُحظر إرساء أو إبحار اليخت الزائر أو أي ألعاب مائية في المناطق المحمية.\n21- في حال صيد الأسماك فيكون ذلك لغرض الاستهلاك الشخصي فقط، ووفق الضوابط التي تضعها الجهة المنظمة لنشاط الصيد الترفيهي حسب النوع والمواسم والكميات وأساليب الصيد، كما يحظر تداولها وبيعها في جميع أسواق ومحلات بيع الأسماك على كافة أنواعها.\n22- عدم صيد أسماك القرش أو الدلافين أو أي أسماك أخرى محمية أو محظور اصطيادها مهما كان نوعها وحجمها على مدار العام.\n23- عدم استخدام الشباك، أو بنادق الصيد البحري أو أي أدوات ومعدات صيد أخرى محظورة.\n24- الالتزام بالأنظمة واللوائح والتعليمات ذات العلاقة لحماية البيئة البحرية، والثروات المائية الحيّة، والحفاظ على التنوع البيولوجي البحري.\n25- عند مغادرة النطاق الجغرافي، يلتزم رُبَّان اليخت الزائر والوكيل الملاحي السياحي بتسجيل خروجه لدى أقرب ميناء أو مرسى بحري سياحي وطلب إلغاء الترخيص الفني (السياحي والترفيهي).",
      "status": "active",
      "paragraphs": [
        {
          "marker": "",
          "text": "المادة العاشرة:  قواعد السلامة والملاحة الآمنة وحماية البيئة البحرية",
          "level": 0
        },
        {
          "marker": "1-",
          "text": "يجب على اليخت الزائر وطاقمه الالتزام التام بجميع الأنظمة واللوائح والاتفاقيات الدولية البحرية المعمول بها في المملكة.",
          "level": 1
        },
        {
          "marker": "2-",
          "text": "الالتزام بتعليمات الملاحة والسلامة الخاصة بالمراسي البحرية السياحية والموانئ.",
          "level": 1
        },
        {
          "marker": "3-",
          "text": "الحفاظ بشكل مستمر على جهاز نظام التعرف الآلي (AIS) لليخت الزائر في حالة تشغيلية خلال فترة التواجد في النطاق الجغرافي.",
          "level": 1
        },
        {
          "marker": "4-",
          "text": "يجب على اليخت الزائر أن تقتصر أنشطته الملاحية والإرساء على المناطق المخصصة والمصرحة له من قبل الهيئة أو المرسى البحري السياحي وعدم دخول المناطق المحظورة أو المحمية أو غير المصرحة له.",
          "level": 1
        },
        {
          "marker": "5-",
          "text": "يجب الالتزام بالسرعة المحددة وعدم استخدام السرعة المفرطة التي قد تتسبب في وقوع حادث أو تسبب تموج مياه البحر مما يؤدي لإلحاق الضرر بأي يخت آخر أو سفينة أو ملكية أخرى.",
          "level": 1
        },
        {
          "marker": "6-",
          "text": "يجب أن يكون اليخت الزائر مجهزاً بمعدات السلامة والملاحة، والاتصالات اللاسلكية، ومعدات حماية البيئة وفقاً للمتطلبات والاتفاقيات والمعاهدات الدولية المعمول بها في المملكة.",
          "level": 1
        },
        {
          "marker": "7-",
          "text": "يجب أن يكون اليخت الزائر مجهزاً بمعدات الكشف عن الحرائق ومعدات مكافحة الحرائق.",
          "level": 1
        },
        {
          "marker": "8-",
          "text": "يجب أن يتوفر في اليخت الزائر معدات السلامة اللازمة، بما في ذلك سترات وطوق النجاة، وطفايات الحريق، وإشارات الاستغاثة، ولوازم الإسعافات الأولية، وذلك بحسب حجم اليخت وسعته.",
          "level": 1
        },
        {
          "marker": "9-",
          "text": "يجب إجراء تدريبات مكافحة الحرائق والطوارئ بانتظام مع التأكد من أن جميع أفراد الطاقم على دراية بإجراءات الطوارئ، وطرق الإخلاء، وبروتوكولات السلامة.",
          "level": 1
        },
        {
          "marker": "10-",
          "text": "يمنع منعاً باتاً تصريف أي مخلفات، بما في ذلك مياه الصرف الصحي، والنفايات، والمواد الزيتية في النطاق الجغرافي.",
          "level": 1
        },
        {
          "marker": "11-",
          "text": "تعزيز الممارسات البيئية المستدامة والتقليل من استخدام المواد البلاستيكية ذات الاستخدام الواحد على متن اليخت الزائر.",
          "level": 1
        },
        {
          "marker": "12-",
          "text": "يمنع استخدام واقي الشمس الضار بالشعاب المرجانية والبيئة البحرية، ويمكن استبداله بأي منتجات أخرى عضوية صديقة للبيئة.",
          "level": 1
        },
        {
          "marker": "13-",
          "text": "الالتزام بالمحافظة على مسافة آمنة من الموائل البحرية عند الإبحار أو الرسو بجانبها.",
          "level": 1
        },
        {
          "marker": "14-",
          "text": "يجب أن يتم الإرساء بعناية فائقة، واستخدام العوامات البحرية المخصصة لتجنب الإضرار بالنظم البيئية تحت الماء وعدم الإرساء في مناطق محظورة أو محمية.",
          "level": 1
        },
        {
          "marker": "15-",
          "text": "يجب الاحتفاظ بتصريح رحلة سياحية عند مغادرة المرسى البحري السياحي.",
          "level": 1
        },
        {
          "marker": "16-",
          "text": "التأكد من أن استخدام الألعاب المائية يتوافق مع المعايير العمرية المناسبة أو المعتمدة، والقيود المفروضة على المعايير المحددة لنسبة الضوضاء، وأن تجهز بمعدات السلامة المناسبة، وأن يشرف عليها طاقم مدرب.",
          "level": 1
        },
        {
          "marker": "17-",
          "text": "التأكد من عدم بقاء أي ألعاب مائية ثابتة في عرض البحر أو تركها في أي منطقة غير مصرح بها.",
          "level": 1
        },
        {
          "marker": "18-",
          "text": "يُحظر التخلص من مياه الصابورة (التوازن) أو النفايات الصلبة والسائلة إلا في المرافق المخصصة للمرسى البحري السياحي.",
          "level": 1
        },
        {
          "marker": "19-",
          "text": "يُحظر إجراء سباقات من أي نوع كان إلا في المناطق المخصصة لذلك والمصرح بها من قبل الجهات ذات العلاقة بالمملكة.",
          "level": 1
        },
        {
          "marker": "20-",
          "text": "يُحظر إرساء أو إبحار اليخت الزائر أو أي ألعاب مائية في المناطق المحمية.",
          "level": 1
        },
        {
          "marker": "21-",
          "text": "في حال صيد الأسماك فيكون ذلك لغرض الاستهلاك الشخصي فقط، ووفق الضوابط التي تضعها الجهة المنظمة لنشاط الصيد الترفيهي حسب النوع والمواسم والكميات وأساليب الصيد، كما يحظر تداولها وبيعها في جميع أسواق ومحلات بيع الأسماك على كافة أنواعها.",
          "level": 1
        },
        {
          "marker": "22-",
          "text": "عدم صيد أسماك القرش أو الدلافين أو أي أسماك أخرى محمية أو محظور اصطيادها مهما كان نوعها وحجمها على مدار العام.",
          "level": 1
        },
        {
          "marker": "23-",
          "text": "عدم استخدام الشباك، أو بنادق الصيد البحري أو أي أدوات ومعدات صيد أخرى محظورة.",
          "level": 1
        },
        {
          "marker": "24-",
          "text": "الالتزام بالأنظمة واللوائح والتعليمات ذات العلاقة لحماية البيئة البحرية، والثروات المائية الحيّة، والحفاظ على التنوع البيولوجي البحري.",
          "level": 1
        },
        {
          "marker": "25-",
          "text": "عند مغادرة النطاق الجغرافي، يلتزم رُبَّان اليخت الزائر والوكيل الملاحي السياحي بتسجيل خروجه لدى أقرب ميناء أو مرسى بحري سياحي وطلب إلغاء الترخيص الفني (السياحي والترفيهي).",
          "level": 1
        }
      ],
      "amendments": [],
      "heading_context": []
    },
    {
      "number": 11,
      "number_text": "المادة الحادية عشرة",
      "text": "المادة الحادية عشرة:  ضوابط استخدام قارب التنقل ((Tender Boat\n1- يجب على رُبَّان اليخت تجهيز الترتيبات المناسبة والآمنة قبل وصول اليخت إلى الوجهة البحرية السياحية.\n2- يجب تنفيذ وثيقة تقييم إدارة المخاطر لكل رحلة وعملية التنقل وصعود وإنزال الركاب بواسطة قارب التنقل من اليخت إلى الشاطئ/ المرسى البحري السياحي.\n3- أن تكون هناك وسيلة اتصال (جهاز لاسلكي) يعمل وبحالة جيدة طول فترة التنقل ويتم اختبارها قبل انطلاق القارب.\n4- يجب أن يتضمن تخطيط رحلة قارب التنقل اتباع تعليمات وتنفيذ قواعد منع التصادم في البحار في حال التطبيق والتيارات والمد والجزر وظروف البحر سواءٌ الحالية أو المتوقعة وتوقعات الطقس وحركة مرور السفن والممرات الملاحية والمناطق المحظورة والتي يجب تجنبها.\n5- أن تكون عملية نقل الركاب من اليخت إلى الشاطئ/ المرسى البحري السياحي بواسطة قارب التنقل بعد موافقة رُبَّان اليخت وإشرافه الكامل على عملية النقل ذهاباً وإياباً.\n6- يجب على رُبَّان اليخت قبل بدء عملية نقل الركاب عقد اجتماع سلامة (Toolbox) مع الضباط والطاقم المشرفين وتوزيع المهام قبل بدء واجباتهم.\n7- يجب تواجد ضابط مسؤول من اليخت أثناء عملية إنزال واستقبال الركاب من وإلى قارب التنقل وأن تتم المراقبة والتواصل بالمتابعة من غرفة قيادة اليخت وبرج مراقبة حركة مرور السفن.\n8- في حالة تنقل الركاب بواسطة قارب التنقل يجب أن يتم تسهيل وتنظيم صعود وإنزال الركاب وأيضاً تسهيل وتوفير رعاية خاصة لذوي الإعاقة وتكون عملية الإنزال والصعود بطريقة آمنة.",
      "original_text": "المادة الحادية عشرة:  ضوابط استخدام قارب التنقل ((Tender Boat\n1- يجب على رُبَّان اليخت تجهيز الترتيبات المناسبة والآمنة قبل وصول اليخت إلى الوجهة البحرية السياحية.\n2- يجب تنفيذ وثيقة تقييم إدارة المخاطر لكل رحلة وعملية التنقل وصعود وإنزال الركاب بواسطة قارب التنقل من اليخت إلى الشاطئ/ المرسى البحري السياحي.\n3- أن تكون هناك وسيلة اتصال (جهاز لاسلكي) يعمل وبحالة جيدة طول فترة التنقل ويتم اختبارها قبل انطلاق القارب.\n4- يجب أن يتضمن تخطيط رحلة قارب التنقل اتباع تعليمات وتنفيذ قواعد منع التصادم في البحار في حال التطبيق والتيارات والمد والجزر وظروف البحر سواءٌ الحالية أو المتوقعة وتوقعات الطقس وحركة مرور السفن والممرات الملاحية والمناطق المحظورة والتي يجب تجنبها.\n5- أن تكون عملية نقل الركاب من اليخت إلى الشاطئ/ المرسى البحري السياحي بواسطة قارب التنقل بعد موافقة رُبَّان اليخت وإشرافه الكامل على عملية النقل ذهاباً وإياباً.\n6- يجب على رُبَّان اليخت قبل بدء عملية نقل الركاب عقد اجتماع سلامة (Toolbox) مع الضباط والطاقم المشرفين وتوزيع المهام قبل بدء واجباتهم.\n7- يجب تواجد ضابط مسؤول من اليخت أثناء عملية إنزال واستقبال الركاب من وإلى قارب التنقل وأن تتم المراقبة والتواصل بالمتابعة من غرفة قيادة اليخت وبرج مراقبة حركة مرور السفن.\n8- في حالة تنقل الركاب بواسطة قارب التنقل يجب أن يتم تسهيل وتنظيم صعود وإنزال الركاب وأيضاً تسهيل وتوفير رعاية خاصة لذوي الإعاقة وتكون عملية الإنزال والصعود بطريقة آمنة.",
      "status": "active",
      "paragraphs": [
        {
          "marker": "",
          "text": "المادة الحادية عشرة:  ضوابط استخدام قارب التنقل ((Tender Boat",
          "level": 0
        },
        {
          "marker": "1-",
          "text": "يجب على رُبَّان اليخت تجهيز الترتيبات المناسبة والآمنة قبل وصول اليخت إلى الوجهة البحرية السياحية.",
          "level": 1
        },
        {
          "marker": "2-",
          "text": "يجب تنفيذ وثيقة تقييم إدارة المخاطر لكل رحلة وعملية التنقل وصعود وإنزال الركاب بواسطة قارب التنقل من اليخت إلى الشاطئ/ المرسى البحري السياحي.",
          "level": 1
        },
        {
          "marker": "3-",
          "text": "أن تكون هناك وسيلة اتصال (جهاز لاسلكي) يعمل وبحالة جيدة طول فترة التنقل ويتم اختبارها قبل انطلاق القارب.",
          "level": 1
        },
        {
          "marker": "4-",
          "text": "يجب أن يتضمن تخطيط رحلة قارب التنقل اتباع تعليمات وتنفيذ قواعد منع التصادم في البحار في حال التطبيق والتيارات والمد والجزر وظروف البحر سواءٌ الحالية أو المتوقعة وتوقعات الطقس وحركة مرور السفن والممرات الملاحية والمناطق المحظورة والتي يجب تجنبها.",
          "level": 1
        },
        {
          "marker": "5-",
          "text": "أن تكون عملية نقل الركاب من اليخت إلى الشاطئ/ المرسى البحري السياحي بواسطة قارب التنقل بعد موافقة رُبَّان اليخت وإشرافه الكامل على عملية النقل ذهاباً وإياباً.",
          "level": 1
        },
        {
          "marker": "6-",
          "text": "يجب على رُبَّان اليخت قبل بدء عملية نقل الركاب عقد اجتماع سلامة (Toolbox) مع الضباط والطاقم المشرفين وتوزيع المهام قبل بدء واجباتهم.",
          "level": 1
        },
        {
          "marker": "7-",
          "text": "يجب تواجد ضابط مسؤول من اليخت أثناء عملية إنزال واستقبال الركاب من وإلى قارب التنقل وأن تتم المراقبة والتواصل بالمتابعة من غرفة قيادة اليخت وبرج مراقبة حركة مرور السفن.",
          "level": 1
        },
        {
          "marker": "8-",
          "text": "في حالة تنقل الركاب بواسطة قارب التنقل يجب أن يتم تسهيل وتنظيم صعود وإنزال الركاب وأيضاً تسهيل وتوفير رعاية خاصة لذوي الإعاقة وتكون عملية الإنزال والصعود بطريقة آمنة.",
          "level": 1
        }
      ],
      "amendments": [],
      "heading_context": []
    },
    {
      "number": 12,
      "number_text": "المادة الثانية عشرة",
      "text": "المادة الثانية  عشرة: تجديد وإلغاء الترخيص الفني (السياحي والترفيهي)\n1- يجوز للوكيل الملاحي السياحي التقدم بطلب تجديد الترخيص قبل (48) ساعة على الأقل من انتهاء صلاحية الترخيص الحالي.\n2- في حال تم استيفاء جميع المتطلبات، يتم تجديد الترخيص والسماح لليخت الزائر بمواصلة نشاطه بنفس الشروط والأحكام الخاصة بالترخيص الأصلي.\n3- تحتفظ الهيئة بالحق في إلغاء الترخيص الفني (السياحي والترفيهي) في حال مخالفة اليخت الزائر لأي أحكام واردة في اللائحة التنظيمية والضوابط والإجراءات أو القيام بأنشطة تشكل تهديداً للسلامة والبيئة أو عدم الامتثال للتعليمات الصادرة من الهيئة أو الجهات ذات العلاقة.",
      "original_text": "المادة الثانية  عشرة: تجديد وإلغاء الترخيص الفني (السياحي والترفيهي)\n1- يجوز للوكيل الملاحي السياحي التقدم بطلب تجديد الترخيص قبل (48) ساعة على الأقل من انتهاء صلاحية الترخيص الحالي.\n2- في حال تم استيفاء جميع المتطلبات، يتم تجديد الترخيص والسماح لليخت الزائر بمواصلة نشاطه بنفس الشروط والأحكام الخاصة بالترخيص الأصلي.\n3- تحتفظ الهيئة بالحق في إلغاء الترخيص الفني (السياحي والترفيهي) في حال مخالفة اليخت الزائر لأي أحكام واردة في اللائحة التنظيمية والضوابط والإجراءات أو القيام بأنشطة تشكل تهديداً للسلامة والبيئة أو عدم الامتثال للتعليمات الصادرة من الهيئة أو الجهات ذات العلاقة.",
      "status": "active",
      "paragraphs": [
        {
          "marker": "",
          "text": "المادة الثانية  عشرة: تجديد وإلغاء الترخيص الفني (السياحي والترفيهي)",
          "level": 0
        },
        {
          "marker": "1-",
          "text": "يجوز للوكيل الملاحي السياحي التقدم بطلب تجديد الترخيص قبل (48) ساعة على الأقل من انتهاء صلاحية الترخيص الحالي.",
          "level": 1
        },
        {
          "marker": "2-",
          "text": "في حال تم استيفاء جميع المتطلبات، يتم تجديد الترخيص والسماح لليخت الزائر بمواصلة نشاطه بنفس الشروط والأحكام الخاصة بالترخيص الأصلي.",
          "level": 1
        },
        {
          "marker": "3-",
          "text": "تحتفظ الهيئة بالحق في إلغاء الترخيص الفني (السياحي والترفيهي) في حال مخالفة اليخت الزائر لأي أحكام واردة في اللائحة التنظيمية والضوابط والإجراءات أو القيام بأنشطة تشكل تهديداً للسلامة والبيئة أو عدم الامتثال للتعليمات الصادرة من الهيئة أو الجهات ذات العلاقة.",
          "level": 1
        }
      ],
      "amendments": [],
      "heading_context": []
    },
    {
      "number": 13,
      "number_text": "المادة الثالثة عشرة",
      "text": "المادة الثالثة  عشرة: المقابل المالي\nا\nل\nوثيقة\nالمقابل المالي\nأقصى مدة\nالترخيص الفني (السياحي والترفيهي)\n(4,000)\nأربعة آلاف ريال سعودي/ (6) أشهر ميلادية\n(6)\nأشهر ميلادية",
      "original_text": "المادة الثالثة  عشرة: المقابل المالي\nا\nل\nوثيقة\nالمقابل المالي\nأقصى مدة\nالترخيص الفني (السياحي والترفيهي)\n(4,000)\nأربعة آلاف ريال سعودي/ (6) أشهر ميلادية\n(6)\nأشهر ميلادية",
      "status": "active",
      "paragraphs": [
        {
          "marker": "",
          "text": "المادة الثالثة  عشرة: المقابل المالي",
          "level": 0
        },
        {
          "marker": "",
          "text": "ا",
          "level": 0
        },
        {
          "marker": "",
          "text": "ل",
          "level": 0
        },
        {
          "marker": "",
          "text": "وثيقة",
          "level": 0
        },
        {
          "marker": "",
          "text": "المقابل المالي",
          "level": 0
        },
        {
          "marker": "",
          "text": "أقصى مدة",
          "level": 0
        },
        {
          "marker": "",
          "text": "الترخيص الفني (السياحي والترفيهي)",
          "level": 0
        },
        {
          "marker": "",
          "text": "(4,000)",
          "level": 0
        },
        {
          "marker": "",
          "text": "أربعة آلاف ريال سعودي/ (6) أشهر ميلادية",
          "level": 0
        },
        {
          "marker": "",
          "text": "(6)",
          "level": 0
        },
        {
          "marker": "",
          "text": "أشهر ميلادية",
          "level": 0
        }
      ],
      "amendments": [],
      "heading_context": []
    }
  ]
}