{
  "law_id": "uqn_24357",
  "law_name": "لائحة شروط تفويض هيئات التصنيف في المملكة العربية السعودية",
  "title": "لائحة شروط تفويض هيئات التصنيف في المملكة العربية السعودية",
  "jurisdiction_ar": "السعودية",
  "doc_type": "official_text",
  "category": "regulation",
  "primary_source_id": "uqn",
  "status": "ساري",
  "issue_date_hijri": "1445/06/30",
  "issue_date_gregorian": "12/01/2024",
  "publish_date_hijri": "1445/06/30",
  "publish_date_gregorian": "12/01/2024",
  "issuing_authority": "لوائح وأنظمة",
  "links": [
    {
      "source_id": "uqn",
      "url": "https://www.uqn.gov.sa/details?p=24357",
      "label_ar": "جريدة أم القرى الرسمية"
    }
  ],
  "total_articles": 14,
  "articles": [
    {
      "number": 1,
      "number_text": "المادة الأولى",
      "text": "المادة الأولى:  التعاريف\nالنظام: النظام البحري التجاري الصادر بالمرسوم الملكي رقم (م/33) وتاريخ 5 /4/ 1440هـ.\nاللائحة: لائحة شروط تفويض هيئات التصنيف في المملكة العربية السعودية.\nالوزير: وزير النقل والخدمات اللوجستية، رئيس مجلس إدارة الهيئة العامة للنقل.\nالرئيس: رئيس الهيئة العامة للنقل.\nالهيئة: الهيئة العامة للنقل (السلطة البحرية).\nالمنظمة: المنظمة البحرية الدولية (IMO).\nدولة العلم: الدولة التي يحق للسفينة رفع علمها.\nالسفينة: كل منشأة عائمة معدّة للعمل في الملاحة البحرية على وجه الاعتياد، ولو لم تهدف إلى الربح، وتعد ملحقات السفينة اللازمة لاستغلالها جزءاً منها.\nمدونة الهيئات المعتمدة: المدونة الصادرة بقرار لجنة السلامة البحرية بالمنظمة البحرية الدولية (IMO) رقم MSC.349 (92)  (RO Code) وما يطرأ عليها من تعديلات.\nهيئات التصنيف: هيئة دولية أو محلية تُعنى بوضع المعايير لتصميم وتشييد السفن، والمحافظة على هذه المعايير طوال فترة حياة السفينة وإصدار الشهادات وتقديم الخدمات وفقاً للمتطلبات الدولية والوطنية نيابة عن دولة العلم، وذلك لضمان استيفاء المعايير الفنية العالية في التصميم والصنع والتشييد والصيانة والتشغيل والأداء من أجل تعزيز السلامة البحرية والمحافظة على البيئة والممتلكات في البحر.\nهيئات التصنيف المؤهلة: هيئات التصني\nف التي من الممكن تفويضها بموجب اتفاقية تُبرم مع الهيئة لاستيفائها شروط تفويض هيئات التصنيف.\nإصدار الشهادات وتقديم الخدمات: الشهادات التي يتم إصدارها والخدمات التي يتم تقديمها بموجب الصكوك الدولية الإلزامية المنضمة لها المملكة، والصادرة من المنظمة البحرية الدولية والأنظمة والقواعد واللوائح التي تضعها المملكة.\nالمعاينة: الكشف على السفينة و/أو هيكلها و/أو أي جزء من مكوناتها، أو محركاتها أو معداتها أو أجهزتها للتحقق من صلاحيتها للملاحة وتوافر كافة الشروط والمتطلبات طبقاً للتشريعات والاتفاقيات البحرية الدولية المصادق عليها من قبل المملكة، والتي دخلت حيز التنفيذ دولياً، ووضع تقرير يصف حالتها الفنية بعد الكشف.\nالاتحاد الدولي لهيئات التصنيف (IACS): هي منظمة عضوية غير ربحية لجمعيات التصنيف التي تضع المعايير والمتطلبات الفنية التي تتناول السلامة البحرية وحماية البيئة وتضمن تطبيقها المتسق، وتتحمل هذه المسؤولية من خلال لجانها ومجموعات الخبراء وفرق المشروع وتوفر نظام شهادة نظام الجودة(QSCS)  الذي يلتزم به أعضاؤها، كضمان للنزاهة المهنية والحفاظ على المعايير المهنية العالية.",
      "original_text": "المادة الأولى:  التعاريف\nالنظام: النظام البحري التجاري الصادر بالمرسوم الملكي رقم (م/33) وتاريخ 5 /4/ 1440هـ.\nاللائحة: لائحة شروط تفويض هيئات التصنيف في المملكة العربية السعودية.\nالوزير: وزير النقل والخدمات اللوجستية، رئيس مجلس إدارة الهيئة العامة للنقل.\nالرئيس: رئيس الهيئة العامة للنقل.\nالهيئة: الهيئة العامة للنقل (السلطة البحرية).\nالمنظمة: المنظمة البحرية الدولية (IMO).\nدولة العلم: الدولة التي يحق للسفينة رفع علمها.\nالسفينة: كل منشأة عائمة معدّة للعمل في الملاحة البحرية على وجه الاعتياد، ولو لم تهدف إلى الربح، وتعد ملحقات السفينة اللازمة لاستغلالها جزءاً منها.\nمدونة الهيئات المعتمدة: المدونة الصادرة بقرار لجنة السلامة البحرية بالمنظمة البحرية الدولية (IMO) رقم MSC.349 (92)  (RO Code) وما يطرأ عليها من تعديلات.\nهيئات التصنيف: هيئة دولية أو محلية تُعنى بوضع المعايير لتصميم وتشييد السفن، والمحافظة على هذه المعايير طوال فترة حياة السفينة وإصدار الشهادات وتقديم الخدمات وفقاً للمتطلبات الدولية والوطنية نيابة عن دولة العلم، وذلك لضمان استيفاء المعايير الفنية العالية في التصميم والصنع والتشييد والصيانة والتشغيل والأداء من أجل تعزيز السلامة البحرية والمحافظة على البيئة والممتلكات في البحر.\nهيئات التصنيف المؤهلة: هيئات التصني\nف التي من الممكن تفويضها بموجب اتفاقية تُبرم مع الهيئة لاستيفائها شروط تفويض هيئات التصنيف.\nإصدار الشهادات وتقديم الخدمات: الشهادات التي يتم إصدارها والخدمات التي يتم تقديمها بموجب الصكوك الدولية الإلزامية المنضمة لها المملكة، والصادرة من المنظمة البحرية الدولية والأنظمة والقواعد واللوائح التي تضعها المملكة.\nالمعاينة: الكشف على السفينة و/أو هيكلها و/أو أي جزء من مكوناتها، أو محركاتها أو معداتها أو أجهزتها للتحقق من صلاحيتها للملاحة وتوافر كافة الشروط والمتطلبات طبقاً للتشريعات والاتفاقيات البحرية الدولية المصادق عليها من قبل المملكة، والتي دخلت حيز التنفيذ دولياً، ووضع تقرير يصف حالتها الفنية بعد الكشف.\nالاتحاد الدولي لهيئات التصنيف (IACS): هي منظمة عضوية غير ربحية لجمعيات التصنيف التي تضع المعايير والمتطلبات الفنية التي تتناول السلامة البحرية وحماية البيئة وتضمن تطبيقها المتسق، وتتحمل هذه المسؤولية من خلال لجانها ومجموعات الخبراء وفرق المشروع وتوفر نظام شهادة نظام الجودة(QSCS)  الذي يلتزم به أعضاؤها، كضمان للنزاهة المهنية والحفاظ على المعايير المهنية العالية.",
      "status": "active",
      "paragraphs": [
        {
          "marker": "",
          "text": "المادة الأولى:  التعاريف",
          "level": 0
        },
        {
          "marker": "",
          "text": "النظام: النظام البحري التجاري الصادر بالمرسوم الملكي رقم (م/33) وتاريخ 5 /4/ 1440هـ.",
          "level": 0
        },
        {
          "marker": "",
          "text": "اللائحة: لائحة شروط تفويض هيئات التصنيف في المملكة العربية السعودية.",
          "level": 0
        },
        {
          "marker": "",
          "text": "الوزير: وزير النقل والخدمات اللوجستية، رئيس مجلس إدارة الهيئة العامة للنقل.",
          "level": 0
        },
        {
          "marker": "",
          "text": "الرئيس: رئيس الهيئة العامة للنقل.",
          "level": 0
        },
        {
          "marker": "",
          "text": "الهيئة: الهيئة العامة للنقل (السلطة البحرية).",
          "level": 0
        },
        {
          "marker": "",
          "text": "المنظمة: المنظمة البحرية الدولية (IMO).",
          "level": 0
        },
        {
          "marker": "",
          "text": "دولة العلم: الدولة التي يحق للسفينة رفع علمها.",
          "level": 0
        },
        {
          "marker": "",
          "text": "السفينة: كل منشأة عائمة معدّة للعمل في الملاحة البحرية على وجه الاعتياد، ولو لم تهدف إلى الربح، وتعد ملحقات السفينة اللازمة لاستغلالها جزءاً منها.",
          "level": 0
        },
        {
          "marker": "",
          "text": "مدونة الهيئات المعتمدة: المدونة الصادرة بقرار لجنة السلامة البحرية بالمنظمة البحرية الدولية (IMO) رقم MSC.349 (92)  (RO Code) وما يطرأ عليها من تعديلات.",
          "level": 0
        },
        {
          "marker": "",
          "text": "هيئات التصنيف: هيئة دولية أو محلية تُعنى بوضع المعايير لتصميم وتشييد السفن، والمحافظة على هذه المعايير طوال فترة حياة السفينة وإصدار الشهادات وتقديم الخدمات وفقاً للمتطلبات الدولية والوطنية نيابة عن دولة العلم، وذلك لضمان استيفاء المعايير الفنية العالية في التصميم والصنع والتشييد والصيانة والتشغيل والأداء من أجل تعزيز السلامة البحرية والمحافظة على البيئة والممتلكات في البحر.",
          "level": 0
        },
        {
          "marker": "",
          "text": "هيئات التصنيف المؤهلة: هيئات التصني",
          "level": 0
        },
        {
          "marker": "",
          "text": "ف التي من الممكن تفويضها بموجب اتفاقية تُبرم مع الهيئة لاستيفائها شروط تفويض هيئات التصنيف.",
          "level": 0
        },
        {
          "marker": "",
          "text": "إصدار الشهادات وتقديم الخدمات: الشهادات التي يتم إصدارها والخدمات التي يتم تقديمها بموجب الصكوك الدولية الإلزامية المنضمة لها المملكة، والصادرة من المنظمة البحرية الدولية والأنظمة والقواعد واللوائح التي تضعها المملكة.",
          "level": 0
        },
        {
          "marker": "",
          "text": "المعاينة: الكشف على السفينة و/أو هيكلها و/أو أي جزء من مكوناتها، أو محركاتها أو معداتها أو أجهزتها للتحقق من صلاحيتها للملاحة وتوافر كافة الشروط والمتطلبات طبقاً للتشريعات والاتفاقيات البحرية الدولية المصادق عليها من قبل المملكة، والتي دخلت حيز التنفيذ دولياً، ووضع تقرير يصف حالتها الفنية بعد الكشف.",
          "level": 0
        },
        {
          "marker": "",
          "text": "الاتحاد الدولي لهيئات التصنيف (IACS): هي منظمة عضوية غير ربحية لجمعيات التصنيف التي تضع المعايير والمتطلبات الفنية التي تتناول السلامة البحرية وحماية البيئة وتضمن تطبيقها المتسق، وتتحمل هذه المسؤولية من خلال لجانها ومجموعات الخبراء وفرق المشروع وتوفر نظام شهادة نظام الجودة(QSCS)  الذي يلتزم به أعضاؤها، كضمان للنزاهة المهنية والحفاظ على المعايير المهنية العالية.",
          "level": 0
        }
      ],
      "amendments": [],
      "heading_context": []
    },
    {
      "number": 2,
      "number_text": "المادة الثانية",
      "text": "المادة الثانية:  الغرض من اللائحة\nتهدف هذه اللائحة إلى وضع شروط وإجراءات تفويض هيئات تصنيف السفن الراغبة في العمل في المملكة العربية السعودية.",
      "original_text": "المادة الثانية:  الغرض من اللائحة\nتهدف هذه اللائحة إلى وضع شروط وإجراءات تفويض هيئات تصنيف السفن الراغبة في العمل في المملكة العربية السعودية.",
      "status": "active",
      "paragraphs": [
        {
          "marker": "",
          "text": "المادة الثانية:  الغرض من اللائحة",
          "level": 0
        },
        {
          "marker": "",
          "text": "تهدف هذه اللائحة إلى وضع شروط وإجراءات تفويض هيئات تصنيف السفن الراغبة في العمل في المملكة العربية السعودية.",
          "level": 0
        }
      ],
      "amendments": [],
      "heading_context": []
    },
    {
      "number": 3,
      "number_text": "المادة الثالثة",
      "text": "المادة الثالثة:  نطاق التطبيق\nمع عدم الإخلال بالأنظمة والاتفاقيات المعمول بها في المملكة، تطبق اللائحة على هيئات التصنيف الراغبة في العمل في المملكة العربية السعودية.",
      "original_text": "المادة الثالثة:  نطاق التطبيق\nمع عدم الإخلال بالأنظمة والاتفاقيات المعمول بها في المملكة، تطبق اللائحة على هيئات التصنيف الراغبة في العمل في المملكة العربية السعودية.",
      "status": "active",
      "paragraphs": [
        {
          "marker": "",
          "text": "المادة الثالثة:  نطاق التطبيق",
          "level": 0
        },
        {
          "marker": "",
          "text": "مع عدم الإخلال بالأنظمة والاتفاقيات المعمول بها في المملكة، تطبق اللائحة على هيئات التصنيف الراغبة في العمل في المملكة العربية السعودية.",
          "level": 0
        }
      ],
      "amendments": [],
      "heading_context": []
    },
    {
      "number": 4,
      "number_text": "المادة الرابعة",
      "text": "المادة الرابعة:  شروط تفويض هيئات التصنيف\nيجب توافر الشروط المنصوص عليها أدناه كحد أدنى لدى هيئات التصنيف لتفويضها بالقيام بإصدار الشهادات وتقديم الخدمات للسفن المسجلة في المملكة العربية السعودية نيابة عن الهيئة:\nأن تكون هيئة التصنيف عضواً بالاتحاد الدولي لهيئات التصنيف (IACS).\nأن يكون لدى هيئة التصنيف الإلمام الشامل بكل ما يتعلق بمجالات الفحص والمعاينة وتقييم تصاميم بناء السفن وإجراء البحوث ذات العلاقة وتصنيفها.\nأن يكون لدى هيئة التصنيف قواعد وأنظمة شاملة تغطي أنشطة فحص ومعاينة وتصميم وبناء أنواع السفن التي تصنفها.\nأن يكون لدى هيئة التصنيف الكفاءات والإمكانيات والقدرات الفنية لتنفيذ المهام التي يتعين القيام بها وتصنيف السفن، وكذلك ضمان تطوير القدرات وتحديث القواعد والتعليمات.\nأن يكون لدى هيئة التصنيف مقر إقليمي/ أو فرع في المملكة عند تقديم الطلب، وفي حال عدم وجودهما، يتم الاستمرار في إجراءات القبول ولا يسمح لهيئة التصنيف بممارسة الأعمال بالنيابة عن الهيئة إلا بعد وجود مقر إقليمي/ أو فرع في المملكة.\nأن تكون هيئة التصنيف حاصلة على سجل تجاري ساري المفعول في المملكة لممارسة نشاط معاينة السفن.\nأن يكون لدى هيئات التصنيف نظام إدارة الجودة فعّال طبقاً للمتطلبات الواردة في مدونة الهيئات المعتمدة (مدونة RO Code) يعتمد على الجوانب ذات الصلة بمعايير الجودة المعترف بها دولياً وآلية إجراءات معتمدة للتنسيق مع الهيئة في حال حجز أي سفينة ترفع العلم السعودي من قبل رقابة دولة الميناء في الموانئ الأجنبية.\nأن يكون معدل حجز السفن الخاضعة تحت إشراف هيئة التصنيف لا يزيد على (3.5) بالمائة في رقابة دولة الميناء (PSC) خلال السنوات الثلاث الماضية لتاريخ تقديم الطلب، وذلك وفقاً لتقارير مذكرات التفاهم للتفتيش والرقابة على السفن.\nأن تمتثل هيئة التصنيف الحد الأدنى من المعايير الموصى بها في قرار لجنة السلامة البحرية بالمنظمة البحرية الدولية رقم MSC.349 (92)  المتعلق بمدونة الهيئات المعتمدة وتعديلاتها.\nيجب أن يكون لدى هيئة التصنيف خطة لتوطين العمل في مجالات الفحص والمعاينة في مكاتبها أو فروعها في المملكة ووفق الأنظمة المعمول بها في المملكة.",
      "original_text": "المادة الرابعة:  شروط تفويض هيئات التصنيف\nيجب توافر الشروط المنصوص عليها أدناه كحد أدنى لدى هيئات التصنيف لتفويضها بالقيام بإصدار الشهادات وتقديم الخدمات للسفن المسجلة في المملكة العربية السعودية نيابة عن الهيئة:\nأن تكون هيئة التصنيف عضواً بالاتحاد الدولي لهيئات التصنيف (IACS).\nأن يكون لدى هيئة التصنيف الإلمام الشامل بكل ما يتعلق بمجالات الفحص والمعاينة وتقييم تصاميم بناء السفن وإجراء البحوث ذات العلاقة وتصنيفها.\nأن يكون لدى هيئة التصنيف قواعد وأنظمة شاملة تغطي أنشطة فحص ومعاينة وتصميم وبناء أنواع السفن التي تصنفها.\nأن يكون لدى هيئة التصنيف الكفاءات والإمكانيات والقدرات الفنية لتنفيذ المهام التي يتعين القيام بها وتصنيف السفن، وكذلك ضمان تطوير القدرات وتحديث القواعد والتعليمات.\nأن يكون لدى هيئة التصنيف مقر إقليمي/ أو فرع في المملكة عند تقديم الطلب، وفي حال عدم وجودهما، يتم الاستمرار في إجراءات القبول ولا يسمح لهيئة التصنيف بممارسة الأعمال بالنيابة عن الهيئة إلا بعد وجود مقر إقليمي/ أو فرع في المملكة.\nأن تكون هيئة التصنيف حاصلة على سجل تجاري ساري المفعول في المملكة لممارسة نشاط معاينة السفن.\nأن يكون لدى هيئات التصنيف نظام إدارة الجودة فعّال طبقاً للمتطلبات الواردة في مدونة الهيئات المعتمدة (مدونة RO Code) يعتمد على الجوانب ذات الصلة بمعايير الجودة المعترف بها دولياً وآلية إجراءات معتمدة للتنسيق مع الهيئة في حال حجز أي سفينة ترفع العلم السعودي من قبل رقابة دولة الميناء في الموانئ الأجنبية.\nأن يكون معدل حجز السفن الخاضعة تحت إشراف هيئة التصنيف لا يزيد على (3.5) بالمائة في رقابة دولة الميناء (PSC) خلال السنوات الثلاث الماضية لتاريخ تقديم الطلب، وذلك وفقاً لتقارير مذكرات التفاهم للتفتيش والرقابة على السفن.\nأن تمتثل هيئة التصنيف الحد الأدنى من المعايير الموصى بها في قرار لجنة السلامة البحرية بالمنظمة البحرية الدولية رقم MSC.349 (92)  المتعلق بمدونة الهيئات المعتمدة وتعديلاتها.\nيجب أن يكون لدى هيئة التصنيف خطة لتوطين العمل في مجالات الفحص والمعاينة في مكاتبها أو فروعها في المملكة ووفق الأنظمة المعمول بها في المملكة.",
      "status": "active",
      "paragraphs": [
        {
          "marker": "",
          "text": "المادة الرابعة:  شروط تفويض هيئات التصنيف",
          "level": 0
        },
        {
          "marker": "",
          "text": "يجب توافر الشروط المنصوص عليها أدناه كحد أدنى لدى هيئات التصنيف لتفويضها بالقيام بإصدار الشهادات وتقديم الخدمات للسفن المسجلة في المملكة العربية السعودية نيابة عن الهيئة:",
          "level": 0
        },
        {
          "marker": "",
          "text": "أن تكون هيئة التصنيف عضواً بالاتحاد الدولي لهيئات التصنيف (IACS).",
          "level": 0
        },
        {
          "marker": "",
          "text": "أن يكون لدى هيئة التصنيف الإلمام الشامل بكل ما يتعلق بمجالات الفحص والمعاينة وتقييم تصاميم بناء السفن وإجراء البحوث ذات العلاقة وتصنيفها.",
          "level": 0
        },
        {
          "marker": "",
          "text": "أن يكون لدى هيئة التصنيف قواعد وأنظمة شاملة تغطي أنشطة فحص ومعاينة وتصميم وبناء أنواع السفن التي تصنفها.",
          "level": 0
        },
        {
          "marker": "",
          "text": "أن يكون لدى هيئة التصنيف الكفاءات والإمكانيات والقدرات الفنية لتنفيذ المهام التي يتعين القيام بها وتصنيف السفن، وكذلك ضمان تطوير القدرات وتحديث القواعد والتعليمات.",
          "level": 0
        },
        {
          "marker": "",
          "text": "أن يكون لدى هيئة التصنيف مقر إقليمي/ أو فرع في المملكة عند تقديم الطلب، وفي حال عدم وجودهما، يتم الاستمرار في إجراءات القبول ولا يسمح لهيئة التصنيف بممارسة الأعمال بالنيابة عن الهيئة إلا بعد وجود مقر إقليمي/ أو فرع في المملكة.",
          "level": 0
        },
        {
          "marker": "",
          "text": "أن تكون هيئة التصنيف حاصلة على سجل تجاري ساري المفعول في المملكة لممارسة نشاط معاينة السفن.",
          "level": 0
        },
        {
          "marker": "",
          "text": "أن يكون لدى هيئات التصنيف نظام إدارة الجودة فعّال طبقاً للمتطلبات الواردة في مدونة الهيئات المعتمدة (مدونة RO Code) يعتمد على الجوانب ذات الصلة بمعايير الجودة المعترف بها دولياً وآلية إجراءات معتمدة للتنسيق مع الهيئة في حال حجز أي سفينة ترفع العلم السعودي من قبل رقابة دولة الميناء في الموانئ الأجنبية.",
          "level": 0
        },
        {
          "marker": "",
          "text": "أن يكون معدل حجز السفن الخاضعة تحت إشراف هيئة التصنيف لا يزيد على (3.5) بالمائة في رقابة دولة الميناء (PSC) خلال السنوات الثلاث الماضية لتاريخ تقديم الطلب، وذلك وفقاً لتقارير مذكرات التفاهم للتفتيش والرقابة على السفن.",
          "level": 0
        },
        {
          "marker": "",
          "text": "أن تمتثل هيئة التصنيف الحد الأدنى من المعايير الموصى بها في قرار لجنة السلامة البحرية بالمنظمة البحرية الدولية رقم MSC.349 (92)  المتعلق بمدونة الهيئات المعتمدة وتعديلاتها.",
          "level": 0
        },
        {
          "marker": "",
          "text": "يجب أن يكون لدى هيئة التصنيف خطة لتوطين العمل في مجالات الفحص والمعاينة في مكاتبها أو فروعها في المملكة ووفق الأنظمة المعمول بها في المملكة.",
          "level": 0
        }
      ],
      "amendments": [],
      "heading_context": []
    },
    {
      "number": 5,
      "number_text": "المادة الخامسة",
      "text": "المادة الخامسة:  القدرات الفنية والتنظيمية\nعلى الهيئة التأكد من أن لدى هيئة التصنيف المواد والمصادر الكافية من حيث القدرات والخبرات الفنية والتنظيمية للعاملين، والقدرة على إجراءات البحوث من أجل القيام بالمهام الموكلة إليها، وذلك وفقاً لمعايير الحد الأدنى التي تنطبق على هيئات التصنيف المعتمدة التي تعمل نيابة عنها، على النحو المنصوص عليه في منهجية الاعتماد والإشراف والتدقيق على هيئات التصنيف المعتمدة من قبل الهيئة.",
      "original_text": "المادة الخامسة:  القدرات الفنية والتنظيمية\nعلى الهيئة التأكد من أن لدى هيئة التصنيف المواد والمصادر الكافية من حيث القدرات والخبرات الفنية والتنظيمية للعاملين، والقدرة على إجراءات البحوث من أجل القيام بالمهام الموكلة إليها، وذلك وفقاً لمعايير الحد الأدنى التي تنطبق على هيئات التصنيف المعتمدة التي تعمل نيابة عنها، على النحو المنصوص عليه في منهجية الاعتماد والإشراف والتدقيق على هيئات التصنيف المعتمدة من قبل الهيئة.",
      "status": "active",
      "paragraphs": [
        {
          "marker": "",
          "text": "المادة الخامسة:  القدرات الفنية والتنظيمية",
          "level": 0
        },
        {
          "marker": "",
          "text": "على الهيئة التأكد من أن لدى هيئة التصنيف المواد والمصادر الكافية من حيث القدرات والخبرات الفنية والتنظيمية للعاملين، والقدرة على إجراءات البحوث من أجل القيام بالمهام الموكلة إليها، وذلك وفقاً لمعايير الحد الأدنى التي تنطبق على هيئات التصنيف المعتمدة التي تعمل نيابة عنها، على النحو المنصوص عليه في منهجية الاعتماد والإشراف والتدقيق على هيئات التصنيف المعتمدة من قبل الهيئة.",
          "level": 0
        }
      ],
      "amendments": [],
      "heading_context": []
    },
    {
      "number": 6,
      "number_text": "المادة السادسة",
      "text": "المادة السادسة:  الرقابة والإشراف\nتقوم الهيئة بالرقابة والإشراف على عمل هيئات التصنيف الدولية المفوضة بالقيام بأعمال الفحص والمعاينة للسفن، وإصدار الشهادات، وتقديم الخدمات نيابة عنها بشكل دوري أو متى دعت الحاجة إلى ذلك عن طريق الآتي:\n1- التحقق من امتثالها لمتطلبات المدونة والمتطلبات الوطنية من خلال التدقيق عليها من قبل المختصين في الهيئة.\n2- مطابقة الشهادات الصادرة لما هو منصوص عليه بأحكام الصكوك الدولية البحرية، الصادرة عن المنظمة ومدى مطابقة البيانات والمعلومات الواردة بالشهادة مع السفينة.\n3- متابعة إصدار الشهادات الإلزامية الصادرة من هيئات التصنيف وفق ما يصدر من المنظمة.\n4- متابعة الحالة الفنية للسفينة من خلال تقارير هيئات التصنيف.\n5- القيام بالتدقيق الإضافي عندما يتم احتجاز سفينة ترفع العلم السعودي من قبل دولة ميناء أو تعرضت لحادث جسيم أو حدث تعطل في محركاتها أو لأي سبب طارئ.\n6- متابعة حجز السفن السعودية في الموانئ الأجنبية والإجراءات المتخذة لمعالجة العيوب الفنية لرفع الحجز في أقل مدة ممكنة.\n7- القيام بالتدقيق الطارئ على أي من هيئات التصنيف المعتمدة للتحقق من استمرارية الامتثال لشروط ومتطلبات التفويض وتوفر الشروط والخبرات الفنية في العاملين المعتمدين من الهيئة.",
      "original_text": "المادة السادسة:  الرقابة والإشراف\nتقوم الهيئة بالرقابة والإشراف على عمل هيئات التصنيف الدولية المفوضة بالقيام بأعمال الفحص والمعاينة للسفن، وإصدار الشهادات، وتقديم الخدمات نيابة عنها بشكل دوري أو متى دعت الحاجة إلى ذلك عن طريق الآتي:\n1- التحقق من امتثالها لمتطلبات المدونة والمتطلبات الوطنية من خلال التدقيق عليها من قبل المختصين في الهيئة.\n2- مطابقة الشهادات الصادرة لما هو منصوص عليه بأحكام الصكوك الدولية البحرية، الصادرة عن المنظمة ومدى مطابقة البيانات والمعلومات الواردة بالشهادة مع السفينة.\n3- متابعة إصدار الشهادات الإلزامية الصادرة من هيئات التصنيف وفق ما يصدر من المنظمة.\n4- متابعة الحالة الفنية للسفينة من خلال تقارير هيئات التصنيف.\n5- القيام بالتدقيق الإضافي عندما يتم احتجاز سفينة ترفع العلم السعودي من قبل دولة ميناء أو تعرضت لحادث جسيم أو حدث تعطل في محركاتها أو لأي سبب طارئ.\n6- متابعة حجز السفن السعودية في الموانئ الأجنبية والإجراءات المتخذة لمعالجة العيوب الفنية لرفع الحجز في أقل مدة ممكنة.\n7- القيام بالتدقيق الطارئ على أي من هيئات التصنيف المعتمدة للتحقق من استمرارية الامتثال لشروط ومتطلبات التفويض وتوفر الشروط والخبرات الفنية في العاملين المعتمدين من الهيئة.",
      "status": "active",
      "paragraphs": [
        {
          "marker": "",
          "text": "المادة السادسة:  الرقابة والإشراف",
          "level": 0
        },
        {
          "marker": "",
          "text": "تقوم الهيئة بالرقابة والإشراف على عمل هيئات التصنيف الدولية المفوضة بالقيام بأعمال الفحص والمعاينة للسفن، وإصدار الشهادات، وتقديم الخدمات نيابة عنها بشكل دوري أو متى دعت الحاجة إلى ذلك عن طريق الآتي:",
          "level": 0
        },
        {
          "marker": "1-",
          "text": "التحقق من امتثالها لمتطلبات المدونة والمتطلبات الوطنية من خلال التدقيق عليها من قبل المختصين في الهيئة.",
          "level": 1
        },
        {
          "marker": "2-",
          "text": "مطابقة الشهادات الصادرة لما هو منصوص عليه بأحكام الصكوك الدولية البحرية، الصادرة عن المنظمة ومدى مطابقة البيانات والمعلومات الواردة بالشهادة مع السفينة.",
          "level": 1
        },
        {
          "marker": "3-",
          "text": "متابعة إصدار الشهادات الإلزامية الصادرة من هيئات التصنيف وفق ما يصدر من المنظمة.",
          "level": 1
        },
        {
          "marker": "4-",
          "text": "متابعة الحالة الفنية للسفينة من خلال تقارير هيئات التصنيف.",
          "level": 1
        },
        {
          "marker": "5-",
          "text": "القيام بالتدقيق الإضافي عندما يتم احتجاز سفينة ترفع العلم السعودي من قبل دولة ميناء أو تعرضت لحادث جسيم أو حدث تعطل في محركاتها أو لأي سبب طارئ.",
          "level": 1
        },
        {
          "marker": "6-",
          "text": "متابعة حجز السفن السعودية في الموانئ الأجنبية والإجراءات المتخذة لمعالجة العيوب الفنية لرفع الحجز في أقل مدة ممكنة.",
          "level": 1
        },
        {
          "marker": "7-",
          "text": "القيام بالتدقيق الطارئ على أي من هيئات التصنيف المعتمدة للتحقق من استمرارية الامتثال لشروط ومتطلبات التفويض وتوفر الشروط والخبرات الفنية في العاملين المعتمدين من الهيئة.",
          "level": 1
        }
      ],
      "amendments": [],
      "heading_context": []
    },
    {
      "number": 7,
      "number_text": "المادة السابعة",
      "text": "المادة السابعة:  إجراءات تقديم الطلب\nتقوم هيئة التصنيف بتقديم طلب التفويض عبر القنوات الرسمية للهيئة مرفقاً معه ما يثبت استيفاءها للشروط الواردة في هذه اللائحة.",
      "original_text": "المادة السابعة:  إجراءات تقديم الطلب\nتقوم هيئة التصنيف بتقديم طلب التفويض عبر القنوات الرسمية للهيئة مرفقاً معه ما يثبت استيفاءها للشروط الواردة في هذه اللائحة.",
      "status": "active",
      "paragraphs": [
        {
          "marker": "",
          "text": "المادة السابعة:  إجراءات تقديم الطلب",
          "level": 0
        },
        {
          "marker": "",
          "text": "تقوم هيئة التصنيف بتقديم طلب التفويض عبر القنوات الرسمية للهيئة مرفقاً معه ما يثبت استيفاءها للشروط الواردة في هذه اللائحة.",
          "level": 0
        }
      ],
      "amendments": [],
      "heading_context": []
    },
    {
      "number": 8,
      "number_text": "المادة الثامنة",
      "text": "المادة الثامنة:  إجراءات تفويض هيئات التصنيف\nبعد تقديم الطلب الرسمي من هيئة التصنيف للقيام بأعمال إصدار الشهادات وتقديم الخدمات نيابة عن الهيئة، تقوم الهيئة بدراسة الطلب الرسمي ومن ثم تفويض هيئة التصنيف بعد التحقق من الآتي:\nامتثال هيئة التصنيف لكافة الشروط والمتطلبات اللازمة للتفويض الوارد ذكرها في",
      "original_text": "المادة الثامنة:  إجراءات تفويض هيئات التصنيف\nبعد تقديم الطلب الرسمي من هيئة التصنيف للقيام بأعمال إصدار الشهادات وتقديم الخدمات نيابة عن الهيئة، تقوم الهيئة بدراسة الطلب الرسمي ومن ثم تفويض هيئة التصنيف بعد التحقق من الآتي:\nامتثال هيئة التصنيف لكافة الشروط والمتطلبات اللازمة للتفويض الوارد ذكرها في",
      "status": "active",
      "paragraphs": [
        {
          "marker": "",
          "text": "المادة الثامنة:  إجراءات تفويض هيئات التصنيف",
          "level": 0
        },
        {
          "marker": "",
          "text": "بعد تقديم الطلب الرسمي من هيئة التصنيف للقيام بأعمال إصدار الشهادات وتقديم الخدمات نيابة عن الهيئة، تقوم الهيئة بدراسة الطلب الرسمي ومن ثم تفويض هيئة التصنيف بعد التحقق من الآتي:",
          "level": 0
        },
        {
          "marker": "",
          "text": "امتثال هيئة التصنيف لكافة الشروط والمتطلبات اللازمة للتفويض الوارد ذكرها في",
          "level": 0
        }
      ],
      "amendments": [],
      "heading_context": []
    },
    {
      "number": 9,
      "number_text": "المادة التاسعة",
      "text": "المادة الرابعة .\nامتثال هيئة التصنيف للمتطلبات الوارد ذكرها في مدونة الهيئات المعتمدة والمتطلبات الوطنية، وذلك من خلال التدقيق الميداني لفرع هيئة التصنيف بالمملكة من قبل المختصين بالهيئة، وفي حال عدم وجود فرع لهيئة التصنيف بالمملكة يتم التدقيق على المقر الإقليمي لها بالمنطقة.",
      "original_text": "المادة الرابعة .\nامتثال هيئة التصنيف للمتطلبات الوارد ذكرها في مدونة الهيئات المعتمدة والمتطلبات الوطنية، وذلك من خلال التدقيق الميداني لفرع هيئة التصنيف بالمملكة من قبل المختصين بالهيئة، وفي حال عدم وجود فرع لهيئة التصنيف بالمملكة يتم التدقيق على المقر الإقليمي لها بالمنطقة.",
      "status": "active",
      "paragraphs": [
        {
          "marker": "",
          "text": "المادة الرابعة .",
          "level": 0
        },
        {
          "marker": "",
          "text": "امتثال هيئة التصنيف للمتطلبات الوارد ذكرها في مدونة الهيئات المعتمدة والمتطلبات الوطنية، وذلك من خلال التدقيق الميداني لفرع هيئة التصنيف بالمملكة من قبل المختصين بالهيئة، وفي حال عدم وجود فرع لهيئة التصنيف بالمملكة يتم التدقيق على المقر الإقليمي لها بالمنطقة.",
          "level": 0
        }
      ],
      "amendments": [],
      "heading_context": []
    },
    {
      "number": 10,
      "number_text": "المادة العاشرة",
      "text": "المادة التاسعة:  اتفاقية تفويض هيئات التصنيف\nبعد استيفاء هيئات التصنيف شروط تفويضها يحق للهيئة إبرام اتفاقية تفويض مع هيئة التصنيف للقيام بأعمال إصدار الشهادات وتقديم الخدمات للسفن التي ترفع العلم السعودي.\nيجوز للهيئة تجديد اتفاقية التفويض مع هيئة التصنيف في حال استمرار استيفائها لشروط تفويضها.\nوللرئيس توقيع اتفاقية التفويض مع هيئات التصنيف المؤهلة، على أن تراعي العقود المتطلبات الواردة في المادة (الرابعة) من هذه اللائحة، وفي حال الإخلال بأي متطلب تخطر الهيئة هيئة التصنيف المفوضة بطلب الالتزام خلال مدة لا تتجاوز (30) يوماً، وفي حال عدم الامتثال يعد العقد ملغى.",
      "original_text": "المادة التاسعة:  اتفاقية تفويض هيئات التصنيف\nبعد استيفاء هيئات التصنيف شروط تفويضها يحق للهيئة إبرام اتفاقية تفويض مع هيئة التصنيف للقيام بأعمال إصدار الشهادات وتقديم الخدمات للسفن التي ترفع العلم السعودي.\nيجوز للهيئة تجديد اتفاقية التفويض مع هيئة التصنيف في حال استمرار استيفائها لشروط تفويضها.\nوللرئيس توقيع اتفاقية التفويض مع هيئات التصنيف المؤهلة، على أن تراعي العقود المتطلبات الواردة في المادة (الرابعة) من هذه اللائحة، وفي حال الإخلال بأي متطلب تخطر الهيئة هيئة التصنيف المفوضة بطلب الالتزام خلال مدة لا تتجاوز (30) يوماً، وفي حال عدم الامتثال يعد العقد ملغى.",
      "status": "active",
      "paragraphs": [
        {
          "marker": "",
          "text": "المادة التاسعة:  اتفاقية تفويض هيئات التصنيف",
          "level": 0
        },
        {
          "marker": "",
          "text": "بعد استيفاء هيئات التصنيف شروط تفويضها يحق للهيئة إبرام اتفاقية تفويض مع هيئة التصنيف للقيام بأعمال إصدار الشهادات وتقديم الخدمات للسفن التي ترفع العلم السعودي.",
          "level": 0
        },
        {
          "marker": "",
          "text": "يجوز للهيئة تجديد اتفاقية التفويض مع هيئة التصنيف في حال استمرار استيفائها لشروط تفويضها.",
          "level": 0
        },
        {
          "marker": "",
          "text": "وللرئيس توقيع اتفاقية التفويض مع هيئات التصنيف المؤهلة، على أن تراعي العقود المتطلبات الواردة في المادة (الرابعة) من هذه اللائحة، وفي حال الإخلال بأي متطلب تخطر الهيئة هيئة التصنيف المفوضة بطلب الالتزام خلال مدة لا تتجاوز (30) يوماً، وفي حال عدم الامتثال يعد العقد ملغى.",
          "level": 0
        }
      ],
      "amendments": [],
      "heading_context": []
    },
    {
      "number": 11,
      "number_text": "المادة الحادية عشرة",
      "text": "المادة العاشرة:  إلغاء أو تعليق التفويض\nللهيئة إلغاء أو تعليق التفويض أو الإنذار بذلك في حال عدم استيفاء هيئة التصنيف الحد الأدنى من الشروط المنصوص عليها في",
      "original_text": "المادة العاشرة:  إلغاء أو تعليق التفويض\nللهيئة إلغاء أو تعليق التفويض أو الإنذار بذلك في حال عدم استيفاء هيئة التصنيف الحد الأدنى من الشروط المنصوص عليها في",
      "status": "active",
      "paragraphs": [
        {
          "marker": "",
          "text": "المادة العاشرة:  إلغاء أو تعليق التفويض",
          "level": 0
        },
        {
          "marker": "",
          "text": "للهيئة إلغاء أو تعليق التفويض أو الإنذار بذلك في حال عدم استيفاء هيئة التصنيف الحد الأدنى من الشروط المنصوص عليها في",
          "level": 0
        }
      ],
      "amendments": [],
      "heading_context": []
    },
    {
      "number": 12,
      "number_text": "المادة الثانية عشرة",
      "text": "المادة الرابعة  أو متى ما دعت الحاجة لذلك.",
      "original_text": "المادة الرابعة  أو متى ما دعت الحاجة لذلك.",
      "status": "active",
      "paragraphs": [
        {
          "marker": "",
          "text": "المادة الرابعة  أو متى ما دعت الحاجة لذلك.",
          "level": 0
        }
      ],
      "amendments": [],
      "heading_context": []
    },
    {
      "number": 13,
      "number_text": "المادة الثالثة عشرة",
      "text": "المادة الحادية عشرة:  الهيئات المفوضة.\nيصدر بقرار من الرئيس جدول يتضمن هيئات التصنيف المفوضة من الهيئة.",
      "original_text": "المادة الحادية عشرة:  الهيئات المفوضة.\nيصدر بقرار من الرئيس جدول يتضمن هيئات التصنيف المفوضة من الهيئة.",
      "status": "active",
      "paragraphs": [
        {
          "marker": "",
          "text": "المادة الحادية عشرة:  الهيئات المفوضة.",
          "level": 0
        },
        {
          "marker": "",
          "text": "يصدر بقرار من الرئيس جدول يتضمن هيئات التصنيف المفوضة من الهيئة.",
          "level": 0
        }
      ],
      "amendments": [],
      "heading_context": []
    },
    {
      "number": 14,
      "number_text": "المادة الرابعة عشرة",
      "text": "المادة الثانية  عشرة: سريان اللائحة\nتُنشر هذه اللائحة في الجريدة الرسمية ويُعمل بها من تاريخ نشرها.",
      "original_text": "المادة الثانية  عشرة: سريان اللائحة\nتُنشر هذه اللائحة في الجريدة الرسمية ويُعمل بها من تاريخ نشرها.",
      "status": "active",
      "paragraphs": [
        {
          "marker": "",
          "text": "المادة الثانية  عشرة: سريان اللائحة",
          "level": 0
        },
        {
          "marker": "",
          "text": "تُنشر هذه اللائحة في الجريدة الرسمية ويُعمل بها من تاريخ نشرها.",
          "level": 0
        }
      ],
      "amendments": [],
      "heading_context": []
    }
  ]
}